Workbook
Name s: [30]梁!$X1*1.2
Name \q: #REF!
Name _001年.xls: #REF!
Name __________TP5125: [1]材料!$F$7
Name _: #REF!
Name page1: #N/A
Name lap: [2]General!$B$2:$G$9
Name A_1: "$"
Name A_1___1: "$"
Name CGFS000001: [3]下拉!$H$3:$H$159
Name GLLB_A: [3]下拉!$D$3:$D$8
Name A_1___2: "$"
Name A_1___4: "$"
Name A_2: "$"
Name A_1___0: "$"
Name A_2___0: "$"
Name ___xlfn_FINV: #N/A
Name __xlfn_FINV: #N/A
Name _4_4.2_0.1_3.8_4__0.6_0.14: [4]土方!#REF!
Name _ae1: '[5]21'!$B$1:$B$802
Name _W200: '[7]21'!$B$1:$B$802
Name _xlfn_FINV: #N/A
Name a: NA()
Name A_2___1: "$"
Name A_2___2: "$"
Name A_2___4: "$"
Name A_5: "$"
Name A_6: "$"
Name aaaa: EVALUATE([8]工程量A6!XFD1)
Name AccountBase: [9]貨品科目!$B$5:$E$857
Name ad: '[10]21'!$A$1:$A$802
Name ae: '[10]21'!$B$1:$B$802
Name B_1: "$"
Name B_1___0: "$"
Name B_1___1: "$"
Name B_1___2: "$"
Name B_1___4: "$"
Name B_2: "$"
Name B_2___0: "$"
Name B_2___1: "$"
Name B_2___2: "$"
Name B_2___4: "$"
Name B01_: "$"
Name B01____0: "$"
Name B01____1: "$"
Name B01____2: "$"
Name B01____4: "$"
Name B02_: "$"
Name B02____0: "$"
Name B02____1: "$"
Name B02____2: "$"
Name B02____4: "$"
Name B03_: "$"
Name B03____0: "$"
Name B03____1: "$"
Name B03____2: "$"
Name B03____4: "$"
Name B04_: "$"
Name B04____0: "$"
Name B04____1: "$"

Sheet 汇总表
A1: 成华区迎晖路194号住宅、商业及配套设施项目幕墙工程成本汇总表
A2: 序号 | B2: 项目名称 | C2: 暂估幕墙面积 （㎡） | D2: 含税总价 （元） | E2: 含税单方造价 （元/㎡） | F2: 备注 | J2: 人数 | K2: 工资 | L2: 工期 | M2: 小计
A3: 1 | B3: 排屋幕墙 | C3: =排屋工程量清单!D118*11 -> 40189.114 | D3: =排屋工程量清单!G118*11 -> 37681753 | E3: =D3/C3 -> 937.61092 | F3: 图纸不齐，工程量暂定 | I3: 项目经理 | J3: 1 | K3: 16000 | L3: 24 | M3: =L3*K3*J3 -> 384000
A4: 2 | B4: 1#2#商业幕墙 | C4: ='商业工程量清单 '!D104 -> 8319.4105 | D4: ='商业工程量清单 '!G104 -> 7934002.9 | E4: =D4/C4 -> 953.67369 | I4: 技术负责人 | J4: 1 | K4: 13000 | L4: 16 | M4: =L4*K4*J4 -> 208000
A5: 3 | B5: 1#2#塔楼 | C5: 30816.26 | D5: =[117]塔楼报价汇总!$G$30 -> 37494777 | E5: =D5/C5 -> 1216.7206 | F5: 图纸不齐，工程量暂定 | I5: 幕墙设计 | J5: 2 | K5: 13000 | L5: 16 | M5: =L5*K5*J5 -> 416000
A6: 4 | B6: 暂定管理人员工资 | D6: =M14 -> 2165000 | F6: 最终据实统计 | G6: =D6/D13 -> 0.025137725 | I6: 施工员 | J6: 1 | K6: 9000 | L6: 16 | M6: =L6*K6*J6 -> 144000
A7: 5 | B7: 暂定差旅费 | D7: 150000 | F7: 最终据实统计 | G7: =D7/D13 -> 0.0017416438 | I7: 安全员 | J7: 1 | K7: 9000 | L7: 16 | M7: =L7*K7*J7 -> 144000
A8: 6 | B8: 暂定办公费用 | D8: 50000 | F8: 最终据实统计 | G8: =D8/D13 -> 0.00058054793 | I8: 材料员 | J8: 1 | K8: 8000 | L8: 8 | M8: =L8*K8*J8 -> 64000
A9: 7 | B9: 暂定房租 | D9: 80000 | F9: 最终据实统计 | G9: =D9/D13 -> 0.00092887669 | I9: 库管 | J9: 1 | K9: 5000 | L9: 16 | M9: =L9*K9*J9 -> 80000
A10: 8 | B10: 暂定检测费 | D10: 450000 | F10: 最终据实统计 | G10: =D10/D13 -> 0.0052249314 | I10: 劳务资料员 | J10: 1 | K10: 8000 | L10: 16 | M10: =L10*K10*J10 -> 128000
A11: 9 | B11: 过节招待费 | D11: 120000 | F11: 最终据实统计 | G11: =D11/D13 -> 0.001393315 | I11: 质量员 | J11: 1 | K11: 12000 | L11: 16 | M11: =L11*K11*J11 -> 192000
I12: 商务 | J12: 1 | K12: 15000 | L12: 24 | M12: =L12*K12*J12 -> 360000
B13: 合计 | C13: =SUM(C3:C5) -> 79324.785 | D13: =SUM(D3:D12) -> 86125533 | G13: =D13/C13 -> 1085.733 | I13: 监理 | J13: 1 | K13: 2500 | L13: 18 | M13: =L13*K13*J13 -> 45000
I14: 合计 | J14: =SUM(J3:J13) -> 12 | M14: =SUM(M3:M13) -> 2165000

Sheet 排屋工程量清单
A1: 成都塔子山11#楼工程量清单（成本）
A2: 序号 | B2: 项目名称 | C2: 部位 | D2: 工程量 | E2: 单位 | F2: 含税单价（元） | G2: 含税合价（元） | H2: 备注
A3: 一 | B3: 80系列断桥隔热铝合金窗 | D3: =SUM(D4:D21) -> 115.204 | G3: =SUM(G4:G21) -> 86828.226
A4: 1 | B4: LMC6117G | D4: =4.05*1.75*2 -> 14.175 | E4: m2 | F4: =VLOOKUP(B4,'综合单价分析表 (11#楼)'!A:I,9,) -> 808.61369 | G4: =+F4*D4 -> 11462.099
A5: =MAX($A$3:$A4)+1 -> 2 | B5: LC1227 | D5: =1.1*1.75*2 -> 3.85 | E5: m2 | F5: =F4 -> 808.61369 | G5: =+F5*D5 -> 3113.1627
A6: =MAX($A$3:$A5)+1 -> 3 | B6: LMC4517G | D6: =2.55*1.75 -> 4.4625 | E6: m2 | F6: =F4 -> 808.61369 | G6: =+F6*D6 -> 3608.4386
A7: =MAX($A$3:$A6)+1 -> 4 | B7: LC4107C | D7: =4.05*0.75 -> 3.0375 | E7: m2 | F7: =F4 -> 808.61369 | G7: =+F7*D7 -> 2456.1641
A8: =MAX($A$3:$A7)+1 -> 5 | B8: LC6321/LC631反 | D8: =6.2*2*2 -> 24.8 | E8: m2 | F8: =F4 -> 808.61369 | G8: =+F8*D8 -> 20053.619
A9: =MAX($A$3:$A8)+1 -> 6 | B9: LC0717C | D9: =0.75*1.75*3 -> 3.9375 | E9: m2 | F9: =F4 -> 808.61369 | G9: =+F9*D9 -> 3183.9164
B10: LC0617B | D10: =0.75*1.75*3 -> 3.9375 | E10: m2 | F10: =F4 -> 808.61369 | G10: =+F10*D10 -> 3183.9164
A11: =MAX($A$3:$A9)+1 -> 7 | B11: LC5121(平开窗) | C11: 5+12A+5㎜钢化中空玻璃 | D11: =5*2 -> 10 | E11: m2 | F11: =F4 -> 808.61369 | G11: =+F11*D11 -> 8086.1369 | H11: 地下室夹层
A12: =MAX($A$3:$A11)+1 -> 8 | B12: LC1015B(平开窗) | C12: 5+12A+5㎜钢化中空玻璃 | D12: =1*1.55*2 -> 3.1 | E12: m2 | F12: =F11 -> 808.61369 | G12: =+F12*D12 -> 2506.7024 | H12: 地下室夹层
A13: =MAX($A$3:$A12)+1 -> 9 | B13: LC1015C(平开窗) | C13: 5+12A+5㎜钢化中空玻璃 | D13: =1.05*1.5 -> 1.575 | E13: m2 | F13: =F11 -> 808.61369 | G13: =+F13*D13 -> 1273.5666 | H13: 地下室夹层
A14: =MAX($A$3:$A13)+1 -> 10 | B14: LC3023(固定窗) | C14: 12+12A+12㎜钢化中空玻璃 | D14: =3*2.3 -> 6.9 | E14: m2 | F14: 600 | G14: =+F14*D14 -> 4140 | H14: 地下室夹层
A15: =MAX($A$3:$A14)+1 -> 11 | B15: LC1215C(平开窗) | C15: 5+12A+5㎜钢化中空玻璃 | D15: =1.25*1.55 -> 1.9375 | E15: m2 | F15: =F11 -> 808.61369 | G15: =+F15*D15 -> 1566.689 | H15: 地下室夹层
A16: =MAX($A$3:$A15)+1 -> 12 | B16: TLM3123(推拉门) | C16: 6+12A+6㎜钢化中空玻璃 | D16: =3.1*2.3 -> 7.13 | E16: m2 | F16: =F4 -> 808.61369 | G16: =+F16*D16 -> 5765.4156 | H16: 地下室夹层
A17: =MAX($A$3:$A16)+1 -> 13 | B17: LC0823A(固定窗) | C17: 5+12A+5㎜钢化中空玻璃 | D17: =0.85*2.3 -> 1.955 | E17: m2 | F17: =F14 -> 600 | G17: =+F17*D17 -> 1173 | H17: 地下室夹层
A18: =MAX($A$3:$A17)+1 -> 14 | B18: LC2421A(固定窗) | C18: 12+12A+12㎜钢化中空玻璃 | D18: =2.55*2.15 -> 5.4825 | E18: m2 | F18: =F14 -> 600 | G18: =+F18*D18 -> 3289.5 | H18: 地下室一层
A19: =MAX($A$3:$A18)+1 -> 15 | B19: LC0913X(固定窗) | C19: 5+12A+5㎜钢化中空玻璃 | D19: =0.95*1.345 -> 1.27775 | E19: m2 | F19: =F14 -> 600 | G19: =+F19*D19 -> 766.65 | H19: 地下室一层
A20: =MAX($A$3:$A19)+1 -> 16 | B20: LC2754B(固定窗) | C20: 15+12A+15㎜钢化中空玻璃 | D20: =2.7*5.45 -> 14.715 | E20: m2 | F20: =F14 -> 600 | G20: =+F20*D20 -> 8829 | H20: 地下室一层
A21: =MAX($A$3:$A20)+1 -> 17 | B21: TLM1223X(平开门) | C21: 5+12A+5㎜钢化中空玻璃 | D21: =1.25*2.345 -> 2.93125 | E21: m2 | F21: =F4 -> 808.61369 | G21: =+F21*D21 -> 2370.2489 | H21: 地下室一层
A22: 二 | B22: 幕墙式铝合金窗 | D22: =SUM(D23:D47) -> 515.11425 | G22: =SUM(G23:G47) -> 648486.36
A23: =MAX($A$3:$A22)+1 -> 18 | B23: LMC10425C | D23: =10.3*2.59 -> 26.677 | E23: m2 | F23: =VLOOKUP(B23,'综合单价分析表 (11#楼)'!A:I,9,) -> 1258.9175 | G23: =D23*F23 -> 33584.143 | H23: 系统门
A24: =MAX($A$3:$A23)+1 -> 19 | B24: LC4124X | D24: =4.162*(2.47+0.7) -> 13.19354 | E24: m2 | F24: =F23 -> 1258.9175 | G24: =D24*F24 -> 16609.579 | H24: 系统窗
A25: =MAX($A$3:$A24)+1 -> 20 | B25: LMC7825F | D25: =7.65*2.59 -> 19.8135 | E25: m2 | F25: =F23 -> 1258.9175 | G25: =D25*F25 -> 24943.562 | H25: 系统门
A26: =MAX($A$3:$A25)+1 -> 21 | B26: LC3724X | D26: =3.762*(2.47+0.7) -> 11.92554 | E26: m2 | F26: =F23 -> 1258.9175 | G26: =D26*F26 -> 15013.271 | H26: 系统窗
A27: =MAX($A$3:$A26)+1 -> 22 | B27: LMC10425F | D27: =10.3*2.59 -> 26.677 | E27: m2 | F27: =F23 -> 1258.9175 | G27: =D27*F27 -> 33584.143 | H27: 系统门
A28: =MAX($A$3:$A27)+1 -> 23 | B28: LC4024X | D28: =4.062*(2.47+0.7) -> 12.87654 | E28: m2 | F28: =F23 -> 1258.9175 | G28: =D28*F28 -> 16210.502 | H28: 系统窗
A29: =MAX($A$3:$A28)+1 -> 24 | B29: LC2822A/LC2822A反 | D29: =2.86*2.22*2 -> 12.6984 | E29: m2 | F29: =F23 -> 1258.9175 | G29: =D29*F29 -> 15986.238 | H29: 系统窗
A30: =MAX($A$3:$A29)+1 -> 25 | B30: LMC13726X/LMC13726X反 | D30: =13.714*2.71*2 -> 74.32988 | E30: m2 | F30: =F23 -> 1258.9175 | G30: =D30*F30 -> 93575.188 | H30: 系统门、系统窗
A31: =MAX($A$3:$A30)+1 -> 26 | B31: LMC4326X/LMC4326X反 | D31: =7.212*2.71*2 -> 39.08904 | E31: m2 | F31: =F23 -> 1258.9175 | G31: =D31*F31 -> 49209.877 | H31: 系统门
A32: =MAX($A$3:$A31)+1 -> 27 | B32: LC7326X | D32: =4.502*2.73 -> 12.29046 | E32: m2 | F32: =F23 -> 1258.9175 | G32: =D32*F32 -> 15472.675 | H32: 系统窗
A33: =MAX($A$3:$A32)+1 -> 28 | B33: LC8226X | D33: =7.913*2.71 -> 21.44423 | E33: m2 | F33: =F23 -> 1258.9175 | G33: =D33*F33 -> 26996.517 | H33: 系统门、系统窗
A34: =MAX($A$3:$A33)+1 -> 29 | B34: LC3126X | D34: =5.512*2.71 -> 14.93752 | E34: m2 | F34: =F23 -> 1258.9175 | G34: =D34*F34 -> 18805.106 | H34: 系统门
A35: =MAX($A$3:$A34)+1 -> 30 | B35: LC6526X | D35: =4.102*2.71 -> 11.11642 | E35: m2 | F35: =F23 -> 1258.9175 | G35: =D35*F35 -> 13994.656 | H35: 系统窗
A36: =MAX($A$3:$A35)+1 -> 31 | B36: LC4426X | D36: =4.402*2.73 -> 12.01746 | E36: m2 | F36: =F23 -> 1258.9175 | G36: =D36*F36 -> 15128.991 | H36: 系统窗
A37: =MAX($A$3:$A36)+1 -> 32 | B37: LC9325X/LC9325X反 | D37: =9.352*2.63*2 -> 49.19152 | E37: m2 | F37: =F23 -> 1258.9175 | G37: =D37*F37 -> 61928.067 | H37: 系统窗
A38: =MAX($A$3:$A37)+1 -> 33 | B38: LC1624H | D38: =1.61*2.52*3 -> 12.1716 | E38: m2 | F38: =F24 -> 1258.9175 | G38: =D38*F38 -> 15323.041 | H38: 固定窗
A39: =MAX($A$3:$A38)+1 -> 34 | B39: LC5726X | D39: =5.69*2.64 -> 15.0216 | E39: m2 | F39: =F25 -> 1258.9175 | G39: =D39*F39 -> 18910.955 | H39: 系统门
A40: =MAX($A$3:$A39)+1 -> 35 | B40: LC4425C | D40: =3.96*2.63 -> 10.4148 | E40: m2 | F40: =F23 -> 1258.9175 | G40: =D40*F40 -> 13111.374 | H40: 系统窗
A41: =MAX($A$3:$A40)+1 -> 36 | B41: LC4325B | D41: =4.19*2.64 -> 11.0616 | E41: m2 | F41: =F23 -> 1258.9175 | G41: =D41*F41 -> 13925.642 | H41: 系统门
A42: =MAX($A$3:$A41)+1 -> 37 | B42: LC6319/LC6319反 | D42: =6.2*1.8*2 -> 22.32 | E42: m2 | F42: =F23 -> 1258.9175 | G42: =D42*F42 -> 28099.039 | H42: 系统窗
A43: =MAX($A$3:$A42)+1 -> 38 | B43: LC5119 | D43: =5*1.9 -> 9.5 | E43: m2 | F43: =F23 -> 1258.9175 | G43: =D43*F43 -> 11959.716 | H43: 系统门
A44: =MAX($A$3:$A43)+1 -> 39 | B44: LC5826B | D44: =5.77*2.53 -> 14.5981 | E44: m2 | F44: =F23 -> 1258.9175 | G44: =D44*F44 -> 18377.804 | H44: 系统窗
A45: =MAX($A$3:$A44)+1 -> 40 | B45: LC5024X | D45: =5.072*2.49 -> 12.62928 | E45: m2 | F45: =F23 -> 1258.9175 | G45: =D45*F45 -> 15899.222 | H45: 系统门
A46: =MAX($A$3:$A45)+1 -> 41 | B46: LC4226X | D46: =4.27*2.53 -> 10.8031 | E46: m2 | F46: =F23 -> 1258.9175 | G46: =D46*F46 -> 13600.212 | H46: 系统窗
A47: =MAX($A$3:$A46)+1 -> 42 | B47: LC5724X/LC5724X反 | D47: =7.694*2.49*2 -> 38.31612 | E47: m2 | F47: =F23 -> 1258.9175 | G47: =D47*F47 -> 48236.835 | H47: 系统门
A48: 三 | B48: 石材幕墙 | D48: =SUM(D49:D57) -> 511.91876 | G48: =SUM(G49:G57) -> 613586.53
A49: 1 | B49: 25㎜葡萄牙灰石材 | C49: 基座 | D49: =SUMIF('工程量计算式 (11#楼)'!A:A,B49,'工程量计算式 (11#楼)'!E:E) -> 67.8042 | E49: m2 | F49: =VLOOKUP(B49,'综合单价分析表 (11#楼)'!A:I,9,) -> 1214.5453 | G49: =D49*F49 -> 82351.275
A50: 2 | B50: 25㎜葡萄牙灰石材（圆弧） | C50: 基座 | D50: =D49*0.2 -> 13.56084 | E50: m2 | F50: =VLOOKUP(B50,'综合单价分析表 (11#楼)'!A:I,9,) -> 2277.5055 | G50: =D50*F50 -> 30884.887
A51: 3 | B51: 25㎜葡萄牙米黄石材 | C51: 南立面、东西立面一层墙面、南立面二层玻璃栏杆下 | D51: =SUMIF('工程量计算式 (11#楼)'!A:A,B51,'工程量计算式 (11#楼)'!E:E) -> 134.7826 | E51: m2 | F51: =VLOOKUP(B51,'综合单价分析表 (11#楼)'!A:I,9,) -> 1275.1313 | G51: =D51*F51 -> 171865.52
A52: 4 | B52: 25㎜葡萄牙米黄石材（圆弧） | C52: 一层 | D52: =D51*0.2 -> 26.95652 | E52: m2 | F52: =VLOOKUP(B52,'综合单价分析表 (11#楼)'!A:I,9,) -> 2140.9579 | G52: =D52*F52 -> 57712.774
A53: 5 | B53: 25㎜葡萄牙米黄石材线条 | C53: 南立面二层 | D53: =SUMIF('工程量计算式 (11#楼)'!A:A,B53,'工程量计算式 (11#楼)'!E:E) -> 104.16 | E53: 米 | F53: =VLOOKUP(B53,'综合单价分析表 (11#楼)'!A:I,9,) -> 560.79409 | G53: =D53*F53 -> 58412.312
A54: 6 | B54: 35㎜蓝眼睛石材（凹槽） | C54: 南立面三层、四层 | D54: =SUMIF('工程量计算式 (11#楼)'!A:A,B54,'工程量计算式 (11#楼)'!E:E) -> 60.33889 | E54: m2 | F54: =VLOOKUP(B54,'综合单价分析表 (11#楼)'!A:I,9,) -> 1186.3314 | G54: =D54*F54 -> 71581.922
A55: 7 | B55: 35㎜蓝眼睛石材（凹槽）圆弧 | C55: 南立面三层、四层 | D55: =D54*0.2 -> 12.067778 | E55: m2 | F55: =VLOOKUP(B55,'综合单价分析表 (11#楼)'!A:I,9,) -> 2481.9581 | G55: =D55*F55 -> 29951.72
A56: 8 | B56: 50㎜蓝眼睛石材（光面） | C56: 南立面 | D56: =SUMIF('工程量计算式 (11#楼)'!A:A,B56,'工程量计算式 (11#楼)'!E:E) -> 1.8606 | E56: m2 | F56: =VLOOKUP(B56,'综合单价分析表 (11#楼)'!A:I,9,) -> 1348.9353 | G56: =D56*F56 -> 2509.829 | H56: =_xlfn.DISPIMG("ID_569B452557F7446297ACB2A33D2215F8",1) -> =DISPIMG("ID_569B452557F7446297ACB2A33D2215F8",1)
A57: 9 | B57: 25㎜葡萄牙灰石材（下沉小院） | C57: 下沉小院 | D57: =SUMIF('工程量计算式 (11#楼)'!A:A,B57,'工程量计算式 (11#楼)'!E:E) -> 90.38733 | E57: m2 | F57: =VLOOKUP(B57,'综合单价分析表 (11#楼)'!A:I,9,) -> 1198.3571 | G57: =D57*F57 -> 108316.3 | J57: 工程量计算规则
A58: 四 | B58: 铝板幕墙 | D58: =SUM(D59:D85) -> 2217.7898 | G58: =SUM(G59:G85) -> 1536058.5 | H58: 造型多
A59: 1 | B59: 2.5㎜中灰色铝板1 | C59: 幕窗四周收边 | D59: =SUMIF('工程量计算式 (11#楼)'!A:A,B59,'工程量计算式 (11#楼)'!E:E)*J59 -> 140.88257 | E59: m2 | F59: =VLOOKUP(B59,'综合单价分析表 (11#楼)'!A:I,9,) -> 719.70173 | G59: =D59*F59 -> 101393.43 | H59: =_xlfn.DISPIMG("ID_D73F7EA642FF451C88734E9DFF731F7A",1) -> =DISPIMG("ID_D73F7EA642FF451C88734E9DFF731F7A",1) | J59: 1.2
A60: 2 | B60: 2.5㎜浅灰色铝板2（带弧形造型） | C60: 南北立面二层梁处,中灰色改浅灰色 | D60: =SUMIF('工程量计算式 (11#楼)'!A:A,B60,'工程量计算式 (11#楼)'!E:E)*J59 -> 120.5717 | E60: m2 | F60: =VLOOKUP(B60,'综合单价分析表 (11#楼)'!A:I,9,) -> 563.13721 | G60: =D60*F60 -> 67898.413
A61: 3 | B61: 2.5㎜浅灰色铝板3（一层墙面） | C61: 北立面一层墙面 | D61: =SUMIF('工程量计算式 (11#楼)'!A:A,B61,'工程量计算式 (11#楼)'!E:E)*J59 -> 192.94027 | E61: m2 | F61: =VLOOKUP(B61,'综合单价分析表 (11#楼)'!A:I,9,) -> 596.29401 | G61: =D61*F61 -> 115049.13 | H61: =_xlfn.DISPIMG("ID_2E381AB3AD474EA4B97F23891DFE8D95",1) -> =DISPIMG("ID_2E381AB3AD474EA4B97F23891DFE8D95",1)
A62: 4 | B62: 2.5㎜银灰色铝板（线条造型） | C62: 南、北立面三层、四层、五层线条造型，JD-117 | D62: =SUMIF('工程量计算式 (11#楼)'!A:A,B62,'工程量计算式 (11#楼)'!E:E)*J59 -> 392.1608 | E62: m2 | F62: =VLOOKUP(B62,'综合单价分析表 (11#楼)'!A:I,9,) -> 636.92022 | G62: =D62*F62 -> 249775.14
A63: 5 | B63: 2.5㎜银灰色铝板（弧形线条造型） | C63: 南、北立面三层、四层、五层线条造型 | D63: =SUMIF('工程量计算式 (11#楼)'!A:A,B63,'工程量计算式 (11#楼)'!E:E)*J59 -> 44.403168 | E63: m2 | F63: =VLOOKUP(B63,'综合单价分析表 (11#楼)'!A:I,9,) -> 1101.4956 | G63: =D63*F63 -> 48909.896
A64: 6 | B64: 2.5㎜香槟色铝单板 | C64: 南立面1-2轴三层造型 | D64: =SUMIF('工程量计算式 (11#楼)'!A:A,B64,'工程量计算式 (11#楼)'!E:E)*J59 -> 7.392 | E64: m2 | F64: =VLOOKUP(B64,'综合单价分析表 (11#楼)'!A:I,9,) -> 828.49013 | G64: =D64*F64 -> 6124.1991
A65: 7 | B65: 2.5㎜香槟色铝单板（弧形） | C65: 南立面1-2轴三层造型 | D65: =SUMIF('工程量计算式 (11#楼)'!A:A,B65,'工程量计算式 (11#楼)'!E:E)*J59 -> 1.4304 | E65: m2 | F65: =VLOOKUP(B65,'综合单价分析表 (11#楼)'!A:I,9,) -> 873.40199 | G65: =D65*F65 -> 1249.3142
A66: 8 | B66: 4㎜香槟色穿孔铝单板（双层，内层1.5㎜镀锌钢板） | C66: 南立面1-2轴三层造型，JD-130，内侧1.5㎜镀锌钢板 | D66: =SUMIF('工程量计算式 (11#楼)'!A:A,B66,'工程量计算式 (11#楼)'!E:E)*J59 -> 209.4558 | E66: m2 | F66: =VLOOKUP(B66,'综合单价分析表 (11#楼)'!A:I,9,) -> 961.34049 | G66: =D66*F66 -> 201358.34 | H66: 300*200*12，6米19支
A67: 9 | B67: 4㎜香槟色穿孔铝单板（双层，内层1.5㎜镀锌钢板）弧形 | C67: 南立面1-2轴三层造型，JD-130，内层1.5㎜镀锌钢板 | D67: =SUMIF('工程量计算式 (11#楼)'!A:A,B67,'工程量计算式 (11#楼)'!E:E)*J59 -> 9.537192 | E67: m2 | F67: =VLOOKUP(B67,'综合单价分析表 (11#楼)'!A:I,9,) -> 1056.9325 | G67: =D67*F67 -> 10080.168
A68: 10 | B68: 4㎜香槟色穿孔铝单板（双层，内层2.5㎜中灰色铝单板） | C68: 北立面，立面双层（内层2.5㎜中灰色铝单板），JD-119 | D68: =SUMIF('工程量计算式 (11#楼)'!A:A,B68,'工程量计算式 (11#楼)'!E:E)*J59 -> 42.141 | E68: m2 | F68: =VLOOKUP(B68,'综合单价分析表 (11#楼)'!A:I,9,) -> 1006.6541 | G68: =D68*F68 -> 42421.411 | H68: =_xlfn.DISPIMG("ID_E142358DB9924EDFA0F9BD3F602E6265",1) -> =DISPIMG("ID_E142358DB9924EDFA0F9BD3F602E6265",1)
A69: 11 | B69: 浅灰色铝板1 | C69: 四层玻璃栏杆下，JD-120；北立面二层梁 | D69: =SUMIF('工程量计算式 (11#楼)'!A:A,B69,'工程量计算式 (11#楼)'!E:E)*J59 -> 59.18964 | E69: m2 | F69: =VLOOKUP(B69,'综合单价分析表 (11#楼)'!A:I,9,) -> 598.64671 | G69: =D69*F69 -> 35433.683
A70: 12 | B70: 浅灰色铝板2（弧形） | C70: 四层玻璃栏杆下，JD-120；北立面二层梁 | D70: =SUMIF('工程量计算式 (11#楼)'!A:A,B70,'工程量计算式 (11#楼)'!E:E)*J59 -> 3.459024 | E70: m2 | F70: =VLOOKUP(B70,'综合单价分析表 (11#楼)'!A:I,9,) -> 663.76253 | G70: =D70*F70 -> 2295.9705
A71: 13 | B71: 屋面铝单板 | C71: 屋面铝板，浅灰/银灰 | D71: =SUMIF('工程量计算式 (11#楼)'!A:A,B71,'工程量计算式 (11#楼)'!E:E)*J59 -> 344.091 | E71: m2 | F71: =VLOOKUP(B71,'综合单价分析表 (11#楼)'!A:I,9,) -> 599.36204 | G71: =D71*F71 -> 206235.09
A72: 14 | B72: 浅灰色铝板4 | C72: 北立面格栅后铝单板，墙面，剖2/剖5，超长带圆弧 | D72: =SUMIF('工程量计算式 (11#楼)'!A:A,B72,'工程量计算式 (11#楼)'!E:E)*J59 -> 145.19292 | E72: m2 | F72: =VLOOKUP(B72,'综合单价分析表 (11#楼)'!A:I,9,) -> 616.38355 | G72: =D72*F72 -> 89494.528
A73: 15 | B73: 浅灰色瓦楞铝板 | C73: 东西立面，剖7 | D73: =SUMIF('工程量计算式 (11#楼)'!A:A,B73,'工程量计算式 (11#楼)'!E:E)*J59 -> 5.07936 | E73: m2 | F73: =VLOOKUP(B73,'综合单价分析表 (11#楼)'!A:I,9,) -> 731.4283 | G73: =D73*F73 -> 3715.1877
A74: 16 | B74: 双色铝板造型线条(中灰色/浅灰色) | C74: JD-106/107/109 | D74: =SUMIF('工程量计算式 (11#楼)'!A:A,B74,'工程量计算式 (11#楼)'!E:E)*J59 -> 103.65942 | E74: m2 | F74: =VLOOKUP(B74,'综合单价分析表 (11#楼)'!A:I,9,) -> 698.21705 | G74: =D74*F74 -> 72376.777
A75: 17 | B75: 双色铝板造型线条(中灰色/浅灰色)弧形 | D75: =SUMIF('工程量计算式 (11#楼)'!A:A,B75,'工程量计算式 (11#楼)'!E:E)*J59 -> 5.029368 | E75: m2 | F75: =VLOOKUP(B75,'综合单价分析表 (11#楼)'!A:I,9,) -> 708.87281 | G75: =D75*F75 -> 3565.1822
A76: 18 | B76: 浅灰色铝板（包栏杆反坎） | C76: 南立面三层包反坎（玻璃栏杆处），JD-135，无龙骨 | D76: =SUMIF('工程量计算式 (11#楼)'!A:A,B76,'工程量计算式 (11#楼)'!E:E)*J59 -> 25.71036 | E76: m2 | F76: =VLOOKUP(B76,'综合单价分析表 (11#楼)'!A:I,9,) -> 512.48328 | G76: =D76*F76 -> 13176.13
A77: 19 | B77: 蓝眼睛仿石铝板（带圆弧，带拉槽） | C77: 北立面，JD-101/2、JD-113 | D77: =SUMIF('工程量计算式 (11#楼)'!A:A,B77,'工程量计算式 (11#楼)'!E:E)*J59 -> 49.2768 | E77: m2 | F77: =VLOOKUP(B77,'综合单价分析表 (11#楼)'!A:I,9,) -> 800.22356 | G77: =D77*F77 -> 39432.456
A78: 20 | B78: 蓝眼睛仿石铝板（四边带圆弧） | C78: 北立面，JD-101/1、JD-113 | D78: =SUMIF('工程量计算式 (11#楼)'!A:A,B78,'工程量计算式 (11#楼)'!E:E)*J59 -> 34.25784 | E78: m2 | F78: =VLOOKUP(B78,'综合单价分析表 (11#楼)'!A:I,9,) -> 634.56541 | G78: =D78*F78 -> 21738.84 | H78: =_xlfn.DISPIMG("ID_8B9A1073B072495C8621B34233F2D9F3",1) -> =DISPIMG("ID_8B9A1073B072495C8621B34233F2D9F3",1)
A79: 21 | B79: 葡萄牙米黄仿石铝板（瓦楞板） | C79: 北立面，剖3，JD-109、JD-110 | D79: =SUMIF('工程量计算式 (11#楼)'!A:A,B79,'工程量计算式 (11#楼)'!E:E)*J59 -> 142.08653 | E79: m2 | F79: =VLOOKUP(B79,'综合单价分析表 (11#楼)'!A:I,9,) -> 739.3182 | G79: =D79*F79 -> 105047.16
A80: 22 | B80: 葡萄牙米黄仿石铝板（瓦楞板）弧形 | D80: =SUMIF('工程量计算式 (11#楼)'!A:A,B80,'工程量计算式 (11#楼)'!E:E)*J59 -> 12.425184 | E80: m2 | F80: =VLOOKUP(B80,'综合单价分析表 (11#楼)'!A:I,9,) -> 831.64012 | G80: =D80*F80 -> 10333.281
A81: 23 | B81: 2.5㎜银灰色铝板（双色线条造型）(中灰色/银灰色) | D81: =SUMIF('工程量计算式 (11#楼)'!A:A,B81,'工程量计算式 (11#楼)'!E:E)*J59 -> 69.088704 | E81: m2 | F81: =F74 -> 698.21705 | G81: =D81*F81 -> 48238.911
A82: 24 | B82: 2.5㎜银灰色铝板（双色线条造型）(中灰色/银灰色)弧形 | D82: =SUMIF('工程量计算式 (11#楼)'!A:A,B82,'工程量计算式 (11#楼)'!E:E)*J59 -> 8.74176 | E82: m2 | F82: =F75 -> 708.87281 | G82: =D82*F82 -> 6196.796
A83: 25 | B83: 双色铝板造型线条(中灰色/香槟色) | D83: =SUMIF('工程量计算式 (11#楼)'!A:A,B83,'工程量计算式 (11#楼)'!E:E)*J59 -> 34.021008 | E83: m2 | F83: =VLOOKUP(B83,'综合单价分析表 (11#楼)'!A:I,9,) -> 703.54493 | G83: =D83*F83 -> 23935.308
A84: 26 | B84: 双色铝板造型线条(中灰色/香槟色)弧形 | D84: =SUMIF('工程量计算式 (11#楼)'!A:A,B84,'工程量计算式 (11#楼)'!E:E) -> 1.50192 | E84: m2 | F84: =VLOOKUP(B84,'综合单价分析表 (11#楼)'!A:I,9,) -> 714.20069 | G84: =D84*F84 -> 1072.6723
A85: 27 | B85: 2.5㎜中灰色瓦楞板 | C85: 下沉小院 | D85: =SUMIF('工程量计算式 (11#楼)'!A:A,B85,'工程量计算式 (11#楼)'!E:E) -> 14.064 | E85: m2 | F85: =VLOOKUP(B85,'综合单价分析表 (11#楼)'!A:I,9,) -> 676.27335 | G85: =D85*F85 -> 9511.1084
A86: 五 | B86: 铝合金格栅 | D86: =SUM(D87:D90) -> 73.5481 | G86: =SUM(G87:G90) -> 49734.82
A87: 1 | B87: 铝合金格栅 | C87: 北立面，剖4 | D87: =SUMIF('工程量计算式 (11#楼)'!A:A,B87,'工程量计算式 (11#楼)'!E:E) -> 33.863 | E87: m2 | F87: =VLOOKUP(B87,'综合单价分析表 (11#楼)'!A:I,9,) -> 675.48581 | G87: =D87*F87 -> 22873.976
A88: 2 | B88: 设备平台铝合金格栅 | C88: 南立面，剖4， | D88: =SUMIF('工程量计算式 (11#楼)'!A:A,B88,'工程量计算式 (11#楼)'!E:E) -> 25.6221 | E88: m2 | F88: =VLOOKUP(B88,'综合单价分析表 (11#楼)'!A:I,9,) -> 683.02261 | G88: =D88*F88 -> 17500.474 | H88: =_xlfn.DISPIMG("ID_ED48176349D74ABFA520040B7216AE84",1) -> =DISPIMG("ID_ED48176349D74ABFA520040B7216AE84",1)
A89: 3 | B89: 屋面格栅 | D89: =SUMIF('工程量计算式 (11#楼)'!A:A,B89,'工程量计算式 (11#楼)'!E:E) -> 9.955 | E89: m2 | F89: =F87 -> 675.48581 | G89: =D89*F89 -> 6724.4612
A90: 4 | B90: 铝合金百叶 | C90: 西立面 | D90: =SUMIF('工程量计算式 (11#楼)'!A:A,B90,'工程量计算式 (11#楼)'!E:E) -> 4.108 | E90: m2 | F90: =VLOOKUP(B90,'综合单价分析表 (11#楼)'!A:I,9,) -> 641.65258 | G90: =D90*F90 -> 2635.9088 | H90: 取消
A91: 六 | B91: 铝合金线条 | D91: =SUM(D92:D102) -> 867.926 | G91: =SUM(G92:G102) -> 57575.405
A92: 1 | B92: 铝合金线条1（60*20） | C92: 北立面1-1剖 | D92: =SUMIF('工程量计算式 (11#楼)'!A:A,B92,'工程量计算式 (11#楼)'!E:E) -> 91.7 | E92: 米 | F92: =VLOOKUP(B92,'综合单价分析表 (11#楼)'!A:I,9,) -> 46.217995 | G92: =D92*F92 -> 4238.1902 | H92: =_xlfn.DISPIMG("ID_71A8B487DAA24C3A930445ACD3BEDE13",1) -> =DISPIMG("ID_71A8B487DAA24C3A930445ACD3BEDE13",1)
A93: 2 | B93: 铝合金线条2（44*40） | C93: 南立面9-9剖 | D93: =SUMIF('工程量计算式 (11#楼)'!A:A,B93,'工程量计算式 (11#楼)'!E:E) -> 28.49 | E93: 米 | F93: =VLOOKUP(B93,'综合单价分析表 (11#楼)'!A:I,9,) -> 49.711681 | G93: =D93*F93 -> 1416.2858
A94: 3 | B94: 铝合金线条3（20*30） | C94: 北立面1-1剖 | D94: =SUMIF('工程量计算式 (11#楼)'!A:A,B94,'工程量计算式 (11#楼)'!E:E) -> 10.65 | E94: 米 | F94: =VLOOKUP(B94,'综合单价分析表 (11#楼)'!A:I,9,) -> 36.799488 | G94: =D94*F94 -> 391.91454 | H94: =_xlfn.DISPIMG("ID_6AFE38AF985F4ACFB0D387BDC0CA5874",1) -> =DISPIMG("ID_6AFE38AF985F4ACFB0D387BDC0CA5874",1)
A95: 4 | B95: 铝合金线条4（30*30） | C95: 浅灰色，北立面浅灰色铝板外竖向线条，JD-103 | D95: =SUMIF('工程量计算式 (11#楼)'!A:A,B95,'工程量计算式 (11#楼)'!E:E) -> 257.04 | E95: 米 | F95: =VLOOKUP(B95,'综合单价分析表 (11#楼)'!A:I,9,) -> 39.387638 | G95: =D95*F95 -> 10124.198 | H95: =_xlfn.DISPIMG("ID_A360F600B8BA457595AD314BCFE242DC",1) -> =DISPIMG("ID_A360F600B8BA457595AD314BCFE242DC",1)
A96: 5 | B96: 铝合金线条5（80*50） | C96: 浅灰色铝板造型上 | D96: =SUMIF('工程量计算式 (11#楼)'!A:A,B96,'工程量计算式 (11#楼)'!E:E) -> 66.86 | E96: 米 | F96: =VLOOKUP(B96,'综合单价分析表 (11#楼)'!A:I,9,) -> 52.637111 | G96: =D96*F96 -> 3519.3173 | H96: =_xlfn.DISPIMG("ID_C0160DC06BE349C08A1A0D359A28F6BB",1) -> =DISPIMG("ID_C0160DC06BE349C08A1A0D359A28F6BB",1)
A97: 6 | B97: 铝合金线条6（150*60） | C97: 银灰色铝板造型上 | D97: =SUMIF('工程量计算式 (11#楼)'!A:A,B97,'工程量计算式 (11#楼)'!E:E) -> 237.066 | E97: 米 | F97: =VLOOKUP(B97,'综合单价分析表 (11#楼)'!A:I,9,) -> 111.20551 | G97: =D97*F97 -> 26363.046 | H97: =_xlfn.DISPIMG("ID_24210E999789430A94456F346736D14C",1) -> =DISPIMG("ID_24210E999789430A94456F346736D14C",1)
A98: 7 | B98: 铝合金线条7（80*50）圆弧 | C98: 浅灰色铝板造型上 | D98: =SUMIF('工程量计算式 (11#楼)'!A:A,B98,'工程量计算式 (11#楼)'!E:E) -> 5.656 | E98: 米 | F98: =VLOOKUP(B98,'综合单价分析表 (11#楼)'!A:I,9,) -> 65.64056 | G98: =D98*F98 -> 371.26301
A99: 8 | B99: 铝合金线条8（150*60）圆弧 | C99: 银灰色铝板造型上 | D99: =SUMIF('工程量计算式 (11#楼)'!A:A,B99,'工程量计算式 (11#楼)'!E:E) -> 14.444 | E99: 米 | F99: =VLOOKUP(B99,'综合单价分析表 (11#楼)'!A:I,9,) -> 155.66841 | G99: =D99*F99 -> 2248.4744
A100: 9 | B100: 铝合金线条9（50*40）香槟色 | C100: 香槟色铝板造型上9-9剖 | D100: =SUMIF('工程量计算式 (11#楼)'!A:A,B100,'工程量计算式 (11#楼)'!E:E) -> 117.796 | E100: 米 | F100: =VLOOKUP(B100,'综合单价分析表 (11#楼)'!A:I,9,) -> 59.08006 | G100: =D100*F100 -> 6959.3948 | H100: =_xlfn.DISPIMG("ID_44FB857AADD14F3AB8D763643937D28F",1) -> =DISPIMG("ID_44FB857AADD14F3AB8D763643937D28F",1)
...

Sheet 商业工程量清单 
A1: 成都塔子山1#2#商业工程量清单（成本）
A2: 序号 | B2: 项目名称 | C2: 部位 | D2: 工程量 | E2: 单位 | F2: 含税单价（元） | G2: 含税合价（元） | H2: 备注
A3: 一 | B3: 玻璃幕墙 | D3: =SUM(D4:D43) -> 1528.5488 | G3: =SUM(G4:G43) -> 1931614 | J3: ='工程量计算式（商业）'!E2 -> 1528.5488 | K3: =D3-J3 -> 0
A4: 1 | B4: 首层座槽式玻璃幕墙（15+2.25SGP+15㎜全超白钢化夹层玻璃）（超宽） | C4: 1#楼南立面2/01~1/01轴 | D4: =SUMIF('工程量计算式（商业）'!A:A,B4,'工程量计算式（商业）'!E:E) -> 25.92 | E4: m2 | F4: =VLOOKUP(B4,'综合单价分析表（商业）'!A:I,9,) -> 1800.8283 | G4: =+F4*D4 -> 46677.469
A5: =MAX($A$3:$A4)+1 -> 2 | B5: 首层座槽式玻璃幕墙（12Low-E(双银)+12A+12全超白钢化中空玻璃） | C5: 1#楼南立面1~2轴 | D5: =SUMIF('工程量计算式（商业）'!A:A,B5,'工程量计算式（商业）'!E:E) -> 10.98 | E5: m2 | F5: =VLOOKUP(B5,'综合单价分析表（商业）'!A:I,9,) -> 617.41484 | G5: =+F5*D5 -> 6779.215
A6: =MAX($A$3:$A5)+1 -> 3 | B6: 首层座槽式玻璃幕墙（12Low-E(双银)+12A+12全超白钢化中空玻璃）（直+弯弧）（直段宽度300㎜+弧长942㎜，圆弧半径600㎜，高3600㎜） | C6: 1#楼南立面2/01~1/01轴 | D6: =SUMIF('工程量计算式（商业）'!A:A,B6,'工程量计算式（商业）'!E:E) -> 8.9424 | E6: m2 | F6: =VLOOKUP(B6,'综合单价分析表（商业）'!A:I,9,) -> 1662.2142 | G6: =+F6*D6 -> 14864.184
A7: =MAX($A$3:$A6)+1 -> 4 | B7: 首层座槽式玻璃幕墙（12+1.9SGP+12㎜全超白钢化夹层玻璃） | C7: 1#楼南立面2~22轴 | D7: =SUMIF('工程量计算式（商业）'!A:A,B7,'工程量计算式（商业）'!E:E) -> 258.624 | E7: m2 | F7: =VLOOKUP(B7,'综合单价分析表（商业）'!A:I,9,) -> 887.51902 | G7: =+F7*D7 -> 229533.72
A8: =MAX($A$3:$A7)+1 -> 5 | B8: 首层座槽式玻璃幕墙（12+1.9SGP+12㎜全超白钢化夹层玻璃）（弯弧）（弧长1414㎜，圆弧半径900㎜，高3600㎜） | C8: 1#楼南立面2~22轴 | D8: =SUMIF('工程量计算式（商业）'!A:A,B8,'工程量计算式（商业）'!E:E) -> 20.3616 | E8: m2 | F8: =VLOOKUP(B8,'综合单价分析表（商业）'!A:I,9,) -> 1344.225 | G8: =+F8*D8 -> 27370.571
A9: =MAX($A$3:$A8)+1 -> 6 | B9: 首层座槽式玻璃幕墙（10+1.9SGP+10Low-E(双银)+12A+12㎜全超白钢化夹层中空玻璃） | C9: 2#楼南立面5/01~4/01轴,12剖 | D9: =SUMIF('工程量计算式（商业）'!A:A,B9,'工程量计算式（商业）'!E:E) -> 63.36 | E9: m2 | F9: =VLOOKUP(B9,'综合单价分析表（商业）'!A:I,9,) -> 1138.0172 | G9: =+F9*D9 -> 72104.767
A10: =MAX($A$3:$A9)+1 -> 7 | B10: 首层座槽式玻璃幕墙（10+1.9SGP+10Low-E(双银)+12A+12㎜全超白钢化夹层中空玻璃）（弯弧）（弧长1414㎜，圆弧半径900㎜，高3600㎜） | C10: 2#楼南立面5/01~4/01轴,12剖 | D10: =SUMIF('工程量计算式（商业）'!A:A,B10,'工程量计算式（商业）'!E:E) -> 10.1808 | E10: m2 | F10: =VLOOKUP(B10,'综合单价分析表（商业）'!A:I,9,) -> 1879.7105 | G10: =+F10*D10 -> 19136.957
A11: =MAX($A$3:$A10)+1 -> 8 | B11: 首层座槽式玻璃幕墙（12+1.9SGP+12㎜全超白钢化夹层玻璃）（弯弧）（弧长1498㎜，圆弧半径900㎜，高3600㎜） | C11: 2#楼南立面2~18轴，10剖 | D11: =SUMIF('工程量计算式（商业）'!A:A,B11,'工程量计算式（商业）'!E:E) -> 9.4788 | E11: m2 | F11: =VLOOKUP(B11,'综合单价分析表（商业）'!A:I,9,) -> 1337.856 | G11: =+F11*D11 -> 12681.269
A12: =MAX($A$3:$A11)+1 -> 9 | B12: 首层座槽式玻璃幕墙（12+1.9SGP+12㎜全超白钢化夹层玻璃）（直+弯弧）（直段宽度840㎜+弧长1135㎜，圆弧半径900㎜，高3600㎜） | C12: 2#楼南立面2~18轴，10剖 | D12: =SUMIF('工程量计算式（商业）'!A:A,B12,'工程量计算式（商业）'!E:E) -> 7.11 | E12: m2 | F12: =VLOOKUP(B12,'综合单价分析表（商业）'!A:I,9,) -> 1573.6342 | G12: =+F12*D12 -> 11188.539
A13: =MAX($A$3:$A12)+1 -> 10 | B13: 首层座槽式玻璃幕墙（12+1.9SGP+12㎜全超白钢化夹层玻璃）（直+弯弧+直）（直段宽度840㎜+弧长1498㎜+直段宽度450㎜，圆弧半径900㎜，高3600㎜） | C13: 2#楼南立面2~18轴，10剖 | D13: =SUMIF('工程量计算式（商业）'!A:A,B13,'工程量计算式（商业）'!E:E) -> 8.9568 | E13: m2 | F13: =VLOOKUP(B13,'综合单价分析表（商业）'!A:I,9,) -> 1548.1117 | G13: =+F13*D13 -> 13866.127
A14: =MAX($A$3:$A13)+1 -> 11 | B14: 首层座槽式玻璃幕墙（10+1.9SGP+10Low-E(双银)+12A+10㎜全超白钢化夹层中空玻璃） | C14: 2#楼南立面18~23轴，9剖 | D14: =SUMIF('工程量计算式（商业）'!A:A,B14,'工程量计算式（商业）'!E:E) -> 54.9 | E14: m2 | F14: =VLOOKUP(B14,'综合单价分析表（商业）'!A:I,9,) -> 946.54305 | G14: =+F14*D14 -> 51965.214
A15: =MAX($A$3:$A14)+1 -> 12 | B15: 首层座槽式玻璃幕墙（10+1.9SGP+10Low-E(双银)+12A+10㎜全超白钢化夹层中空玻璃）（弯弧）（弧长1100㎜，圆弧半径900㎜，高3600㎜） | C15: 2#楼南立面18~23轴，9剖 | D15: =SUMIF('工程量计算式（商业）'!A:A,B15,'工程量计算式（商业）'!E:E) -> 3.96 | E15: m2 | F15: =VLOOKUP(B15,'综合单价分析表（商业）'!A:I,9,) -> 1645.2037 | G15: =+F15*D15 -> 6515.0066
A16: =MAX($A$3:$A15)+1 -> 13 | B16: 首层座槽式玻璃幕墙（10+1.9SGP+10Low-E(双银)+12A+10㎜全超白钢化夹层中空玻璃）（直+弯弧）（直段宽度600㎜+弧长1100㎜，圆弧半径700㎜，高3600㎜） | C16: 2#楼南立面18~23轴，9剖 | D16: =SUMIF('工程量计算式（商业）'!A:A,B16,'工程量计算式（商业）'!E:E) -> 6.12 | E16: m2 | F16: =VLOOKUP(B16,'综合单价分析表（商业）'!A:I,9,) -> 2336.0147 | G16: =+F16*D16 -> 14296.41
... A43: =MAX($A$3:$A42)+1 -> 40 | B43: 二层明框玻璃幕墙（6+1.52PVB+6Low-E(双银)+12A+10㎜全超白钢化夹层中空玻璃）（直+弯弧+直）（直段宽度210㎜+弧长1414㎜+直段宽度210㎜，圆弧半径900㎜，高2330㎜） | C43: 2#北立面23~18轴,2剖 | D43: =SUMIF('工程量计算式（商业）'!A:A,B43,'工程量计算式（商业）'!E:E) -> 8.54644 | E43: m2 | F43: =VLOOKUP(B43,'综合单价分析表（商业）'!A:I,9,) -> 1937.0646 | G43: =+F43*D43 -> 16555.006
A44: 二 | B44: 玻璃地弹门 | D44: =SUM(D45) -> 138.492 | G44: =SUM(G45) -> 145653.3
A45: 1 | B45: 地弹门（6Low-E(双银)+12A+6㎜全超白钢化中空玻璃） | D45: =SUMIF('工程量计算式（商业）'!A:A,B45,'工程量计算式（商业）'!E:E) -> 138.492 | E45: m2 | F45: =VLOOKUP(B45,'综合单价分析表（商业）'!A:I,9,) -> 1051.7091 | G45: =D45*F45 -> 145653.3 | H45: 无节点
A46: 三 | B46: 石材幕墙（2#商业有下沉庭院） | D46: =SUM(D47:D57) -> 862.11437 | G46: =SUM(G47:G57) -> 1414940.2
A47: 1 | B47: 30mm厚光面福鼎黑石材（造型柱基座） | D47: =SUMIF('工程量计算式（商业）'!A:A,B47,'工程量计算式（商业）'!E:E) -> 6.3 | E47: m2 | F47: =VLOOKUP(B47,'综合单价分析表（商业）'!A:I,9,) -> 1078.8613 | G47: =D47*F47 -> 6796.8263
A48: 2 | B48: 30mm厚光面贝金米黄石材 | D48: =SUMIF('工程量计算式（商业）'!A:A,B48,'工程量计算式（商业）'!E:E) -> 442.04052 | E48: m2 | F48: =VLOOKUP(B48,'综合单价分析表（商业）'!A:I,9,) -> 1281.9863 | G48: =D48*F48 -> 566689.88
A49: 3 | B49: 30mm厚光面贝金米黄石材（弧形） | D49: =D48*0.1 -> 44.204052 | E49: m2 | F49: =VLOOKUP(B49,'综合单价分析表（商业）'!A:I,9,) -> 4218.6373 | G49: =D49*F49 -> 186480.86
A50: 4 | B50: 25mm厚透光云石造型柱 | C50: 1#楼北立面24轴 | D50: =SUMIF('工程量计算式（商业）'!A:A,B50,'工程量计算式（商业）'!E:E) -> 13.6 | E50: m2 | F50: =VLOOKUP(B50,'综合单价分析表（商业）'!A:I,9,) -> 1097.1991 | G50: =D50*F50 -> 14921.908 | H50: =_xlfn.DISPIMG("ID_401A07236E3C452F939057EB265C2CEF",1) -> =DISPIMG("ID_401A07236E3C452F939057EB265C2CEF",1)
A51: 5 | B51: 30mm厚光面深灰色石材 | C51: 1#楼北立面15轴二层 | D51: =SUMIF('工程量计算式（商业）'!A:A,B51,'工程量计算式（商业）'!E:E) -> 7.833 | E51: m2 | F51: =VLOOKUP(B51,'综合单价分析表（商业）'!A:I,9,) -> 1216.3937 | G51: =D51*F51 -> 9528.0119
A52: 6 | B52: 40mm厚自然面贝金米黄石材 | C52: 2#楼北立面5/01轴至4/01轴交B轴至F轴内庭 | D52: =SUMIF('工程量计算式（商业）'!A:A,B52,'工程量计算式（商业）'!E:E) -> 23.3432 | E52: m2 | F52: =VLOOKUP(B52,'综合单价分析表（商业）'!A:I,9,) -> 1600.8976 | G52: =D52*F52 -> 37370.073
A53: 7 | B53: 40mm厚拉槽面贝金米黄石材 | C53: 2#楼北立面5/01轴至4/01轴交B轴至F轴内庭 | D53: =SUMIF('工程量计算式（商业）'!A:A,B53,'工程量计算式（商业）'!E:E) -> 176.0352 | E53: m2 | F53: =VLOOKUP(B53,'综合单价分析表（商业）'!A:I,9,) -> 1846.8711 | G53: =D53*F53 -> 325114.32
A54: 8 | B54: 30mm厚光面贝金米黄石材（造型柱弧形） | C54: 2#楼南立面1/01轴右侧柱子 | D54: =SUMIF('工程量计算式（商业）'!A:A,B54,'工程量计算式（商业）'!E:E) -> 30.828 | E54: m2 | F54: =VLOOKUP(B54,'综合单价分析表（商业）'!A:I,9,) -> 4132.5464 | G54: =D54*F54 -> 127398.14
A55: 9 | B55: 30mm厚透光云石（造型柱弧形） | C55: 2#楼南立面1/01轴右侧柱子 | D55: =SUMIF('工程量计算式（商业）'!A:A,B55,'工程量计算式（商业）'!E:E) -> 20.8104 | E55: m2 | F55: =VLOOKUP(B55,'综合单价分析表（商业）'!A:I,9,) -> 3481.0772 | G55: =D55*F55 -> 72442.61
A56: 10 | B56: 贝金米黄石材拉槽线条1 | C56: 1#楼南立面22轴至24轴，下沉庭院上部线条 | D56: =SUMIF('工程量计算式（商业）'!A:A,B56,'工程量计算式（商业）'!E:E) -> 48.56 | E56: 米 | F56: =VLOOKUP(B56,'综合单价分析表（商业）'!A:I,9,) -> 333.23904 | G56: =D56*F56 -> 16182.088
A57: 11 | B57: 贝金米黄石材拉槽线条2 | C57: 1#楼南立面22轴至24轴，下沉庭院下部弧形线条 | D57: =SUMIF('工程量计算式（商业）'!A:A,B57,'工程量计算式（商业）'!E:E) -> 48.56 | E57: 米 | F57: =VLOOKUP(B57,'综合单价分析表（商业）'!A:I,9,) -> 1071.1594 | G57: =D57*F57 -> 52015.5
A58: 四 | B58: 金属幕墙 | D58: =SUM(D59:D80) -> 4634.494 | G58: =SUM(G59:G80) -> 2867597.1 | J58: 工程量计算规则
A59: 1 | B59: 中灰色仿石材铝单板 | C59: 层间包梁，剖5 | D59: =SUMIF('工程量计算式（商业）'!A:A,B59,'工程量计算式（商业）'!E:E) -> 48.707275 | E59: m2 | F59: =VLOOKUP(B59,'综合单价分析表（商业）'!A:I,9,) -> 582.17204 | G59: =D59*F59 -> 28356.014
A60: 2 | B60: 中灰色仿石材铝单板（弧形） | D60: =SUMIF('工程量计算式（商业）'!A:A,B60,'工程量计算式（商业）'!E:E) -> 8.33553 | E60: m2 | F60: =VLOOKUP(B60,'综合单价分析表（商业）'!A:I,9,) -> 680.47326 | G60: =D60*F60 -> 5672.1053
A61: 3 | B61: 香槟色瓦楞板 | C61: 1.5㎜厚，层间包梁，剖5，JD-203 | D61: =SUMIF('工程量计算式（商业）'!A:A,B61,'工程量计算式（商业）'!E:E) -> 68.90185 | E61: m2 | F61: =VLOOKUP(B61,'综合单价分析表（商业）'!A:I,9,) -> 608.91521 | G61: =D61*F61 -> 41955.384
A62: 4 | B62: 香槟色瓦楞板（弧形） | D62: =SUMIF('工程量计算式（商业）'!A:A,B62,'工程量计算式（商业）'!E:E) -> 7.56828 | E62: m2 | F62: =VLOOKUP(B62,'综合单价分析表（商业）'!A:I,9,) -> 768.53397 | G62: =D62*F62 -> 5816.4803
A63: 5 | B63: 银灰色铝合金瓦楞板（异形） | C63: 北立面 | D63: =SUMIF('工程量计算式（商业）'!A:A,B63,'工程量计算式（商业）'!E:E) -> 39.45325 | E63: m2 | F63: =VLOOKUP(B63,'综合单价分析表（商业）'!A:I,9,) -> 976.3132 | G63: =D63*F63 -> 38518.729
A64: 6 | B64: 银灰色铝合金瓦楞板（异形）（弧形） | D64: =SUMIF('工程量计算式（商业）'!A:A,B64,'工程量计算式（商业）'!E:E) -> 6.183 | E64: m2 | F64: =VLOOKUP(B64,'综合单价分析表（商业）'!A:I,9,) -> 1216.4281 | G64: =D64*F64 -> 7521.1749
A65: 7 | B65: 中灰色铝单板 | D65: =SUMIF('工程量计算式（商业）'!A:A,B65,'工程量计算式（商业）'!E:E) -> 1.05 | E65: m2 | F65: =VLOOKUP(B65,'综合单价分析表（商业）'!A:I,9,) -> 650.75404 | G65: =D65*F65 -> 683.29174
A66: 8 | B66: 东立面墙面：银灰色铝板 | C66: 剖1，2#楼 | D66: =SUMIF('工程量计算式（商业）'!A:A,B66,'工程量计算式（商业）'!E:E) -> 171.44635 | E66: m2 | F66: =VLOOKUP(B66,'综合单价分析表（商业）'!A:I,9,) -> 705.15208 | G66: =D66*F66 -> 120895.75
A67: 9 | B67: 东立面墙面：银灰色铝板（弧形） | C67: 剖1，PU-18造型大样图一 | D67: =D66*0.15 -> 25.716953 | E67: m2 | F67: =VLOOKUP(B67,'综合单价分析表（商业）'!A:I,9,) -> 784.2919 | G67: =D67*F67 -> 20169.598
A68: 10 | B68: 浅灰色铝板 | C68: 1#设备庭院墙面，剖7 | D68: =SUMIF('工程量计算式（商业）'!A:A,B68,'工程量计算式（商业）'!E:E) -> 118.668 | E68: m2 | F68: =VLOOKUP(B68,'综合单价分析表（商业）'!A:I,9,) -> 571.20014 | G68: =D68*F68 -> 67783.178
A69: 11 | B69: 银灰色铝单板 | C69: 1#楼北立面24轴造型柱，JD-235 | D69: =SUMIF('工程量计算式（商业）'!A:A,B69,'工程量计算式（商业）'!E:E) -> 110.79687 | E69: m2 | F69: =VLOOKUP(B69,'综合单价分析表（商业）'!A:I,9,) -> 601.70308 | G69: =D69*F69 -> 66666.818
A70: 12 | B70: 香槟色铝板（弧形） | C70: 剖19 | D70: =D71*0.2 -> 6.233175 | E70: m2 | F70: =VLOOKUP(B70,'综合单价分析表（商业）'!A:I,9,) -> 784.08531 | G70: =D70*F70 -> 4887.341
A71: 13 | B71: 香槟色铝板 | C71: 剖19 | D71: =SUMIF('工程量计算式（商业）'!A:A,B71,'工程量计算式（商业）'!E:E) -> 31.165875 | E71: m2 | F71: =VLOOKUP(B71,'综合单价分析表（商业）'!A:I,9,) -> 665.64611 | G71: =D71*F71 -> 20745.444
A72: 14 | B72: 墙面：25㎜香槟色蜂窝铝板 | C72: 1#，剖19 | D72: =SUMIF('工程量计算式（商业）'!A:A,B72,'工程量计算式（商业）'!E:E) -> 166.38622 | E72: m2 | F72: =VLOOKUP(B72,'综合单价分析表（商业）'!A:I,9,) -> 655.23764 | G72: =D72*F72 -> 109022.51
A73: 15 | B73: 墙面：25㎜香槟色蜂窝铝板（弧形） | C73: 1#，剖19 | D73: =D72*0.1 -> 16.638622 | E73: m2 | F73: =VLOOKUP(B73,'综合单价分析表（商业）'!A:I,9,) -> 801.65638 | G73: =D73*F73 -> 13338.458
A74: 16 | B74: 吊顶：香槟色铝板 | C74: JD-211-1 | D74: =SUMIF('工程量计算式（商业）'!A:A,B74,'工程量计算式（商业）'!E:E) -> 682.1514 | E74: m2 | F74: =VLOOKUP(B74,'综合单价分析表（商业）'!A:I,9,) -> 631.37432 | G74: =D74*F74 -> 430692.88
A75: 17 | B75: 吊顶：25㎜香槟色蜂窝铝板 | C75: JD-211 | D75: =SUMIF('工程量计算式（商业）'!A:A,B75,'工程量计算式（商业）'!E:E) -> 447.2187 | E75: m2 | F75: =VLOOKUP(B75,'综合单价分析表（商业）'!A:I,9,) -> 658.73641 | G75: =D75*F75 -> 294599.24
A76: 18 | B76: 雨蓬上表面：银灰色铝板 | D76: =SUMIF('工程量计算式（商业）'!A:A,B76,'工程量计算式（商业）'!E:E) -> 987.43406 | E76: m2 | F76: =VLOOKUP(B76,'综合单价分析表（商业）'!A:I,9,) -> 657.16454 | G76: =D76*F76 -> 648906.65
A77: 19 | B77: 屋面上表面：浅灰色铝板 | D77: =SUMIF('工程量计算式（商业）'!A:A,B77,'工程量计算式（商业）'!E:E) -> 1318.3075 | E77: m2 | F77: =VLOOKUP(B77,'综合单价分析表（商业）'!A:I,9,) -> 612.54797 | G77: =D77*F77 -> 807526.58
A78: 20 | B78: 2.5㎜铝单板（无龙骨） | C78: 1#收边收口 | D78: =SUMIF('工程量计算式（商业）'!A:A,B78,'工程量计算式（商业）'!E:E) -> 204 | E78: m2 | F78: =VLOOKUP(B78,'综合单价分析表（商业）'!A:I,9,) -> 373.62403 | G78: =D78*F78 -> 76219.301
A79: 21 | B79: 2㎜铝单板（背衬） | C79: 1#楼北立面二层梁，剖6 | D79: =SUMIF('工程量计算式（商业）'!A:A,B79,'工程量计算式（商业）'!E:E) -> 14.44686 | E79: m2 | F79: =VLOOKUP(B79,'综合单价分析表（商业）'!A:I,9,) -> 263.86199 | G79: =D79*F79 -> 3811.9772
A80: 22 | B80: 3㎜浅灰色穿孔铝板 | C80: 不锈钢天沟上盖板 | D80: =SUMIF('工程量计算式（商业）'!A:A,B80,'工程量计算式（商业）'!E:E) -> 153.68425 | E80: m2 | F80: =VLOOKUP(B80,'综合单价分析表（商业）'!A:I,9,) -> 350.1215 | G80: =D80*F80 -> 53808.162
A81: 五 | B81: 金属网 | D81: =SUM(D82:D83) -> 431.63129 | G81: =SUM(G82:G83) -> 249586.32
A82: 1 | B82: 二层金属网 | C82: JD206-208 | D82: =SUMIF('工程量计算式（商业）'!A:A,B82,'工程量计算式（商业）'!E:E) -> 371.92459 | E82: m2 | F82: =VLOOKUP(B82,'综合单价分析表（商业）'!A:I,9,) -> 570.8578 | G82: =D82*F82 -> 212316.05
A83: 2 | B83: 二层金属网（圆弧） | D83: =SUMIF('工程量计算式（商业）'!A:A,B83,'工程量计算式（商业）'!E:E) -> 59.706703 | E83: m2 | F83: =VLOOKUP(B83,'综合单价分析表（商业）'!A:I,9,) -> 624.22251 | G83: =D83*F83 -> 37270.268
A84: 六 | B84: 铝合金格栅与百叶 | D84: =SUM(D85:D86) -> 140.296 | G84: =SUM(G85:G86) -> 95581.072
A85: 1 | B85: 铝合金格栅 | D85: =SUMIF('工程量计算式（商业）'!A:A,B85,'工程量计算式（商业）'!E:E) -> 32.41 | E85: m2 | F85: =排屋工程量清单!F87 -> 675.48581 | G85: =D85*F85 -> 21892.495
A86: 2 | B86: 铝合金百叶 | C86: 2#北立面、东立面 | D86: =SUMIF('工程量计算式（商业）'!A:A,B86,'工程量计算式（商业）'!E:E) -> 107.886 | E86: m2 | F86: =排屋工程量清单!F88 -> 683.02261 | G86: =D86*F86 -> 73688.577
A87: 七 | B87: 铝合金线条 | D87: =SUM(D88:D91) -> 6155.826 | G87: =SUM(G88:G92) -> 385753.24
A88: 1 | B88: 香槟色格栅线条（40*50） | D88: =SUMIF('工程量计算式（商业）'!A:A,B88,'工程量计算式（商业）'!E:E) -> 5432.62 | E88: 米 | F88: =VLOOKUP(B88,'综合单价分析表（商业）'!A:I,9,) -> 49.154252 | G88: =D88*F88 -> 267036.37
A89: 2 | B89: 香槟色铝合金线条（169*100） | C89: 20260330版图纸修改 | D89: =SUMIF('工程量计算式（商业）'!A:A,B89,'工程量计算式（商业）'!E:E) -> 341.661 | E89: 米 | F89: =VLOOKUP(B89,'综合单价分析表（商业）'!A:I,9,) -> 166.51266 | G89: =D89*F89 -> 56890.881
A90: 3 | B90: 铝合金线条（80*160） | C90: JD-235 | D90: =SUMIF('工程量计算式（商业）'!A:A,B90,'工程量计算式（商业）'!E:E) -> 27.6 | E90: 米 | F90: =VLOOKUP(B90,'综合单价分析表（商业）'!A:I,9,) -> 157.15446 | G90: =D90*F90 -> 4337.4631
A91: 4 | B91: 浅灰色铝合金线条（200*50） | C91: 屋面顶部，剖5 | D91: =SUMIF('工程量计算式（商业）'!A:A,B91,'工程量计算式（商业）'!E:E) -> 353.945 | E91: 米 | F91: =VLOOKUP(B91,'综合单价分析表（商业）'!A:I,9,) -> 123.69373 | G91: =D91*F91 -> 43780.777
A92: 5 | B92: 银灰色铝合金线条（120*30） | C92: 香槟色瓦楞板与仿石铝板之间线条，JD-202 | D92: =SUMIF('工程量计算式（商业）'!A:A,B92,'工程量计算式（商业）'!E:E) -> 106.125 | E92: 米 | F92: =VLOOKUP(B92,'综合单价分析表（商业）'!A:I,9,) -> 129.16599 | G92: =D92*F92 -> 13707.741
A93: 八 | B93: 不锈钢 | D93: =SUM(D94) -> 491.004 | G93: =SUM(G94) -> 233424.78
A94: 1 | B94: 不锈钢天沟 | D94: =SUMIF('工程量计算式（商业）'!A:A,B94,'工程量计算式（商业）'!E:E) -> 491.004 | E94: 米 | F94: =VLOOKUP(B94,'综合单价分析表（商业）'!A:I,9,) -> 475.40302 | G94: =D94*F94 -> 233424.78
A95: 九 | B95: 玻璃栏杆 | D95: =SUM(D96:D97) -> 92.83 | G95: =SUM(G96:G97) -> 81172.769
A96: 1 | B96: 6+1.14PVB+6㎜超白钢化夹层玻璃栏杆 | D96: =SUMIF('工程量计算式（商业）'!A:A,B96,'工程量计算式（商业）'!E:E) -> 84.128 | E96: 米 | F96: =排屋工程量清单!F107 -> 869.51382 | G96: =D96*F96 -> 73150.459
A97: 2 | B97: 6+1.14PVB+6㎜超白钢化夹层玻璃栏杆（弧形） | D97: =SUMIF('工程量计算式（商业）'!A:A,B97,'工程量计算式（商业）'!E:E) -> 8.702 | E97: 米 | F97: =排屋工程量清单!F108 -> 921.89268 | G97: =D97*F97 -> 8022.3101
A98: 十 | B98: 其他 | G98: =SUM(G99:G102) -> 193353.83
A99: 1 | B99: 入口钢龙骨 | D99: 1100 | E99: m2 | F99: 90 | G99: =D99*F99 -> 99000
A100: 2 | B100: 后置埋件 | E100: T | G100: =D100*F100 -> 0
A101: 3 | B101: 防火隔断 | D101: =SUMIF('工程量计算式（商业）'!A:A,B101,'工程量计算式（商业）'!E:E) -> 1368 | E101: 米 | F101: =VLOOKUP(B101,'综合单价分析表（商业）'!A:I,9,) -> 65.612212 | G101: =D101*F101 -> 89757.507
A102: 4 | B102: 1.5㎜镀锌钢板封堵 | D102: =SUMIF('工程量计算式（商业）'!A:A,B102,'工程量计算式（商业）'!E:E) -> 50 | E102: m2 | F102: =VLOOKUP(B102,'综合单价分析表（商业）'!A:I,9,) -> 91.926549 | G102: =D102*F102 -> 4596.3274
A103: 十 | B103: 措施费 | D103: 1 | E103: 项 | F103: ='措施费 (商业)'!F16 -> 335326.31 | G103: =D103*F103 -> 335326.31
B104: 合计： | D104: =D3+D44+D46+D58+D81+D84+D93+D95 -> 8319.4105 | F104: =+G104/D104 -> 953.67369 | G104: =G3+G44+G46+G58+G81+G84+G87+G93+G95+G98+G103 -> 7934002.9

Sheet 11#楼措施费
A1: 长住集团成都成华区迎晖路194号地块项目示范区幕墙工程
A2: 措施费清单
C3: 工程量 | D3: 单位 | E3: 综合单价 | F3: 合价 | G3: 备注
B4: 11#号楼 | E4: 不含增值税税额 | F4: 含增值税税额
A5: 1 | B5: 安全文明环境费（含幕墙施工时简易措施等） | C5: 1 | D5: 项 | E5: 20000 | F5: =E5*C5*$H$5 -> 21800 | H5: 1.09
A6: 2 | B6: 措施费（含脚手架、吊车设备、登高车、叉车等） | C6: =C5 -> 1 | D6: 项 | E6: =3688*25 -> 92200 | F6: =E6*C6*$H$5 -> 100498 | G6: 脚手架仅考虑改架、二次搭设等
A7: 3 | B7: 夜间施工、展示区赶工费（本项目工期较为紧张，充分考虑抢工费用，后续不可再向甲方上报抢工费用，存在夜间加班施工情况，本次报价充分考虑夜间加班费用） | C7: =C6 -> 1 | D7: 项 | E7: 10000 | F7: =E7*C7*$H$5 -> 10900 | G7: 仅仅11#楼考虑该费用，后续楼栋正常施工可以不计或少计取该费用
A8: 4 | B8: 二次搬运及多次搬运费 | C8: 1 | D8: 项 | E8: 10000 | F8: =E8*C8*$H$5 -> 10900 | G8: 材料比较复杂对场地要求较高，综合考虑肯定容易发生转运费用
A9: 5 | B9: 已完工程及设备保护费、成品保护费 | C9: =C8 -> 1 | D9: 项 | E9: 20000 | F9: =E9*C9*$H$5 -> 21800 | G9: 豪宅类项目成品保护费用偏高
A10: 7 | B10: 外墙清洗费 | C10: 1 | D10: 项 | E10: 12000 | F10: =E10*C10*$H$5 -> 13080
A11: 8 | B11: 开模费 | C11: 1 | D11: 项 | E11: 10000 | F11: =E11*C11*$H$5 -> 10900
A12: 合计 | F12: =SUM(F5:F11) -> 189878

Sheet 措施费 (商业)
A1: 长住集团成都成华区迎晖路194号地块项目示范区幕墙工程
A2: 措施费清单
C3: 工程量 | D3: 单位 | E3: 综合单价 | F3: 合价 | G3: 备注
B4: 1#2#楼商业幕墙 | E4: 不含增值税税额 | F4: 含增值税税额
A5: 1 | B5: 安全文明环境费 | C5: 1 | D5: 项 | E5: 5000 | F5: =E5*C5*$H$5 -> 5450 | H5: 1.09
A6: 2 | B6: 临时设施费 | C6: 1 | D6: 项 | E6: 0 | F6: =E6*C6*$H$5 -> 0
A7: 3 | B7: 夜间施工、展示区赶工费（本项目工期较为紧张，充分考虑抢工费用，后续不可再向甲方上报抢工费用，存在夜间加班施工情况，本次报价充分考虑夜间加班费用） | C7: 1 | D7: 项 | E7: 30000 | F7: =E7*C7*$H$5 -> 32700
A8: 4 | B8: 冬雨季施工增加费 | C8: 1 | D8: 项 | E8: 0 | F8: =E8*C8*$H$5 -> 0
A9: 5 | B9: 二次搬运及多次搬运费 | C9: 1 | D9: 项 | E9: 10000 | F9: =E9*C9*$H$5 -> 10900
A10: 6 | B10: 已完工程及设备保护费、成品保护费 | C10: 1 | D10: 项 | E10: 20000 | F10: =E10*C10*$H$5 -> 21800
A11: 7 | B11: 脚手架费 | C11: 1 | D11: 项 | E11: =K12 -> 96000 | F11: =E11*C11*$H$5 -> 104640 | K11: =3000*32 -> 96000
A12: 8 | B12: 吊篮费 | C12: 1 | D12: 项 | E12: 0 | F12: =E12*C12*$H$5 -> 0 | K12: =SUM(K11:K11) -> 96000
A13: 9 | B13: 机械措施费 | C13: 1 | D13: 项 | E13: 80000 | F13: =E13*C13*$H$5 -> 87200
A14: 12 | B14: 外墙清洗费 | C14: 1 | D14: 项 | E14: ='商业工程量清单 '!D104*2 -> 16638.821 | F14: =E14*C14*$H$5 -> 18136.315
A15: 13 | B15: 开模费 | C15: 1 | D15: 项 | E15: 50000 | F15: =E15*C15*$H$5 -> 54500
A16: 合计 | F16: =SUM(F5:F15) -> 335326.31

Sheet 综合单价分析表 (11#楼)
B1: 综合单价分析表
A2: 1 | B2: 序号 | C2: 清单项名称： | D2: =+A10 -> LMC6117G | F2: 80系列断桥隔热铝合金窗 | H2: 费率 | I2: 金额 | J2: 单位 | K2: =VLOOKUP(A2,排屋工程量清单!A:D,4,) -> 14.175
B3: 1 | C3: 直接工程费 | D3: 人工费 | I3: =J15 -> 80 | J3: 元 | L3: 80系列 | O3: 4.05 | P3: 1.75 | Q3: 1 | R3: =+Q3*P3*O3 -> 7.0875
B4: 2 | D4: 材料费 | I4: =J40 -> 651.84742 | J4: 元
B5: 3 | D5: 机械费 | I5: =J41 -> 10 | J5: 元 | M5: 名称 | N5: 米重 | O5: 长/宽 | P5: 数量 | Q5: 总重 | R5: 单方
B6: 4 | C6: 直接费 | D6: (1)+（2）+（3） | I6: =SUM(I3:I5) -> 741.84742 | J6: 元 | L6: 粉末喷涂铝型材T5 | M6: 铝合金窗框-竖 | O6: =P3 -> 1.75 | P6: 2 | Q6: =+P6*O6*N6 -> 0 | R6: =+Q6/R3 -> 0
B7: 5 | C7: 公司管理、利润 | D7: （4）*a% | H7: =+'材料表 '!$E$178 -> 0 | I7: =H7*I6 -> 0 | J7: 元 | L7: 粉末喷涂铝型材T5 | M7: 铝合金窗框-横 | O7: =O3 -> 4.05 | P7: 2 | Q7: =+P7*O7*N7 -> 0 | R7: =+Q7/R3 -> 0
B8: 6 | C8: 现场管理费 | D8: （4）*b% | H8: =+'材料表 '!$E$179 -> 0 | I8: =H8*I6 -> 0 | J8: 元 | L8: 粉末喷涂铝型材T5 | M8: 铝合金中梃-竖 | O8: =P3*2 -> 3.5 | P8: 1 | Q8: =+P8*O8*N8 -> 0 | R8: =+Q8/R3 -> 0
B9: 7 | C9: 税金 | D9: [(4)+(5)+(6)]*c% | H9: =+'材料表 '!$E$180 -> 0.09 | I9: =(I6+I7+I8)*H9 -> 66.766268 | J9: 元 | L9: 粉末喷涂铝型材T5 | M9: 铝合金加强中梃-竖 | O9: 0 | P9: 1 | Q9: =+P9*O9*N9 -> 0 | R9: =+Q9/R3 -> 0
A10: LMC6117G | B10: 8 | C10: 综合单价 | D10: （4）-（7）之和 | I10: =SUM(I6:I9) -> 808.61369 | J10: 元/m² | L10: 粉末喷涂铝型材T5 | M10: 铝合金中梃-横 | O10: 0 | P10: 1 | Q10: =+P10*O10*N10 -> 0 | R10: =+Q10/R3 -> 0
B11: 其中 | L11: 粉末喷涂铝型材T5 | M11: 铝合金转换料 | O11: =(P3*2+0.65*2)*2 -> 9.6 | P11: 1 | Q11: =+P11*O11*N11 -> 0 | R11: =+Q11/R3 -> 0
B12: 1 | C12: 人工费 | D12: 名称 | E12: 单位 | H12: 数量 | I12: 单价 | J12: 金额（元） | L12: 粉末喷涂铝型材T5 | M12: 铝合金扇料 | O12: =O11 -> 9.6 | P12: 1 | Q12: =+P12*O12*N12 -> 0 | R12: =+Q12/R3 -> 0
B13: 2 | D13: 80系列断桥隔热铝合金窗 | E13: ㎡ | H13: 1 | I13: =+辅材及安装费!$G$10 -> 80 | J13: =H13*I13 -> 80 | L13: 粉末喷涂铝型材T5 | M13: 开启压条 | O13: =O12 -> 9.6 | P13: 1 | Q13: =+P13*O13*N13 -> 0 | R13: =+Q13/R3 -> 0
B14: 3 | L14: 粉末喷涂铝型材T5 | M14: 固定压条 | O14: =2.75*2+P3*2 -> 9 | P14: 1 | Q14: =+P14*O14*N14 -> 0 | R14: =+Q14/R3 -> 0
B15: 4 | D15: 人工费合计 | E15: 元 | J15: =SUM(J13:J13) -> 80
B16: 1 | C16: 材料费 | D16: 粉末喷涂铝型材T6 | E16: =+VLOOKUP(D16,'材料表 '!C:F,2,0) -> kg | F16: =+SUMIF($L$3:$L$41,D16,$R$3:$R$41) -> 0 | G16: =+VLOOKUP(D16,'材料表 '!C:F,4,0) -> 0.03 | H16: =F16*(G16+1) -> 0 | I16: =+VLOOKUP(D16,'材料表 '!C:F,3,0) -> 25.849558 | J16: =H16*I16 -> 0 | K16: =H16*K2 -> 0
B17: 2 | D17: 粉末喷涂铝型材T5 | E17: =+VLOOKUP(D17,'材料表 '!C:F,2,0) -> kg | F17: 12 | G17: =+VLOOKUP(D17,'材料表 '!C:F,4,0) -> 0.03 | H17: =F17*(G17+1) -> 12.36 | I17: =+VLOOKUP(D17,'材料表 '!C:F,3,0) -> 25.672566 | J17: =H17*I17 -> 317.31292 | K17: =H17*K2 -> 175.203 | L17: 隔热条（H=39mm） | O17: =(O6*P6+O7*P7+O8*P8+O9*P9+O10*P10+O11*P11+O12*P12) -> 34.3 | P17: =+P6 -> 2 | Q17: =+P17*O17 -> 68.6 | R17: =+Q17/R3 -> 9.6790123
B18: 3 | D18: 阳极氧化铝型材T6 | E18: =+VLOOKUP(D18,'材料表 '!C:F,2,0) -> kg | F18: =+SUMIF($L$3:$L$41,D18,$R$3:$R$41) -> 0 | G18: =+VLOOKUP(D18,'材料表 '!C:F,4,0) -> 0.03 | H18: =F18*(G18+1) -> 0 | I18: =+VLOOKUP(D18,'材料表 '!C:F,3,0) -> 26.115044 | J18: =H18*I18 -> 0 | K18: =H18*K2 -> 0
B19: 4 | D19: 光身料铝型材T6 | E19: =+VLOOKUP(D19,'材料表 '!C:F,2,0) -> kg | F19: =+SUMIF($L$3:$L$41,D19,$R$3:$R$41) -> 0 | G19: =+VLOOKUP(D19,'材料表 '!C:F,4,0) -> 0.03 | H19: =F19*(G19+1) -> 0 | I19: =+VLOOKUP(D19,'材料表 '!C:F,3,0) -> 24.610619 | J19: =H19*I19 -> 0 | K19: =H19*K2 -> 0 | L19: 热镀锌钢管 | M19: 80*30*3 | N19: 4.898 | O19: =+O3*2+P3*2 -> 11.6 | P19: 1 | Q19: =+P19*O19*N19 -> 56.8168 | R19: =+Q19/R3 -> 8.0164797
B20: 5 | D20: 阳极氧化铝型材T5 | E20: =+VLOOKUP(D20,'材料表 '!C:F,2,0) -> kg | F20: =+SUMIF($L$3:$L$41,D20,$R$3:$R$41) -> 0 | G20: =+VLOOKUP(D20,'材料表 '!C:F,4,0) -> 0.03 | H20: =F20*(G20+1) -> 0 | I20: =+VLOOKUP(D20,'材料表 '!C:F,3,0) -> 26.115044 | J20: =H20*I20 -> 0 | K20: =H20*K2 -> 0 | R20: =+Q20/R3 -> 0
B21: 6 | D21: 铝材表面氟碳喷涂 | E21: =+VLOOKUP(D21,'材料表 '!C:F,2,0) -> m2 | F21: =+SUMIF($L$3:$L$41,D21,$R$3:$R$41) -> 0 | G21: =+VLOOKUP(D21,'材料表 '!C:F,4,0) -> 0 | H21: =F21*(G21+1) -> 0 | I21: =+VLOOKUP(D21,'材料表 '!C:F,3,0) -> 49.557522 | J21: =H21*I21 -> 0 | K21: =H21*K2 -> 0 | R21: =+Q28/R3 -> 0.23779894
B22: 7 | D22: 隔热条（H=39mm） | E22: =+VLOOKUP(D22,'材料表 '!C:F,2,0) -> m | F22: =+SUMIF($L$3:$L$41,D22,$R$3:$R$41) -> 9.6790123 | G22: =+VLOOKUP(D22,'材料表 '!C:F,4,0) -> 0 | H22: =F22*(G22+1) -> 9.6790123 | I22: =+VLOOKUP(D22,'材料表 '!C:F,3,0) -> 5.3097345 | J22: =H22*I22 -> 51.392986 | K22: =H22*K2 -> 137.2 | R22: =+Q29/R3 -> 0.59898413
B23: 8 | D23: 热镀锌钢管 | E23: =+VLOOKUP(D23,'材料表 '!C:F,2,0) -> kg | F23: =+SUMIF($L$3:$L$41,D23,$R$3:$R$41) -> 8.0164797 | G23: =+VLOOKUP(D23,'材料表 '!C:F,4,0) -> 0.03 | H23: =F23*(G23+1) -> 8.2569741 | I23: =+VLOOKUP(D23,'材料表 '!C:F,3,0) -> 3.8053097 | J23: =H23*I23 -> 31.420344 | K23: =H23*K2 -> 117.04261 | R23: =+Q23/R3 -> 0
B24: 9 | D24: 三元乙丙胶条 | E24: =+VLOOKUP(D24,'材料表 '!C:F,2,0) -> kg | F24: =0.065*1.3*(O12)*2/R3 -> 0.22891005 | G24: =+VLOOKUP(D24,'材料表 '!C:F,4,0) -> 0.03 | H24: =F24*(G24+1) -> 0.23577735 | I24: =+VLOOKUP(D24,'材料表 '!C:F,3,0) -> 19.469027 | J24: =H24*I24 -> 4.5903556 | K24: =H24*K2 -> 3.342144 | R24: =+Q24/R3 -> 0
B25: 10 | D25: 玻璃密封胶 | E25: =+VLOOKUP(D25,'材料表 '!C:F,2,0) -> 支 | F25: =0.8 -> 0.8 | G25: =+VLOOKUP(D25,'材料表 '!C:F,4,0) -> 0.15 | H25: =F25*(G25+1) -> 0.92 | I25: =+VLOOKUP(D25,'材料表 '!C:F,3,0) -> 11.504425 | J25: =H25*I25 -> 10.584071 | K25: =H25*K2 -> 13.041 | R25: =+Q25/R3 -> 0
B26: 11 | D26: 水泥砂浆封堵 | E26: =+VLOOKUP(D26,'材料表 '!C:F,2,0) -> m | F26: =(O3*2+P3*2)/R3 -> 1.6366843 | G26: =+VLOOKUP(D26,'材料表 '!C:F,4,0) -> 0 | H26: =F26*(G26+1) -> 1.6366843 | I26: =+VLOOKUP(D26,'材料表 '!C:F,3,0) -> 0 | J26: =H26*I26 -> 0 | K26: =H26*K2 -> 23.2 | R26: =+Q26/R3 -> 0
B27: 12 | D27: 外开窗五金件 | E27: =+VLOOKUP(D27,'材料表 '!C:F,2,0) -> 套 | F27: =2/R3 -> 0.28218695 | G27: =+VLOOKUP(D27,'材料表 '!C:F,4,0) -> 0 | H27: =F27*(G27+1) -> 0.28218695 | I27: =+VLOOKUP(D27,'材料表 '!C:F,3,0) -> 247.78761 | J27: =H27*I27 -> 69.92243 | K27: =H27*K2 -> 4
B28: 13 | D28: 5Low-E(双银)+12A+5+12A+5mm全超白钢化中空玻璃 | E28: =+VLOOKUP(D28,'材料表 '!C:F,2,0) -> m2 | F28: =+SUMIF($L$3:$L$41,D28,$R$3:$R$41) -> 0.23779894 | G28: =+VLOOKUP(D28,'材料表 '!C:F,4,0) -> 0.01 | H28: =F28*(G28+1) -> 0.24017693 | I28: =+VLOOKUP(D28,'材料表 '!C:F,3,0) -> 132.74336 | J28: =H28*I28 -> 31.881894 | K28: =H28*K2 -> 3.404508 | L28: 5Low-E(双银)+12A+5+12A+5mm全超白钢化中空玻璃 | N28: =(0.65-0.08-0.04)*(1.75-0.08*2) -> 0.8427 | P28: 2 | Q28: =N28*P28 -> 1.6854 | R28: =Q28/R3 -> 0.23779894
B29: 14 | D29: 10Low-E(双银)+12A+10+12A+10mm全超白钢化中空玻璃 | E29: =+VLOOKUP(D29,'材料表 '!C:F,2,0) -> m2 | F29: =+SUMIF($L$3:$L$41,D29,$R$3:$R$41) -> 0.59898413 | G29: =+VLOOKUP(D29,'材料表 '!C:F,4,0) -> 0.01 | H29: =F29*(G29+1) -> 0.60497397 | I29: =+VLOOKUP(D29,'材料表 '!C:F,3,0) -> 206.19469 | J29: =H29*I29 -> 124.74242 | K29: =H29*K2 -> 8.575506 | L29: 10Low-E(双银)+12A+10+12A+10mm全超白钢化中空玻璃 | N29: =(2.75-0.04-0.04)*(1.75-0.08*2) -> 4.2453 | P29: 1 | Q29: =N29*P29 -> 4.2453 | R29: =Q29/R3 -> 0.59898413
B30: 15
B31: 16
B32: 17
B33: 18
B34: 19
B35: 20
B36: 21
B37: 22
B38: 23
B39: 24 | D39: 辅材材料费 | E39: m2 | G39: 1 | H39: 1 | I39: =+辅材及安装费!$E$10 -> 10 | J39: =H39*I39 -> 10
B40: 25 | D40: 材料费合计 | J40: =SUM(J16:J39) -> 651.84742
B41: 1 | C41: 其他费 | D41: 机械费+运输费 | E41: m2 | H41: 1 | I41: =+辅材及安装费!$F$10 -> 10 | J41: =H41*I41 -> 10
B42: 综合单价分析表
A43: 18 | B43: 序号 | C43: 清单项名称： | D43: =+A51 -> LMC10425C | F43: 幕墙式铝合金窗 | H43: 费率 | I43: 金额 | J43: 单位 | K43: =VLOOKUP(A43,排屋工程量清单!A:D,4,) -> 26.677
B44: 1 | C44: 直接工程费 | D44: 人工费 | I44: =J56 -> 175 | J44: 元 | O44: 10.3 | P44: 2.59 | Q44: 1 | R44: =+Q44*P44*O44 -> 26.677
B45: 2 | D45: 材料费 | I45: =J81 -> 974.9702 | J45: 元
B46: 3 | D46: 机械费 | I46: =J82 -> 5 | J46: 元 | M46: 名称 | N46: 米重 | O46: 长/宽 | P46: 数量 | Q46: 总重 | R46: 单方
B47: 4 | C47: 直接费 | D47: (1)+（2）+（3） | I47: =SUM(I44:I46) -> 1154.9702 | J47: 元 | L47: 粉末喷涂铝型材T5 | M47: 铝合金窗框 | N47: 2.513 | O47: =O44*2+P44*2 -> 25.78 | P47: 1 | Q47: =+P47*O47*N47 -> 64.78514 | R47: =+Q47/R44 -> 2.4285017
B48: 5 | C48: 公司管理、利润 | D48: （4）*a% | H48: =+'材料表 '!$E$178 -> 0 | I48: =H48*I47 -> 0 | J48: 元 | L48: 阳极氧化铝型材T6 | M48: 铝合金窗框压板 | N48: 0.424 | O48: =O47 -> 25.78 | P48: 1 | Q48: =+P48*O48*N48 -> 10.93072 | R48: =+Q48/R44 -> 0.40974322
B49: 6 | C49: 现场管理费 | D49: （4）*b% | H49: =+'材料表 '!$E$179 -> 0 | I49: =H49*I47 -> 0 | J49: 元 | L49: 光身料铝型材T5 | M49: 铝合金窗框外罩板 | N49: 0.484 | O49: =O47 -> 25.78 | P49: 1 | Q49: =+P49*O49*N49 -> 12.47752 | R49: =+Q49/R44 -> 0.46772576 | S49: =(0.05+0.046+0.015)*2 -> 0.222 | T49: =O49*S49 -> 5.72316 | U49: =T49/R44 -> 0.21453537
B50: 7 | C50: 税金 | D50: [(4)+(5)+(6)]*c% | H50: =+'材料表 '!$E$180 -> 0.09 | I50: =(I47+I48+I49)*H50 -> 103.94732 | J50: 元 | L50: 粉末喷涂铝型材T6 | M50: 铝合金中梃 | N50: 2.816 | O50: =P44*3 -> 7.77 | P50: 1 | Q50: =+P50*O50*N50 -> 21.88032 | R50: =+Q50/R44 -> 0.82019417
A51: LMC10425C | B51: 8 | C51: 综合单价 | D51: （4）-（7）之和 | I51: =SUM(I47:I50) -> 1258.9175 | J51: 元/m² | L51: 阳极氧化铝型材T6 | M51: 铝合金中梃压板 | N51: 0.656 | O51: =O50 -> 7.77 | P51: 1 | Q51: =+P51*O51*N51 -> 5.09712 | R51: =+Q51/R44 -> 0.19106796
B52: 其中 | L52: 光身料铝型材T5 | M52: 铝合金中梃罩板 | N52: 0.443 | O52: =O50 -> 7.77 | P52: 1 | Q52: =+P52*O52*N52 -> 3.44211 | R52: =+Q52/R44 -> 0.12902913 | S52: =0.105*2 -> 0.21 | T52: =O52*S52 -> 1.6317 | U52: =T52/R44 -> 0.061165049
B53: 1 | C53: 人工费 | D53: 名称 | E53: 单位 | H53: 数量 | I53: 单价 | J53: 金额（元） | L53: 粉末喷涂铝型材T5 | M53: 固定窗拼接件 | N53: 0.324 | O53: =7.05*2+P44*4 -> 24.46 | P53: 1 | Q53: =+P53*O53*N53 -> 7.92504 | R53: =+Q53/R44 -> 0.29707388
B54: 2 | D54: 幕墙式铝合窗 | E54: ㎡ | H54: 1 | I54: =+辅材及安装费!$G$5 -> 175 | J54: =H54*I54 -> 175 | L54: 粉末喷涂铝型材T6 | M54: 铝合金拼樘 | N54: 1.837 | O54: 2 | P54: 1 | Q54: =+P54*O54*N54 -> 3.674 | R54: =+Q54/R44 -> 0.13772163
B55: 3 | M55: 窗扇 | N55: 3.8 | O55: =(1.625+P44)*2 -> 8.43 | P55: 1 | Q55: =+P55*O55*N55 -> 32.034 | R55: =+Q55/R44 -> 1.2008097
B56: 4 | D56: 人工费合计 | E56: 元 | J56: =SUM(J54:J54) -> 175 | P56: 1
B57: 1 | C57: 材料费 | D57: 粉末喷涂铝型材T6 | E57: =+VLOOKUP(D57,'材料表 '!C:F,2,0) -> kg | F57: =+SUMIF($L$44:$L$82,D57,$R$44:$R$82) -> 0.95791581 | G57: =+VLOOKUP(D57,'材料表 '!C:F,4,0) -> 0.03 | H57: =F57*(G57+1) -> 0.98665328 | I57: =+VLOOKUP(D57,'材料表 '!C:F,3,0) -> 25.849558 | J57: =H57*I57 -> 25.504551 | K57: =H57*K43 -> 26.32095 | P57: 1
B58: 2 | D58: 粉末喷涂铝型材T5 | E58: =+VLOOKUP(D58,'材料表 '!C:F,2,0) -> kg | F58: =+SUMIF($L$44:$L$82,D58,$R$44:$R$82) -> 2.7255756 | G58: =+VLOOKUP(D58,'材料表 '!C:F,4,0) -> 0.03 | H58: =F58*(G58+1) -> 2.8073429 | I58: =+VLOOKUP(D58,'材料表 '!C:F,3,0) -> 25.672566 | J58: =H58*I58 -> 72.071696 | K58: =H58*K43 -> 74.891485
B59: 3 | D59: 阳极氧化铝型材T6 | E59: =+VLOOKUP(D59,'材料表 '!C:F,2,0) -> kg | F59: =+SUMIF($L$44:$L$82,D59,$R$44:$R$82) -> 0.60081119 | G59: =+VLOOKUP(D59,'材料表 '!C:F,4,0) -> 0.03 | H59: =F59*(G59+1) -> 0.61883552 | I59: =+VLOOKUP(D59,'材料表 '!C:F,3,0) -> 26.115044 | J59: =H59*I59 -> 16.160917 | K59: =H59*K43 -> 16.508675
B60: 4 | D60: 光身料铝型材T5 | E60: =+VLOOKUP(D60,'材料表 '!C:F,2,0) -> kg | F60: =+SUMIF($L$44:$L$82,D60,$R$44:$R$82) -> 0.59675488 | G60: =+VLOOKUP(D60,'材料表 '!C:F,4,0) -> 0.03 | H60: =F60*(G60+1) -> 0.61465753 | I60: =+VLOOKUP(D60,'材料表 '!C:F,3,0) -> 24.433628 | J60: =H60*I60 -> 15.018314 | K60: =H60*K43 -> 16.397219 | L60: 隔热条（H=39mm） | O60: =(O47+O50+O54+O55) -> 43.98 | P60: =+P47 -> 1 | Q60: =+P60*O60 -> 43.98 | R60: =+Q60/R44 -> 1.6486112
B61: 5 | D61: 阳极氧化铝型材T5 | E61: =+VLOOKUP(D61,'材料表 '!C:F,2,0) -> kg | F61: =+SUMIF($L$44:$L$82,D61,$R$44:$R$82) -> 0 | G61: =+VLOOKUP(D61,'材料表 '!C:F,4,0) -> 0.03 | H61: =F61*(G61+1) -> 0 | I61: =+VLOOKUP(D61,'材料表 '!C:F,3,0) -> 26.115044 | J61: =H61*I61 -> 0 | K61: =H61*K43 -> 0
B62: 6 | D62: 铝材表面氟碳喷涂 | E62: =+VLOOKUP(D62,'材料表 '!C:F,2,0) -> m2 | F62: =U49+U52 -> 0.27570042 | G62: =+VLOOKUP(D62,'材料表 '!C:F,4,0) -> 0 | H62: =F62*(G62+1) -> 0.27570042 | I62: =+VLOOKUP(D62,'材料表 '!C:F,3,0) -> 49.557522 | J62: =H62*I62 -> 13.663029 | K62: =H62*K43 -> 7.35486 | L62: 热镀锌钢管 | M62: 80*30*3 | N62: 4.898 | O62: =+O44*2+P44*2 -> 25.78 | P62: 1 | Q62: =+P62*O62*N62 -> 126.27044 | R62: =+Q62/R44 -> 4.7333073
B63: 7 | D63: 隔热条（H=39mm） | E63: =+VLOOKUP(D63,'材料表 '!C:F,2,0) -> m | F63: =+SUMIF($L$44:$L$82,D63,$R$44:$R$82) -> 1.6486112 | G63: =+VLOOKUP(D63,'材料表 '!C:F,4,0) -> 0 | H63: =F63*(G63+1) -> 1.6486112 | I63: =+VLOOKUP(D63,'材料表 '!C:F,3,0) -> 5.3097345 | J63: =H63*I63 -> 8.7536876 | K63: =H63*K43 -> 43.98
B64: 8 | D64: 热镀锌钢管 | E64: =+VLOOKUP(D64,'材料表 '!C:F,2,0) -> kg | F64: =+SUMIF($L$44:$L$82,D64,$R$44:$R$82) -> 4.7333073 | G64: =+VLOOKUP(D64,'材料表 '!C:F,4,0) -> 0.03 | H64: =F64*(G64+1) -> 4.8753066 | I64: =+VLOOKUP(D64,'材料表 '!C:F,3,0) -> 3.8053097 | J64: =H64*I64 -> 18.552052 | K64: =H64*K43 -> 130.05855
B65: 9 | D65: 三元乙丙胶条 | E65: =+VLOOKUP(D65,'材料表 '!C:F,2,0) -> kg | F65: 2 | G65: =+VLOOKUP(D65,'材料表 '!C:F,4,0) -> 0.03 | H65: =F65*(G65+1) -> 2.06 | I65: =+VLOOKUP(D65,'材料表 '!C:F,3,0) -> 19.469027 | J65: =H65*I65 -> 40.106195 | K65: =H65*K43 -> 54.95462
B66: 10 | D66: 玻璃密封胶 | E66: =+VLOOKUP(D66,'材料表 '!C:F,2,0) -> 支 | F66: =8*8*(O47+O53+O55)*2/300/R44 -> 0.93835639 | G66: =+VLOOKUP(D66,'材料表 '!C:F,4,0) -> 0.15 | H66: =F66*(G66+1) -> 1.0791098 | I66: =+VLOOKUP(D66,'材料表 '!C:F,3,0) -> 11.504425 | J66: =H66*I66 -> 12.414538 | K66: =H66*K43 -> 28.787413
B67: 11 | D67: 水泥砂浆封堵 | E67: =+VLOOKUP(D67,'材料表 '!C:F,2,0) -> m | F67: =(O44*2+P44*2)/R44 -> 0.96637553 | G67: =+VLOOKUP(D67,'材料表 '!C:F,4,0) -> 0 | H67: =F67*(G67+1) -> 0.96637553 | I67: =+VLOOKUP(D67,'材料表 '!C:F,3,0) -> 0 | J67: =H67*I67 -> 0 | K67: =H67*K43 -> 25.78
B68: 12 | D68: 移门（系统门） | E68: =+VLOOKUP(D68,'材料表 '!C:F,2,0) -> 套 | F68: =2/R44 -> 0.074970949 | G68: =+VLOOKUP(D68,'材料表 '!C:F,4,0) -> 0 | H68: =F68*(G68+1) -> 0.074970949 | I68: =+VLOOKUP(D68,'材料表 '!C:F,3,0) -> 1327.4336 | J68: =H68*I68 -> 99.518959 | K68: =H68*K43 -> 2
B69: 13 | D69: 8Low-E(双银)+12A+8+12A+8mm全超白钢化中空玻璃 | E69: =+VLOOKUP(D69,'材料表 '!C:F,2,0) -> m2 | F69: =+SUMIF($L$44:$L$82,D69,$R$44:$R$82) -> 0.46359223 | G69: =+VLOOKUP(D69,'材料表 '!C:F,4,0) -> 0.01 | H69: =F69*(G69+1) -> 0.46822816 | I69: =+VLOOKUP(D69,'材料表 '!C:F,3,0) -> 177.87611 | J69: =H69*I69 -> 83.286601 | K69: =H69*K43 -> 12.490922 | L69: 8Low-E(双银)+12A+8+12A+8mm全超白钢化中空玻璃 | N69: =(4.85-0.025*3)*(P44-0.025*0) -> 12.36725 | P69: 1 | Q69: =N69*P69 -> 12.36725 | R69: =Q69/R44 -> 0.46359223
B70: 14 | D70: 15Low-E(双银)+12A+15+12A+15mm全超白钢化中空玻璃（超宽） | E70: =+VLOOKUP(D70,'材料表 '!C:F,2,0) -> m2 | F70: =+SUMIF($L$44:$L$82,D70,$R$44:$R$82) -> 0.52669903 | G70: =+VLOOKUP(D70,'材料表 '!C:F,4,0) -> 0.01 | H70: =F70*(G70+1) -> 0.53196602 | I70: =+VLOOKUP(D70,'材料表 '!C:F,3,0) -> 1061.9469 | J70: =H70*I70 -> 564.91967 | K70: =H70*K43 -> 14.191258 | L70: 15Low-E(双银)+12A+15+12A+15mm全超白钢化中空玻璃（超宽） | N70: =(5.45-0.025*1)*(P44-0.025*0) -> 14.05075 | P70: 1 | Q70: =N70*P70 -> 14.05075 | R70: =Q70/R44 -> 0.52669903
B71: 15
B72: 16
B73: 17
B74: 18
B75: 19
B76: 20
B77: 21
B78: 22
B79: 23
B80: 24 | D80: 辅材材料费 | E80: m2 | G80: 1 | H80: 1 | I80: =+辅材及安装费!$E$5 -> 5 | J80: =H80*I80 -> 5
B81: 25 | D81: 材料费合计 | J81: =SUM(J57:J80) -> 974.9702
B82: 1 | C82: 其他费 | D82: 机械费+运输费 | E82: m2 | H82: 1 | I82: =+辅材及安装费!$F$5 -> 5 | J82: =H82*I82 -> 5
B83: 综合单价分析表
A84: 1 | B84: 序号 | C84: 清单项名称： | D84: =+A92 -> 25㎜葡萄牙灰石材 | F84: 石材幕墙 | H84: 费率 | I84: 金额 | J84: 单位 | K84: =VLOOKUP(A84,排屋工程量清单!$A$49:$D$57,4,) -> 67.8042
B85: 1 | C85: 直接工程费 | D85: 人工费 | I85: =J97 -> 210 | J85: 元 | L85: 西立面 | M85: 1-1剖/JD-132 | O85: 11.35 | P85: 0.55 | Q85: 1 | R85: =+Q85*P85*O85 -> 6.2425
B86: 2 | D86: 材料费 | I86: =J121 -> 899.26178 | J86: 元 | L86: 石材幕墙
B87: 3 | D87: 机械费 | I87: =J122 -> 5 | J87: 元 | M87: 名称 | N87: 米重 | O87: 长/宽 | P87: 数量 | Q87: 总重 | R87: 单方
B88: 4 | C88: 直接费 | D88: (1)+（2）+（3） | I88: =SUM(I85:I87) -> 1114.2618 | J88: 元 | L88: 热镀锌钢管 | M88: 80x60x5矩形钢管 | N88: 10.21 | O88: =+P85 -> 0.55 | P88: 10 | Q88: =+P88*O88*N88 -> 56.155 | R88: =+Q88/R85 -> 8.9955947
B89: 5 | C89: 公司管理、利润 | D89: （4）*a% | H89: =+'材料表 '!$E$178 -> 0 | I89: =H89*I88 -> 0 | J89: 元 | L89: 热镀锌角钢 | M89: L50*5 | N89: 3.77 | O89: =+O85 -> 11.35 | P89: 2 | Q89: =+P89*O89*N89 -> 85.579 | R89: =+Q89/R85 -> 13.709091
B90: 6 | C90: 现场管理费 | D90: （4）*b% | H90: =+'材料表 '!$E$179 -> 0 | I90: =H90*I88 -> 0 | J90: 元 | L90: 热镀锌埋件 | M90: 150*200*10 | N90: =0.15*0.2*7.85*10 -> 2.355 | O90: 2 | P90: =+P88 -> 10 | Q90: =+P90*O90*N90 -> 47.1 | R90: =+Q90/R85 -> 7.5450541
B91: 7 | C91: 税金 | D91: [(4)+(5)+(6)]*c% | H91: =+'材料表 '!$E$180 -> 0.09 | I91: =(I88+I89+I90)*H91 -> 100.28356 | J91: 元 | L91: 热镀锌钢连接件 | M91: L=150 | N91: =3.77 -> 3.77 | O91: 0.155 | P91: 0 | Q91: =+P91*O91*N91 -> 0 | R91: =+Q91/R85 -> 0
A92: 25㎜葡萄牙灰石材 | B92: 8 | C92: 综合单价 | D92: （4）-（7）之和 | I92: =SUM(I88:I91) -> 1214.5453 | J92: 元/m² | L92: 热镀锌钢连接件 | M92: 钢芯60*40*4 | N92: 5.778 | O92: 0.125 | P92: =+P88*2 -> 20 | Q92: =+P92*O92*N92 -> 14.445 | R92: =+Q92/R85 -> 2.3139768
B93: 其中 | L93: 铝合金挂件 | O93: =15*4 -> 60 | P93: 1 | Q93: =+P93*O93 -> 60 | R93: =+Q93/R85 -> 9.6115338
B94: 1 | C94: 人工费 | D94: 名称 | E94: 单位 | H94: 数量 | I94: 单价 | J94: 金额（元）
B95: 2 | D95: 石材幕墙人工制作安装费 | E95: ㎡ | H95: 1 | I95: =+辅材及安装费!$G$8 -> 210 | J95: =H95*I95 -> 210 | L95: 后切式背栓-M8 | Q95: =+Q93 -> 60 | R95: =+Q95/R85 -> 9.6115338
B96: 3 | L96: M12x120不锈钢螺栓 | P96: =+P91 -> 0 | Q96: =+P96 -> 0 | R96: =+Q96/R85 -> 0
B97: 4 | D97: 人工费合计 | E97: 元 | J97: =SUM(J95:J95) -> 210 | L97: 不锈钢螺栓-M8x35 | Q97: =+(Q93)*3 -> 180 | R97: =+Q97/R85 -> 28.834602
B98: 1 | C98: 材料费 | D98: 热镀锌钢管 | E98: =+VLOOKUP(D98,'材料表 '!C:F,2,0) -> kg | F98: =+SUMIF($L$86:$L$122,D98,$R$86:$R$122) -> 8.9955947 | G98: =+VLOOKUP(D98,'材料表 '!C:F,4,0) -> 0.03 | H98: =F98*(G98+1) -> 9.2654626 | I98: =+VLOOKUP(D98,'材料表 '!C:F,3,0) -> 3.8053097 | J98: =H98*I98 -> 35.257955 | K98: =H98*K84 -> 628.23728
B99: 2 | D99: 热镀锌角钢 | E99: =+VLOOKUP(D99,'材料表 '!C:F,2,0) -> kg | F99: =+SUMIF($L$86:$L$122,D99,$R$86:$R$122) -> 13.709091 | G99: =+VLOOKUP(D99,'材料表 '!C:F,4,0) -> 0.03 | H99: =F99*(G99+1) -> 14.120364 | I99: =+VLOOKUP(D99,'材料表 '!C:F,3,0) -> 3.539823 | J99: =H99*I99 -> 49.983588 | K99: =H99*K84 -> 957.41996
B100: 3 | D100: 热镀锌钢连接件 | E100: =+VLOOKUP(D100,'材料表 '!C:F,2,0) -> kg | F100: =+SUMIF($L$86:$L$122,D100,$R$86:$R$122) -> 2.3139768 | G100: =+VLOOKUP(D100,'材料表 '!C:F,4,0) -> 0.03 | H100: =F100*(G100+1) -> 2.3833961 | I100: =+VLOOKUP(D100,'材料表 '!C:F,3,0) -> 6.0176991 | J100: =H100*I100 -> 14.34256 | K100: =H100*K84 -> 161.60426 | L100: M12化学锚栓 | Q100: =+O90*P90*4 -> 80 | R100: =+Q100/R85 -> 12.815378
...

Sheet 材料表 
A1: 材料表
A2: 序号 | B2: 分类 | C2: 项目名称 | D2: 单位 | E2: 不含税综合单价（元/单位） | F2: 材料损耗率 | G2: 备注 | I2: 含税单价 | K2: 11#楼 | L2: 1#2#商业
A3: 1 | B3: 石材 | C3: 25㎜葡萄牙灰石材 | D3: m2 | E3: =+I3/H3 -> 623.89381 | F3: 0.02 | H3: 1.13 | I3: =680+J4 -> 705 | J3: 加工增加费 | K3: =SUMIF('综合单价分析表 (11#楼)'!D:D,C3,'综合单价分析表 (11#楼)'!K:K) -> 366.63781 | L3: =SUMIF('综合单价分析表（商业）'!D:D,C3,'综合单价分析表（商业）'!K:K) -> 0
A4: =MAX($A$3:$A3)+1 -> 2 | C4: 25㎜葡萄牙灰石材（圆弧） | D4: m2 | E4: =+I4/H4 -> 1402.6549 | F4: 0.02 | H4: 1.13 | I4: =1560+J4 -> 1585 | J4: 25 | K4: =SUMIF('综合单价分析表 (11#楼)'!D:D,C4,'综合单价分析表 (11#楼)'!K:K) -> 54.888547 | L4: =SUMIF('综合单价分析表（商业）'!D:D,C4,'综合单价分析表（商业）'!K:K) -> 0
A5: =MAX($A$3:$A4)+1 -> 3 | C5: 25㎜葡萄牙米黄石材 | D5: m2 | E5: =+I5/H5 -> 358.40708 | F5: 0.02 | H5: 1.13 | I5: =380+J4 -> 405 | K5: =SUMIF('综合单价分析表 (11#楼)'!D:D,C5,'综合单价分析表 (11#楼)'!K:K) -> 134.7826 | L5: =SUMIF('综合单价分析表（商业）'!D:D,C5,'综合单价分析表（商业）'!K:K) -> 0
A6: =MAX($A$3:$A5)+1 -> 4 | C6: 25㎜葡萄牙米黄石材（圆弧） | D6: m2 | E6: =+I6/H6 -> 995.57522 | F6: 0.02 | H6: 1.13 | I6: =1100+J4 -> 1125 | K6: =SUMIF('综合单价分析表 (11#楼)'!D:D,C6,'综合单价分析表 (11#楼)'!K:K) -> 26.95652 | L6: =SUMIF('综合单价分析表（商业）'!D:D,C6,'综合单价分析表（商业）'!K:K) -> 0
A7: =MAX($A$3:$A6)+1 -> 5 | C7: 25㎜葡萄牙米黄石材线条 | D7: 米 | E7: =+I7/H7 -> 402.65487 | F7: 0.02 | H7: 1.13 | I7: =430+J4 -> 455 | K7: =SUMIF('综合单价分析表 (11#楼)'!D:D,C7,'综合单价分析表 (11#楼)'!K:K) -> 210.4032 | L7: =SUMIF('综合单价分析表（商业）'!D:D,C7,'综合单价分析表（商业）'!K:K) -> 0
A8: =MAX($A$3:$A7)+1 -> 6 | C8: 35㎜蓝眼睛石材（凹槽） | D8: m2 | E8: =+I8/H8 -> 535.39823 | F8: 0.05 | H8: 1.13 | I8: =580+J4 -> 605 | K8: =SUMIF('综合单价分析表 (11#楼)'!D:D,C8,'综合单价分析表 (11#楼)'!K:K) -> 123.69472 | L8: =SUMIF('综合单价分析表（商业）'!D:D,C8,'综合单价分析表（商业）'!K:K) -> 0
A9: =MAX($A$3:$A8)+1 -> 7 | C9: 35㎜蓝眼睛石材（凹槽）圆弧 | D9: m2 | E9: =+I9/H9 -> 1305.3097 | F9: 0.05 | H9: 1.13 | I9: =1450+J4 -> 1475 | K9: =SUMIF('综合单价分析表 (11#楼)'!D:D,C9,'综合单价分析表 (11#楼)'!K:K) -> 24.738945 | L9: =SUMIF('综合单价分析表（商业）'!D:D,C9,'综合单价分析表（商业）'!K:K) -> 0
A10: =MAX($A$3:$A9)+1 -> 8 | C10: 50㎜蓝眼睛石材（光面） | D10: m2 | E10: =+I10/H10 -> 774.33628 | F10: 0.02 | G10: 需确认厚度 | H10: 1.13 | I10: =850+J4 -> 875 | K10: =SUMIF('综合单价分析表 (11#楼)'!D:D,C10,'综合单价分析表 (11#楼)'!K:K) -> 3.758412 | L10: =SUMIF('综合单价分析表（商业）'!D:D,C10,'综合单价分析表（商业）'!K:K) -> 0
A11: 2 | C11: 30mm厚光面福鼎黑石材（造型柱基座） | D11: m2 | E11: =+I11/H11 -> 553.09735 | F11: 0.06 | G11: 带圆弧 | H11: 1.13 | I11: =600+J4 -> 625 | K11: =SUMIF('综合单价分析表 (11#楼)'!D:D,C11,'综合单价分析表 (11#楼)'!K:K) -> 0 | L11: =SUMIF('综合单价分析表（商业）'!D:D,C11,'综合单价分析表（商业）'!K:K) -> 12.978
A12: =MAX($A$3:$A11)+1 -> 9 | C12: 30mm厚光面贝金米黄石材 | D12: m2 | E12: =+I12/H12 -> 774.33628 | F12: 0.02 | H12: 1.13 | I12: =850+J4 -> 875 | K12: =SUMIF('综合单价分析表 (11#楼)'!D:D,C12,'综合单价分析表 (11#楼)'!K:K) -> 0 | L12: =SUMIF('综合单价分析表（商业）'!D:D,C12,'综合单价分析表（商业）'!K:K) -> 892.92185
A13: =MAX($A$3:$A12)+1 -> 10 | C13: 30mm厚光面贝金米黄石材（弧形） | D13: m2 | E13: =+I13/H13 -> 3119.469 | F13: 0.06 | H13: 1.13 | I13: =3500+J4 -> 3525 | K13: =SUMIF('综合单价分析表 (11#楼)'!D:D,C13,'综合单价分析表 (11#楼)'!K:K) -> 0 | L13: =SUMIF('综合单价分析表（商业）'!D:D,C13,'综合单价分析表（商业）'!K:K) -> 123.73803
A14: =MAX($A$3:$A13)+1 -> 11 | C14: 25mm厚透光云石造型柱 | D14: m2 | E14: =+I14/H14 -> 641.59292 | F14: 0.05 | H14: 1.13 | I14: =700+J4 -> 725 | K14: =SUMIF('综合单价分析表 (11#楼)'!D:D,C14,'综合单价分析表 (11#楼)'!K:K) -> 0 | L14: =SUMIF('综合单价分析表（商业）'!D:D,C14,'综合单价分析表（商业）'!K:K) -> 27.88
A15: =MAX($A$3:$A14)+1 -> 12 | C15: 30mm厚光面深灰色石材 | D15: m2 | E15: =+I15/H15 -> 623.89381 | F15: 0.02 | H15: 1.13 | I15: =680+J4 -> 705 | K15: =SUMIF('综合单价分析表 (11#楼)'!D:D,C15,'综合单价分析表 (11#楼)'!K:K) -> 0 | L15: =SUMIF('综合单价分析表（商业）'!D:D,C15,'综合单价分析表（商业）'!K:K) -> 15.82266
A16: =MAX($A$3:$A15)+1 -> 13 | C16: 40mm厚自然面贝金米黄石材 | D16: m2 | E16: =+I16/H16 -> 1084.0708 | F16: 0.02 | H16: 1.13 | I16: =1200+J4 -> 1225 | K16: =SUMIF('综合单价分析表 (11#楼)'!D:D,C16,'综合单价分析表 (11#楼)'!K:K) -> 0 | L16: =SUMIF('综合单价分析表（商业）'!D:D,C16,'综合单价分析表（商业）'!K:K) -> 47.153264
A17: =MAX($A$3:$A16)+1 -> 14 | C17: 40mm厚拉槽面贝金米黄石材 | D17: m2 | E17: =+I17/H17 -> 1305.3097 | F17: 0.02 | H17: 1.13 | I17: =1450+J4 -> 1475 | K17: =SUMIF('综合单价分析表 (11#楼)'!D:D,C17,'综合单价分析表 (11#楼)'!K:K) -> 0 | L17: =SUMIF('综合单价分析表（商业）'!D:D,C17,'综合单价分析表（商业）'!K:K) -> 355.5911
C18: 50㎜厚贝金米黄亚光面石材 | D18: m2 | E18: =+I18/H18 -> 1438.0531 | F18: 0.02 | H18: 1.13 | I18: =1600+J4 -> 1625
A19: =MAX($A$3:$A17)+1 -> 15 | C19: 30mm厚透光云石（造型柱弧形） | D19: m2 | E19: =+I19/H19 -> 840.70796 | F19: 0.02 | H19: 1.13 | I19: =I14+200+J4 -> 950 | K19: =SUMIF('综合单价分析表 (11#楼)'!D:D,C19,'综合单价分析表 (11#楼)'!K:K) -> 0 | L19: =SUMIF('综合单价分析表（商业）'!D:D,C19,'综合单价分析表（商业）'!K:K) -> 42.037008
A20: =MAX($A$3:$A19)+1 -> 16 | C20: 贝金米黄石材拉槽线条1 | D20: 米 | E20: =+I20/H20 -> 225.66372 | F20: 0.02 | G20: 75*77㎜ | H20: 1.13 | I20: =230+J4 -> 255 | K20: =SUMIF('综合单价分析表 (11#楼)'!D:D,C20,'综合单价分析表 (11#楼)'!K:K) -> 0 | L20: =SUMIF('综合单价分析表（商业）'!D:D,C20,'综合单价分析表（商业）'!K:K) -> 98.0912
A21: =MAX($A$3:$A20)+1 -> 17 | C21: 贝金米黄石材拉槽线条2 | D21: 米 | E21: =+I21/H21 -> 889.38053 | F21: 0.02 | G21: 200*200㎜，R=200 | H21: 1.13 | I21: =980+J4 -> 1005 | J21: 加工增加费 | K21: =SUMIF('综合单价分析表 (11#楼)'!D:D,C21,'综合单价分析表 (11#楼)'!K:K) -> 0 | L21: =SUMIF('综合单价分析表（商业）'!D:D,C21,'综合单价分析表（商业）'!K:K) -> 98.0912
A22: =MAX($A$3:$A21)+1 -> 18 | B22: 铝板 | C22: 2.5mm厚铝单板(香槟色) | D22: m2 | E22: =+I22/H22 -> 257.52212 | F22: 0.02 | H22: 1.13 | I22: =261+5+J22 -> 291 | J22: 25 | K22: =SUMIF('综合单价分析表 (11#楼)'!D:D,C22,'综合单价分析表 (11#楼)'!K:K) -> 10.05312 | L22: =SUMIF('综合单价分析表（商业）'!D:D,C22,'综合单价分析表（商业）'!K:K) -> 31.789192
A23: =MAX($A$3:$A22)+1 -> 19 | C23: 2.5mm厚铝单板 | D23: m2 | E23: =+I23/H23 -> 253.09735 | F23: 0.02 | H23: 1.13 | I23: =261+J22 -> 286 | K23: =SUMIF('综合单价分析表 (11#楼)'!D:D,C23,'综合单价分析表 (11#楼)'!K:K) -> 0 | L23: =SUMIF('综合单价分析表（商业）'!D:D,C23,'综合单价分析表（商业）'!K:K) -> 208.08
A24: =MAX($A$3:$A23)+1 -> 20 | C24: 2.5mm厚铝单板(浅灰色) | D24: m2 | E24: =+I24/H24 -> 253.09735 | F24: 0.02 | H24: 1.13 | I24: =261+J22 -> 286 | K24: =SUMIF('综合单价分析表 (11#楼)'!D:D,C24,'综合单价分析表 (11#楼)'!K:K) -> 287.29954 | L24: =SUMIF('综合单价分析表（商业）'!D:D,C24,'综合单价分析表（商业）'!K:K) -> 1479.1617
A25: =MAX($A$3:$A24)+1 -> 21 | C25: 2.5mm厚铝单板(浅灰色)弧形 | D25: m2 | E25: =+I25/H25 -> 261.9469 | F25: 0.02 | H25: 1.13 | I25: =261+10+J22 -> 296 | K25: =SUMIF('综合单价分析表 (11#楼)'!D:D,C25,'综合单价分析表 (11#楼)'!K:K) -> 3.7562633 | L25: =SUMIF('综合单价分析表（商业）'!D:D,C25,'综合单价分析表（商业）'!K:K) -> 0
A26: =MAX($A$3:$A25)+1 -> 22 | C26: 2.5mm厚铝单板(浅灰色)超长板 | D26: m2 | E26: =+I26/H26 -> 261.9469 | F26: 0.02 | G26: 屋面 | H26: 1.13 | I26: =261+10+J22 -> 296 | K26: =SUMIF('综合单价分析表 (11#楼)'!D:D,C26,'综合单价分析表 (11#楼)'!K:K) -> 350.97282 | L26: =SUMIF('综合单价分析表（商业）'!D:D,C26,'综合单价分析表（商业）'!K:K) -> 0
A27: =MAX($A$3:$A26)+1 -> 23 | C27: 2.5mm厚铝单板(浅灰色)超长板带圆弧 | D27: m2 | E27: =+I27/H27 -> 270.79646 | F27: 0.02 | G27: 北立面墙面 | H27: 1.13 | I27: =261+20+J22 -> 306 | K27: =SUMIF('综合单价分析表 (11#楼)'!D:D,C27,'综合单价分析表 (11#楼)'!K:K) -> 148.09678 | L27: =SUMIF('综合单价分析表（商业）'!D:D,C27,'综合单价分析表（商业）'!K:K) -> 0
A28: =MAX($A$3:$A27)+1 -> 24 | C28: 2.5mm厚铝单板(中灰色) | D28: m2 | E28: =+I28/H28 -> 253.09735 | F28: 0.02 | H28: 1.13 | I28: =261+J22 -> 286 | K28: =SUMIF('综合单价分析表 (11#楼)'!D:D,C28,'综合单价分析表 (11#楼)'!K:K) -> 186.68404 | L28: =SUMIF('综合单价分析表（商业）'!D:D,C28,'综合单价分析表（商业）'!K:K) -> 1.071
A29: =MAX($A$3:$A28)+1 -> 25 | C29: 2.5mm厚铝单板(浅灰色带弧形造型) | D29: m2 | E29: =+I29/H29 -> 270.79646 | F29: 0.02 | H29: 1.13 | I29: =261+20+J22 -> 306 | K29: =SUMIF('综合单价分析表 (11#楼)'!D:D,C29,'综合单价分析表 (11#楼)'!K:K) -> 124.22539 | L29: =SUMIF('综合单价分析表（商业）'!D:D,C29,'综合单价分析表（商业）'!K:K) -> 0
A30: =MAX($A$3:$A29)+1 -> 26 | C30: 2.5mm厚铝单板(银灰色) | D30: m2 | E30: =+I30/H30 -> 253.09735 | F30: 0.02 | H30: 1.13 | I30: =261+J22 -> 286 | K30: =SUMIF('综合单价分析表 (11#楼)'!D:D,C30,'综合单价分析表 (11#楼)'!K:K) -> 400.00402 | L30: =SUMIF('综合单价分析表（商业）'!D:D,C30,'综合单价分析表（商业）'!K:K) -> 1266.2836
A31: =MAX($A$3:$A30)+1 -> 27 | C31: 2.5mm厚铝单板(银灰色)弧形 | D31: m2 | E31: =+I31/H31 -> 261.9469 | F31: 0.02 | H31: 1.13 | I31: =261+10+J22 -> 296 | K31: =SUMIF('综合单价分析表 (11#楼)'!D:D,C31,'综合单价分析表 (11#楼)'!K:K) -> 45.291231 | L31: =SUMIF('综合单价分析表（商业）'!D:D,C31,'综合单价分析表（商业）'!K:K) -> 37.532573
A32: =MAX($A$3:$A31)+1 -> 28 | C32: 2.5mm厚铝单板(香槟色)弧形 | D32: m2 | E32: =+I32/H32 -> 266.37168 | F32: 0.02 | H32: 1.13 | I32: =261+5+10+J22 -> 301 | K32: =SUMIF('综合单价分析表 (11#楼)'!D:D,C32,'综合单价分析表 (11#楼)'!K:K) -> 1.945344 | L32: =SUMIF('综合单价分析表（商业）'!D:D,C32,'综合单价分析表（商业）'!K:K) -> 6.3578385
A33: =MAX($A$3:$A32)+1 -> 29 | C33: 2.5mm厚瓦楞铝板(浅灰色) | D33: m2 | E33: =+I33/H33 -> 319.46903 | F33: 0.02 | H33: 1.13 | I33: =336+J22 -> 361 | K33: =SUMIF('综合单价分析表 (11#楼)'!D:D,C33,'综合单价分析表 (11#楼)'!K:K) -> 5.6114662 | L33: =SUMIF('综合单价分析表（商业）'!D:D,C33,'综合单价分析表（商业）'!K:K) -> 0
A34: =MAX($A$3:$A33)+1 -> 30 | C34: 4mm厚穿孔铝单板(香槟色) | D34: m2 | E34: =+I34/H34 -> 361.06195 | F34: 0.02 | H34: 1.13 | I34: =373+10+J22 -> 408 | K34: =SUMIF('综合单价分析表 (11#楼)'!D:D,C34,'综合单价分析表 (11#楼)'!K:K) -> 258.12189 | L34: =SUMIF('综合单价分析表（商业）'!D:D,C34,'综合单价分析表（商业）'!K:K) -> 0
A35: =MAX($A$3:$A34)+1 -> 31 | C35: 4mm厚穿孔铝单板(香槟色)弧形 | D35: m2 | E35: =+I35/H35 -> 265.48673 | F35: 0.02 | H35: 1.13 | I35: 300 | K35: =SUMIF('综合单价分析表 (11#楼)'!D:D,C35,'综合单价分析表 (11#楼)'!K:K) -> 9.7279358 | L35: =SUMIF('综合单价分析表（商业）'!D:D,C35,'综合单价分析表（商业）'!K:K) -> 0
A36: =MAX($A$3:$A35)+1 -> 32 | C36: 2.5mm厚铝单板（中灰色/浅灰色双色) | D36: m2 | E36: =+I36/H36 -> 272.56637 | F36: 0.02 | H36: 1.13 | I36: =283+J22 -> 308 | K36: =SUMIF('综合单价分析表 (11#楼)'!D:D,C36,'综合单价分析表 (11#楼)'!K:K) -> 114.51041 | L36: =SUMIF('综合单价分析表（商业）'!D:D,C36,'综合单价分析表（商业）'!K:K) -> 0
A37: =MAX($A$3:$A36)+1 -> 33 | C37: 2.5mm厚铝单板（中灰色/浅灰色双色)弧形 | D37: m2 | E37: =+I37/H37 -> 281.41593 | F37: 0.02 | H37: 1.13 | I37: =283+10+J22 -> 318 | K37: =SUMIF('综合单价分析表 (11#楼)'!D:D,C37,'综合单价分析表 (11#楼)'!K:K) -> 5.5558384 | L37: =SUMIF('综合单价分析表（商业）'!D:D,C37,'综合单价分析表（商业）'!K:K) -> 0
A38: =MAX($A$3:$A37)+1 -> 34 | C38: 2.5mm厚蓝眼睛仿石铝板（带圆弧，带拉槽） | D38: m2 | E38: =+I38/H38 -> 270.79646 | F38: 0.02 | G38: 上下边带圆弧，带拉槽 | H38: 1.13 | I38: =261+10+10+J22 -> 306 | K38: =SUMIF('综合单价分析表 (11#楼)'!D:D,C38,'综合单价分析表 (11#楼)'!K:K) -> 88.53287 | L38: =SUMIF('综合单价分析表（商业）'!D:D,C38,'综合单价分析表（商业）'!K:K) -> 0
A39: =MAX($A$3:$A38)+1 -> 35 | C39: 2.5mm厚蓝眼睛仿石铝板（四边带圆弧） | D39: m2 | E39: =+I39/H39 -> 266.37168 | F39: 0.02 | G39: 上下边带圆弧，带拉槽 | H39: 1.13 | I39: =261+15+J22 -> 301 | K39: =SUMIF('综合单价分析表 (11#楼)'!D:D,C39,'综合单价分析表 (11#楼)'!K:K) -> 0 | L39: =SUMIF('综合单价分析表（商业）'!D:D,C39,'综合单价分析表（商业）'!K:K) -> 0
A40: =MAX($A$3:$A39)+1 -> 36 | C40: 2.5mm厚葡萄牙米黄仿石铝板（瓦楞板） | D40: m2 | E40: =+I40/H40 -> 287.61062 | F40: 0.02 | H40: 1.13 | I40: =300+J22 -> 325 | K40: =SUMIF('综合单价分析表 (11#楼)'!D:D,C40,'综合单价分析表 (11#楼)'!K:K) -> 179.05714 | L40: =SUMIF('综合单价分析表（商业）'!D:D,C40,'综合单价分析表（商业）'!K:K) -> 0
A41: =MAX($A$3:$A40)+1 -> 37 | C41: 2.5mm厚葡萄牙米黄仿石铝板（瓦楞板）弧形 | D41: m2 | E41: =+I41/H41 -> 305.30973 | F41: 0.02 | H41: 1.13 | I41: =300+20+J22 -> 345 | K41: =SUMIF('综合单价分析表 (11#楼)'!D:D,C41,'综合单价分析表 (11#楼)'!K:K) -> 15.658191 | L41: =SUMIF('综合单价分析表（商业）'!D:D,C41,'综合单价分析表（商业）'!K:K) -> 0
A42: =MAX($A$3:$A41)+1 -> 38 | C42: 2.5mm厚铝单板(中灰色/香槟色双色) | D42: m2 | E42: =+I42/H42 -> 276.99115 | F42: 0.02 | H42: 1.13 | I42: =283+5+J22 -> 313 | K42: =SUMIF('综合单价分析表 (11#楼)'!D:D,C42,'综合单价分析表 (11#楼)'!K:K) -> 37.582301 | L42: =SUMIF('综合单价分析表（商业）'!D:D,C42,'综合单价分析表（商业）'!K:K) -> 0
A43: =MAX($A$3:$A42)+1 -> 39 | C43: 2.5mm厚铝单板(中灰色/香槟色双色)弧形 | D43: m2 | E43: =+I43/H43 -> 285.84071 | F43: 0.02 | H43: 1.13 | I43: =283+5+10+J22 -> 323 | K43: =SUMIF('综合单价分析表 (11#楼)'!D:D,C43,'综合单价分析表 (11#楼)'!K:K) -> 1.6591399 | L43: =SUMIF('综合单价分析表（商业）'!D:D,C43,'综合单价分析表（商业）'!K:K) -> 0
A44: =MAX($A$3:$A43)+1 -> 40 | C44: 3㎜铝芯复合板（玻璃背称） | D44: m2 | E44: =+I44/H44 -> 247.78761 | F44: 0.02 | H44: 1.13 | I44: =280 -> 280 | K44: =SUMIF('综合单价分析表 (11#楼)'!D:D,C44,'综合单价分析表 (11#楼)'!K:K) -> 11.137391 | L44: =SUMIF('综合单价分析表（商业）'!D:D,C44,'综合单价分析表（商业）'!K:K) -> 0
A45: =MAX($A$3:$A44)+1 -> 41 | C45: 2.5mm厚铝单板(中灰色仿石铝板) | D45: m2 | E45: =+I45/H45 -> 249.55752 | F45: 0.02 | H45: 1.13 | I45: =257+J22 -> 282 | K45: =SUMIF('综合单价分析表 (11#楼)'!D:D,C45,'综合单价分析表 (11#楼)'!K:K) -> 0 | L45: =SUMIF('综合单价分析表（商业）'!D:D,C45,'综合单价分析表（商业）'!K:K) -> 50.675049
A46: =MAX($A$3:$A45)+1 -> 42 | C46: 2.5mm厚铝单板(中灰色仿石铝板)弧形 | D46: m2 | E46: =+I46/H46 -> 280.53097 | F46: 0.02 | H46: 1.13 | I46: =I45+10+J22 -> 317 | K46: =SUMIF('综合单价分析表 (11#楼)'!D:D,C46,'综合单价分析表 (11#楼)'!K:K) -> 0 | L46: =SUMIF('综合单价分析表（商业）'!D:D,C46,'综合单价分析表（商业）'!K:K) -> 8.6722854
A47: =MAX($A$3:$A46)+1 -> 43 | C47: 1.5mm厚香槟色铝合金瓦楞板 | D47: m2 | E47: =+I47/H47 -> 207.9646 | F47: 0.02 | H47: 1.13 | I47: =210+J22 -> 235 | K47: =SUMIF('综合单价分析表 (11#楼)'!D:D,C47,'综合单价分析表 (11#楼)'!K:K) -> 0 | L47: =SUMIF('综合单价分析表（商业）'!D:D,C47,'综合单价分析表（商业）'!K:K) -> 70.279887
A48: =MAX($A$3:$A47)+1 -> 44 | C48: 1.5mm厚香槟色铝合金瓦楞板（弧形） | D48: m2 | E48: =+I48/H48 -> 238.93805 | F48: 0.02 | H48: 1.13 | I48: =I47+10+J22 -> 270 | K48: =SUMIF('综合单价分析表 (11#楼)'!D:D,C48,'综合单价分析表 (11#楼)'!K:K) -> 0 | L48: =SUMIF('综合单价分析表（商业）'!D:D,C48,'综合单价分析表（商业）'!K:K) -> 7.7196456
A49: =MAX($A$3:$A48)+1 -> 45 | C49: 1.5mm厚银灰色铝合金瓦楞板（弯弧造型） | D49: m2 | E49: =+I49/H49 -> 349.55752 | F49: 0.02 | H49: 1.13 | I49: =I48+100+J22 -> 395 | K49: =SUMIF('综合单价分析表 (11#楼)'!D:D,C49,'综合单价分析表 (11#楼)'!K:K) -> 0 | L49: =SUMIF('综合单价分析表（商业）'!D:D,C49,'综合单价分析表（商业）'!K:K) -> 78.202278
A50: =MAX($A$3:$A49)+1 -> 46 | C50: 25㎜香槟色蜂窝铝板 | D50: m2 | E50: =+I50/H50 -> 303.53982 | F50: 0.02 | H50: 1.13 | I50: =318+J22 -> 343 | K50: =SUMIF('综合单价分析表 (11#楼)'!D:D,C50,'综合单价分析表 (11#楼)'!K:K) -> 0 | L50: =SUMIF('综合单价分析表（商业）'!D:D,C50,'综合单价分析表（商业）'!K:K) -> 639.56191
A51: =MAX($A$3:$A50)+1 -> 47 | C51: 25㎜香槟色蜂窝铝板（弧形） | D51: m2 | E51: =+I51/H51 -> 352.21239 | F51: 0.02 | H51: 1.13 | I51: =I50+30+J22 -> 398 | K51: =SUMIF('综合单价分析表 (11#楼)'!D:D,C51,'综合单价分析表 (11#楼)'!K:K) -> 0 | L51: =SUMIF('综合单价分析表（商业）'!D:D,C51,'综合单价分析表（商业）'!K:K) -> 16.971394
A52: =MAX($A$3:$A51)+1 -> 48 | C52: 2.5mm厚铝单板(香槟色)吊顶板 | D52: m2 | E52: =+I52/H52 -> 279.64602 | F52: 0.02 | G52: 超大板 | H52: 1.13 | I52: =I22+J22 -> 316 | K52: =SUMIF('综合单价分析表 (11#楼)'!D:D,C52,'综合单价分析表 (11#楼)'!K:K) -> 0 | L52: =SUMIF('综合单价分析表（商业）'!D:D,C52,'综合单价分析表（商业）'!K:K) -> 716.66826
A53: =MAX($A$3:$A52)+1 -> 49 | C53: 2.0mm厚粉末喷涂铝单板 | D53: m2 | E53: =+I53/H53 -> 186.72566 | F53: 0.02 | G53: 背称 | H53: 1.13 | I53: =186+J22 -> 211 | K53: =SUMIF('综合单价分析表 (11#楼)'!D:D,C53,'综合单价分析表 (11#楼)'!K:K) -> 0 | L53: =SUMIF('综合单价分析表（商业）'!D:D,C53,'综合单价分析表（商业）'!K:K) -> 14.735797
A54: =MAX($A$3:$A53)+1 -> 50 | C54: 3㎜浅灰色穿孔铝板 | D54: m2 | E54: =+I54/H54 -> 270.79646 | F54: 0.02 | G54: 天沟上盖板 | H54: 1.13 | I54: =261+15+5+$J$22 -> 306 | K54: =SUMIF('综合单价分析表 (11#楼)'!D:D,C54,'综合单价分析表 (11#楼)'!K:K) -> 0 | L54: =SUMIF('综合单价分析表（商业）'!D:D,C54,'综合单价分析表（商业）'!K:K) -> 310.44219
A55: =MAX($A$3:$A54)+1 -> 51 | C55: 2.5㎜中灰色瓦楞板 | D55: m2 | E55: =+I55/H55 -> 319.46903 | F55: 0.02 | H55: 1.13 | I55: =I33 -> 361 | J55: 加工增加费 | K55: =SUMIF('综合单价分析表 (11#楼)'!D:D,C55,'综合单价分析表 (11#楼)'!K:K) -> 28.40928 | L55: =SUMIF('综合单价分析表（商业）'!D:D,C55,'综合单价分析表（商业）'!K:K) -> 0
A56: =MAX($A$3:$A55)+1 -> 52 | B56: 玻璃 | C56: 5Low-E(双银)+12A+5+12A+5mm全超白钢化中空玻璃 | D56: m2 | E56: =+I56/H56 -> 132.74336 | F56: 0.01 | H56: 1.13 | I56: 150 | J56: 40 | K56: =SUMIF('综合单价分析表 (11#楼)'!D:D,C56,'综合单价分析表 (11#楼)'!K:K) -> 3.404508 | L56: =SUMIF('综合单价分析表（商业）'!D:D,C56,'综合单价分析表（商业）'!K:K) -> 0
A57: =MAX($A$3:$A56)+1 -> 53 | C57: 6Low-E(双银)+12A+6+12A+6mm全超白钢化中空玻璃 | D57: m2 | E57: =+I57/H57 -> 149.55752 | F57: 0.01 | H57: 1.13 | I57: 169 | K57: =SUMIF('综合单价分析表 (11#楼)'!D:D,C57,'综合单价分析表 (11#楼)'!K:K) -> 0 | L57: =SUMIF('综合单价分析表（商业）'!D:D,C57,'综合单价分析表（商业）'!K:K) -> 0
A58: =MAX($A$3:$A57)+1 -> 54 | C58: 8Low-E(双银)+12A+8+12A+8mm全超白钢化中空玻璃 | D58: m2 | E58: =+I58/H58 -> 177.87611 | F58: 0.01 | H58: 1.13 | I58: 201 | K58: =SUMIF('综合单价分析表 (11#楼)'!D:D,C58,'综合单价分析表 (11#楼)'!K:K) -> 12.490922 | L58: =SUMIF('综合单价分析表（商业）'!D:D,C58,'综合单价分析表（商业）'!K:K) -> 0
A59: =MAX($A$3:$A58)+1 -> 55 | C59: 10Low-E(双银)+12A+10+12A+10mm全超白钢化中空玻璃 | D59: m2 | E59: =+I59/H59 -> 206.19469 | F59: 0.01 | H59: 1.13 | I59: 233 | K59: =SUMIF('综合单价分析表 (11#楼)'!D:D,C59,'综合单价分析表 (11#楼)'!K:K) -> 8.575506 | L59: =SUMIF('综合单价分析表（商业）'!D:D,C59,'综合单价分析表（商业）'!K:K) -> 0
A60: =MAX($A$3:$A59)+1 -> 56 | C60: 12Low-E(双银)+12A+12+12A+12mm全超白钢化中空玻璃 | D60: m2 | E60: =+I60/H60 -> 234.51327 | F60: 0.01 | H60: 1.13 | I60: 265 | K60: =SUMIF('综合单价分析表 (11#楼)'!D:D,C60,'综合单价分析表 (11#楼)'!K:K) -> 0 | L60: =SUMIF('综合单价分析表（商业）'!D:D,C60,'综合单价分析表（商业）'!K:K) -> 0
A61: =MAX($A$3:$A60)+1 -> 57 | C61: 15Low-E(双银)+12A+15+12A+15mm全超白钢化中空玻璃 | D61: m2 | E61: =+I61/H61 -> 373.45133 | F61: 0.01 | H61: 1.13 | I61: 422 | K61: =SUMIF('综合单价分析表 (11#楼)'!D:D,C61,'综合单价分析表 (11#楼)'!K:K) -> 0 | L61: =SUMIF('综合单价分析表（商业）'!D:D,C61,'综合单价分析表（商业）'!K:K) -> 0
A62: =MAX($A$3:$A61)+1 -> 58 | C62: 6Low-E(双银)+12A+6+12A+6mm全超白钢化中空玻璃-弧形 | D62: m2 | E62: =+I62/H62 -> 235.39823 | F62: 0.01 | H62: 1.13 | I62: 266 | K62: =SUMIF('综合单价分析表 (11#楼)'!D:D,C62,'综合单价分析表 (11#楼)'!K:K) -> 0 | L62: =SUMIF('综合单价分析表（商业）'!D:D,C62,'综合单价分析表（商业）'!K:K) -> 0
A63: =MAX($A$3:$A62)+1 -> 59 | C63: 15Low-E(双银)+12A+15+12A+15mm全超白钢化中空玻璃（超宽） | D63: m2 | E63: =+I63/H63 -> 1061.9469 | F63: 0.01 | H63: 1.13 | I63: 1200 | K63: =SUMIF('综合单价分析表 (11#楼)'!D:D,C63,'综合单价分析表 (11#楼)'!K:K) -> 14.191258 | L63: =SUMIF('综合单价分析表（商业）'!D:D,C63,'综合单价分析表（商业）'!K:K) -> 0
A64: =MAX($A$3:$A63)+1 -> 60 | C64: 6Low-E(双银)+12A+6+12A+6mm全超白钢化中空玻璃（弯弧） | D64: m2 | E64: =+I64/H64 -> 179.46903 | F64: 0.01 | H64: 1.13 | I64: =I57*1.2 -> 202.8 | K64: =SUMIF('综合单价分析表 (11#楼)'!D:D,C64,'综合单价分析表 (11#楼)'!K:K) -> 0 | L64: =SUMIF('综合单价分析表（商业）'!D:D,C64,'综合单价分析表（商业）'!K:K) -> 0
A65: =MAX($A$3:$A64)+1 -> 61 | C65: 6Low-E(双银)+12A+6㎜全超白钢化中空玻璃 | D65: m2 | E65: =+I65/H65 -> 135.39823 | F65: 0.01 | H65: 1.13 | I65: =113+J56 -> 153 | K65: =SUMIF('综合单价分析表 (11#楼)'!D:D,C65,'综合单价分析表 (11#楼)'!K:K) -> 0 | L65: =SUMIF('综合单价分析表（商业）'!D:D,C65,'综合单价分析表（商业）'!K:K) -> 157.3275
A66: =MAX($A$3:$A65)+1 -> 62 | C66: 8Low-E(双银)+12A+8㎜全超白钢化中空玻璃 | D66: m2 | E66: =+I66/H66 -> 157.52212 | F66: 0.01 | H66: 1.13 | I66: =138+J56 -> 178 | K66: =SUMIF('综合单价分析表 (11#楼)'!D:D,C66,'综合单价分析表 (11#楼)'!K:K) -> 0 | L66: =SUMIF('综合单价分析表（商业）'!D:D,C66,'综合单价分析表（商业）'!K:K) -> 0
A67: =MAX($A$3:$A66)+1 -> 63 | C67: 10Low-E(双银)+12A+10㎜全超白钢化中空玻璃 | D67: m2 | E67: =+I67/H67 -> 179.64602 | F67: 0.01 | H67: 1.13 | I67: =163+J56 -> 203 | K67: =SUMIF('综合单价分析表 (11#楼)'!D:D,C67,'综合单价分析表 (11#楼)'!K:K) -> 0 | L67: =SUMIF('综合单价分析表（商业）'!D:D,C67,'综合单价分析表（商业）'!K:K) -> 210.11015
A68: =MAX($A$3:$A67)+1 -> 64 | C68: 12Low-E(双银)+12A+12㎜全超白钢化中空玻璃 | D68: m2 | E68: =+I68/H68 -> 210.61947 | F68: 0.01 | H68: 1.13 | I68: =198+J56 -> 238 | K68: =SUMIF('综合单价分析表 (11#楼)'!D:D,C68,'综合单价分析表 (11#楼)'!K:K) -> 0 | L68: =SUMIF('综合单价分析表（商业）'!D:D,C68,'综合单价分析表（商业）'!K:K) -> 53.4593
A69: =MAX($A$3:$A68)+1 -> 65 | C69: 15Low-E(双银)+12A+15㎜全超白钢化中空玻璃 | D69: m2 | E69: =+I69/H69 -> 267.25664 | F69: 0.01 | H69: 1.13 | I69: =262+J56 -> 302 | K69: =SUMIF('综合单价分析表 (11#楼)'!D:D,C69,'综合单价分析表 (11#楼)'!K:K) -> 0 | L69: =SUMIF('综合单价分析表（商业）'!D:D,C69,'综合单价分析表（商业）'!K:K) -> 15.67015
A70: =MAX($A$3:$A69)+1 -> 66 | C70: 6+1.52PVB+6Low-E(双银)+12A+6㎜全超白钢化夹层中空玻璃 | D70: m2 | E70: =+I70/H70 -> 223.00885 | F70: 0.01 | H70: 1.13 | I70: =212+J56 -> 252 | K70: =SUMIF('综合单价分析表 (11#楼)'!D:D,C70,'综合单价分析表 (11#楼)'!K:K) -> 0 | L70: =SUMIF('综合单价分析表（商业）'!D:D,C70,'综合单价分析表（商业）'!K:K) -> 30.664155
A71: =MAX($A$3:$A70)+1 -> 67 | C71: 6+1.52PVB+6Low-E(双银)+12A+10㎜全超白钢化夹层中空玻璃 | D71: m2 | E71: =+I71/H71 -> 241.59292 | F71: 0.01 | H71: 1.13 | I71: =233+J56 -> 273 | K71: =SUMIF('综合单价分析表 (11#楼)'!D:D,C71,'综合单价分析表 (11#楼)'!K:K) -> 0 | L71: =SUMIF('综合单价分析表（商业）'!D:D,C71,'综合单价分析表（商业）'!K:K) -> 145.04625
A72: =MAX($A$3:$A71)+1 -> 68 | C72: 8+1.52PVB+8Low-E(双银)+12A+12㎜全超白钢化夹层中空玻璃 | D72: m2 | E72: =+I72/H72 -> 266.37168 | F72: 0.01 | H72: 1.13 | I72: =261+J56 -> 301 | K72: =SUMIF('综合单价分析表 (11#楼)'!D:D,C72,'综合单价分析表 (11#楼)'!K:K) -> 0 | L72: =SUMIF('综合单价分析表（商业）'!D:D,C72,'综合单价分析表（商业）'!K:K) -> 43.385207
A73: =MAX($A$3:$A72)+1 -> 69 | C73: 8+1.52PVB+8Low-E(双银)+12A+15㎜全超白钢化夹层中空玻璃 | D73: m2 | E73: =+I73/H73 -> 285.84071 | F73: 0.01 | H73: 1.13 | I73: =261+22+J56 -> 323 | K73: =SUMIF('综合单价分析表 (11#楼)'!D:D,C73,'综合单价分析表 (11#楼)'!K:K) -> 0 | L73: =SUMIF('综合单价分析表（商业）'!D:D,C73,'综合单价分析表（商业）'!K:K) -> 19.809837
A74: =MAX($A$3:$A73)+1 -> 70 | C74: 10+1.9SGP+10Low-E(双银)+12A+10㎜全超白钢化夹层中空玻璃 | D74: m2 | E74: =+I74/H74 -> 516.81416 | F74: 0.01 | H74: 1.13 | I74: =544+J56 -> 584 | K74: =SUMIF('综合单价分析表 (11#楼)'!D:D,C74,'综合单价分析表 (11#楼)'!K:K) -> 0 | L74: =SUMIF('综合单价分析表（商业）'!D:D,C74,'综合单价分析表（商业）'!K:K) -> 55.449
A75: =MAX($A$3:$A74)+1 -> 71 | C75: 12+1.9SGP+12㎜全超白钢化夹层玻璃 | D75: m2 | E75: =+I75/H75 -> 483.18584 | F75: 0.01 | G75: （宽1820㎜，高3600㎜） | H75: 1.13 | I75: =466+40+J56 -> 546 | K75: =SUMIF('综合单价分析表 (11#楼)'!D:D,C75,'综合单价分析表 (11#楼)'!K:K) -> 0 | L75: =SUMIF('综合单价分析表（商业）'!D:D,C75,'综合单价分析表（商业）'!K:K) -> 261.21024
A76: =MAX($A$3:$A75)+1 -> 72 | C76: 15+2.28SGP+15全超白钢化夹层玻璃(超宽)（宽7200㎜，高3600㎜） | D76: m2 | E76: =+I76/H76 -> 1362.8319 | F76: 0.01 | H76: 1.13 | I76: =1500+J56 -> 1540 | K76: =SUMIF('综合单价分析表 (11#楼)'!D:D,C76,'综合单价分析表 (11#楼)'!K:K) -> 0 | L76: =SUMIF('综合单价分析表（商业）'!D:D,C76,'综合单价分析表（商业）'!K:K) -> 26.440992
A77: =MAX($A$3:$A76)+1 -> 73 | C77: 12+1.9SGP+12㎜全超白钢化夹层玻璃（弯弧）（弧长1414㎜，高3600㎜，半径900㎜） | D77: m2 | E77: =+I77/H77 -> 873.45133 | F77: 0.01 | H77: 1.13 | I77: =947+J56 -> 987 | K77: =SUMIF('综合单价分析表 (11#楼)'!D:D,C77,'综合单价分析表 (11#楼)'!K:K) -> 0 | L77: =SUMIF('综合单价分析表（商业）'!D:D,C77,'综合单价分析表（商业）'!K:K) -> 20.565216
A78: =MAX($A$3:$A77)+1 -> 74 | C78: 12Low-E(双银)+12A+12㎜全超白钢化中空玻璃（直+弯弧）（直段宽度300㎜+弧长942㎜，圆弧半径600㎜，高3600㎜） | D78: m2 | E78: =+I78/H78 -> 1097.3451 | F78: 0.01 | H78: 1.13 | I78: =1200+J56 -> 1240 | K78: =SUMIF('综合单价分析表 (11#楼)'!D:D,C78,'综合单价分析表 (11#楼)'!K:K) -> 0 | L78: =SUMIF('综合单价分析表（商业）'!D:D,C78,'综合单价分析表（商业）'!K:K) -> 9.031824
A79: =MAX($A$3:$A78)+1 -> 75 | C79: 10Low-E(双银)+12A+10㎜全超白钢化中空玻璃（直+弯弧+直）（直段宽度210㎜+弧长942㎜+直线宽度210㎜，圆弧半径㎜600，高2500㎜） | D79: m2 | E79: =+I79/H79 -> 918.58407 | F79: 0.01 | H79: 1.13 | I79: =998+J56 -> 1038 | K79: =SUMIF('综合单价分析表 (11#楼)'!D:D,C79,'综合单价分析表 (11#楼)'!K:K) -> 0 | L79: =SUMIF('综合单价分析表（商业）'!D:D,C79,'综合单价分析表（商业）'!K:K) -> 6.8781
A80: =MAX($A$3:$A79)+1 -> 76 | C80: 10Low-E(双银)+12A+10㎜全超白钢化中空玻璃（直+弯弧+直）（直段宽度210㎜+弧长1414㎜+直线宽度210㎜，圆弧半径㎜900，高2500㎜） | D80: m2 | E80: =+I80/H80 -> 794.69027 | F80: 0.01 | H80: 1.13 | I80: =858+J56 -> 898 | K80: =SUMIF('综合单价分析表 (11#楼)'!D:D,C80,'综合单价分析表 (11#楼)'!K:K) -> 0 | L80: =SUMIF('综合单价分析表（商业）'!D:D,C80,'综合单价分析表（商业）'!K:K) -> 0
A81: =MAX($A$3:$A80)+1 -> 77 | C81: 8+1.52+8全超白钢化夹层玻璃（弯弧）（弧长942㎜，高3035㎜，半径600㎜） | D81: m2 | E81: =+I81/H81 -> 292.0354 | F81: 0.01 | H81: 1.13 | I81: =290+J56 -> 330 | K81: =SUMIF('综合单价分析表 (11#楼)'!D:D,C81,'综合单价分析表 (11#楼)'!K:K) -> 0 | L81: =SUMIF('综合单价分析表（商业）'!D:D,C81,'综合单价分析表（商业）'!K:K) -> 0
A82: =MAX($A$3:$A81)+1 -> 78 | C82: 8+1.52+8全超白钢化夹层玻璃（弯弧）（弧长1414㎜，高3035㎜，半径900㎜） | D82: m2 | E82: =+I82/H82 -> 292.0354 | F82: 0.01 | H82: 1.13 | I82: =290+J56 -> 330 | K82: =SUMIF('综合单价分析表 (11#楼)'!D:D,C82,'综合单价分析表 (11#楼)'!K:K) -> 0 | L82: =SUMIF('综合单价分析表（商业）'!D:D,C82,'综合单价分析表（商业）'!K:K) -> 42.746306
A83: =MAX($A$3:$A82)+1 -> 79 | C83: 8+1.52PVB+8Low-E(双银)+12A+12全超白钢化夹层中空玻璃（直+弯弧+直）（直段宽度210㎜+弧长942㎜+直线宽度210㎜，圆弧半径㎜600，高3500㎜） | D83: m2 | E83: =+I83/H83 -> 1273.4513 | F83: 0.01 | H83: 1.13 | I83: =1399+J56 -> 1439 | K83: =SUMIF('综合单价分析表 (11#楼)'!D:D,C83,'综合单价分析表 (11#楼)'!K:K) -> 0 | L83: =SUMIF('综合单价分析表（商业）'!D:D,C83,'综合单价分析表（商业）'!K:K) -> 0
A84: =MAX($A$3:$A83)+1 -> 80 | C84: 6+1.52PVB+6Low-E(双银)+12A+6全超白钢化夹层中空玻璃（直+弯弧+直）（直段宽度210㎜+弧长942㎜+直段宽度210㎜，圆弧半径㎜600，高620㎜） | D84: m2 | E84: =+I84/H84 -> 1076.9912 | F84: 0.01 | H84: 1.13 | I84: =1177+J56 -> 1217 | K84: =SUMIF('综合单价分析表 (11#楼)'!D:D,C84,'综合单价分析表 (11#楼)'!K:K) -> 0 | L84: =SUMIF('综合单价分析表（商业）'!D:D,C84,'综合单价分析表（商业）'!K:K) -> 0
A85: =MAX($A$3:$A84)+1 -> 81 | C85: 8+1.52PVB+8Low-E(双银)+12A+12全超白钢化夹层中空玻璃（直+弯弧+直）（直段宽度210㎜+弧长1414㎜+直段宽度210㎜，圆弧半径㎜900，高2300㎜） | D85: m2 | E85: =+I85/H85 -> 1273.4513 | F85: 0.01 | H85: 1.13 | I85: =I83 -> 1439 | K85: =SUMIF('综合单价分析表 (11#楼)'!D:D,C85,'综合单价分析表 (11#楼)'!K:K) -> 0 | L85: =SUMIF('综合单价分析表（商业）'!D:D,C85,'综合单价分析表（商业）'!K:K) -> 0
A86: =MAX($A$3:$A85)+1 -> 82 | C86: 6+1.52PVB+6Low-E(双银)+12A+6全超白钢化夹层中空玻璃（直+弯弧+直）（直段宽度210㎜+弧长1414㎜+直段宽度210㎜，圆弧半径㎜900，高620㎜） | D86: m2 | E86: =+I86/H86 -> 1076.9912 | F86: 0.01 | H86: 1.13 | I86: =I84 -> 1217 | K86: =SUMIF('综合单价分析表 (11#楼)'!D:D,C86,'综合单价分析表 (11#楼)'!K:K) -> 0 | L86: =SUMIF('综合单价分析表（商业）'!D:D,C86,'综合单价分析表（商业）'!K:K) -> 0
A87: =MAX($A$3:$A86)+1 -> 83 | C87: 6Low-E(双银)+12A+6mm全超白钢化中空玻璃（直+弯弧+直）（直段宽度210㎜+弧长1414㎜+直段宽度210㎜，圆弧半径㎜900，高620㎜） | D87: m2 | E87: =+I87/H87 -> 833.62832 | F87: 0.01 | H87: 1.13 | I87: =902+J56 -> 942 | K87: =SUMIF('综合单价分析表 (11#楼)'!D:D,C87,'综合单价分析表 (11#楼)'!K:K) -> 0 | L87: =SUMIF('综合单价分析表（商业）'!D:D,C87,'综合单价分析表（商业）'!K:K) -> 8.9878486
A88: =MAX($A$3:$A87)+1 -> 84 | C88: 12+1.9SGP+12全超白钢化夹层玻璃（弯弧）（弧长1135㎜，高3600㎜，半径900㎜） | D88: m2 | E88: =+I88/H88 -> 876.10619 | F88: 0.01 | H88: 1.13 | I88: =950+J56 -> 990 | K88: =SUMIF('综合单价分析表 (11#楼)'!D:D,C88,'综合单价分析表 (11#楼)'!K:K) -> 0 | L88: =SUMIF('综合单价分析表（商业）'!D:D,C88,'综合单价分析表（商业）'!K:K) -> 0
A89: =MAX($A$3:$A88)+1 -> 85 | C89: 12+1.9SGP+12全超白钢化夹层玻璃（弯弧）（弧长1498㎜，高3600㎜，半径900㎜） | D89: m2 | E89: =+I89/H89 -> 876.10619 | F89: 0.01 | H89: 1.13 | I89: =950+J56 -> 990 | K89: =SUMIF('综合单价分析表 (11#楼)'!D:D,C89,'综合单价分析表 (11#楼)'!K:K) -> 0 | L89: =SUMIF('综合单价分析表（商业）'!D:D,C89,'综合单价分析表（商业）'!K:K) -> 0
A90: =MAX($A$3:$A89)+1 -> 86 | C90: 10+1.9SGP+10Low-E(双银)+12A+10㎜全超白钢化夹层中空玻璃（弯弧）（弧长1100㎜，圆弧半径900㎜，高3600㎜） | D90: m2 | E90: =+I90/H90 -> 1116.8142 | F90: 0.01 | H90: 1.13 | I90: =1222+J56 -> 1262 | K90: =SUMIF('综合单价分析表 (11#楼)'!D:D,C90,'综合单价分析表 (11#楼)'!K:K) -> 0 | L90: =SUMIF('综合单价分析表（商业）'!D:D,C90,'综合单价分析表（商业）'!K:K) -> 3.9996
A91: =MAX($A$3:$A90)+1 -> 87 | C91: 10+1.9SGP+10Low-E(双银)+12A+10㎜全超白钢化夹层中空玻璃（直+弯弧）（直段宽度600㎜+弧长1100㎜，圆弧半径700㎜，高3600㎜） | D91: m2 | E91: =+I91/H91 -> 1794.6903 | F91: 0.01 | H91: 1.13 | I91: =1988+J56 -> 2028 | K91: =SUMIF('综合单价分析表 (11#楼)'!D:D,C91,'综合单价分析表 (11#楼)'!K:K) -> 0 | L91: =SUMIF('综合单价分析表（商业）'!D:D,C91,'综合单价分析表（商业）'!K:K) -> 6.1812 | P91: =1.8*2.5 -> 4.5
A92: =MAX($A$3:$A91)+1 -> 88 | C92: 8+1.52+8全超白钢化夹层玻璃（弯弧）（弧长1100mm，高3035㎜，半径700㎜） | D92: m2 | E92: =+I92/H92 -> 347.78761 | F92: 0.01 | H92: 1.13 | I92: =353+J56 -> 393 | K92: =SUMIF('综合单价分析表 (11#楼)'!D:D,C92,'综合单价分析表 (11#楼)'!K:K) -> 0 | L92: =SUMIF('综合单价分析表（商业）'!D:D,C92,'综合单价分析表（商业）'!K:K) -> 0 | O92: =7+9*2 -> 25 | P92: =O92*2 -> 50 | Q92: =P92/P91 -> 11.111111
A93: =MAX($A$3:$A92)+1 -> 89 | C93: 6+1.52PVB+6Low-E(双银)+12A+10㎜全超白钢化夹层中空玻璃（直+弯弧+直）（直段宽度210㎜+弧长1414㎜+直段宽度210㎜，圆弧半径㎜900，高2300㎜） | D93: m2 | E93: =+I93/H93 -> 956.63717 | F93: 0.01 | H93: 1.13 | I93: =1041+J56 -> 1081 | K93: =SUMIF('综合单价分析表 (11#楼)'!D:D,C93,'综合单价分析表 (11#楼)'!K:K) -> 0 | L93: =SUMIF('综合单价分析表（商业）'!D:D,C93,'综合单价分析表（商业）'!K:K) -> 0
A94: =MAX($A$3:$A93)+1 -> 90 | C94: 6+1.52PVB+6Low-E(双银)+12A+10㎜全超白钢化夹层中空玻璃（弯弧）（弧长1414㎜，圆弧半径900㎜，高3035㎜） | D94: m2 | E94: =+I94/H94 -> 779.64602 | F94: 0.01 | H94: 1.13 | I94: =I93-200 -> 881 | K94: =SUMIF('综合单价分析表 (11#楼)'!D:D,C94,'综合单价分析表 (11#楼)'!K:K) -> 0 | L94: =SUMIF('综合单价分析表（商业）'!D:D,C94,'综合单价分析表（商业）'!K:K) -> 24.08139
A95: =MAX($A$3:$A94)+1 -> 91 | C95: 10Low-E(双银)+12A+10mm全超白钢化中空玻璃（直+弯弧）（直段宽度210㎜+弧长1095㎜，圆弧半径㎜700，高2300㎜） | D95: m2 | E95: =+I95/H95 -> 1060.177 | F95: 0.01 | H95: 1.13 | I95: =858+300+J56 -> 1198 | K95: =SUMIF('综合单价分析表 (11#楼)'!D:D,C95,'综合单价分析表 (11#楼)'!K:K) -> 0 | L95: =SUMIF('综合单价分析表（商业）'!D:D,C95,'综合单价分析表（商业）'!K:K) -> 0
A96: =MAX($A$3:$A95)+1 -> 92 | C96: 6+1.14+6全超白钢化夹层玻璃(弯弧）（弧长942㎜，圆弧半径㎜600，高1200㎜） | D96: m2 | E96: =+I96/H96 -> 242.47788 | F96: 0.01 | H96: 1.13 | I96: =234+J56 -> 274 | K96: =SUMIF('综合单价分析表 (11#楼)'!D:D,C96,'综合单价分析表 (11#楼)'!K:K) -> 0 | L96: =SUMIF('综合单价分析表（商业）'!D:D,C96,'综合单价分析表（商业）'!K:K) -> 0
A97: =MAX($A$3:$A96)+1 -> 93 | C97: 6+1.14+6全超白钢化夹层玻璃(弯弧）（直+弯弧）（直段宽度270㎜+弧长754㎜，圆弧半径㎜900，高1200㎜） | D97: m2 | E97: =+I97/H97 -> 794.69027 | F97: 0.01 | H97: 1.13 | I97: =858+J56 -> 898 | K97: =SUMIF('综合单价分析表 (11#楼)'!D:D,C97,'综合单价分析表 (11#楼)'!K:K) -> 0 | L97: =SUMIF('综合单价分析表（商业）'!D:D,C97,'综合单价分析表（商业）'!K:K) -> 0
A98: =MAX($A$3:$A97)+1 -> 94 | C98: 8+1.52PVB+8Low-E(双银)+12A+8+1.52PVB+8㎜全超白钢化夹层中空玻璃（超高）（宽2175㎜，高6800㎜） | D98: m2 | E98: =+I98/H98 -> 1362.8319 | F98: 0.01 | H98: 1.13 | I98: =1500+J56 -> 1540 | K98: =SUMIF('综合单价分析表 (11#楼)'!D:D,C98,'综合单价分析表 (11#楼)'!K:K) -> 0 | L98: =SUMIF('综合单价分析表（商业）'!D:D,C98,'综合单价分析表（商业）'!K:K) -> 14.9379
A99: =MAX($A$3:$A98)+1 -> 95 | C99: 10+1.9SGP+10Low-E(双银)+12A+12㎜全超白钢化夹层中空玻璃 | D99: m2 | E99: =+I99/H99 -> 693.80531 | F99: 0.01 | H99: 1.13 | I99: =544+200+J56 -> 784 | K99: =SUMIF('综合单价分析表 (11#楼)'!D:D,C99,'综合单价分析表 (11#楼)'!K:K) -> 0 | L99: =SUMIF('综合单价分析表（商业）'!D:D,C99,'综合单价分析表（商业）'!K:K) -> 63.9936
A100: =MAX($A$3:$A99)+1 -> 96 | C100: 10+1.9SGP+10Low-E(双银)+12A+12㎜全超白钢化夹层中空玻璃）（弯弧）（弧长1414㎜，圆弧半径900㎜，高3600㎜） | D100: m2 | E100: =+I100/H100 -> 1359.8584 | F100: 0.01 | H100: 1.13 | I100: =I99*1.96 -> 1536.64 | K100: =SUMIF('综合单价分析表 (11#楼)'!D:D,C100,'综合单价分析表 (11#楼)'!K:K) -> 0 | L100: =SUMIF('综合单价分析表（商业）'!D:D,C100,'综合单价分析表（商业）'!K:K) -> 10.282608
...

Sheet 工程量计算式 (11#楼)
A1: 名称 | B1: 位置 | C1: 单位 | D1: 计算式 | E1: 面积 | F1: 备注
A2: 石材幕墙 | E2: =SUM(E3:E32) -> 459.33362
A3: 25㎜葡萄牙灰石材 | B3: 西立面柱脚 | C3: ㎡ | D3: (0.55+0.45+0.15+2.9+0.15+2.9)*1 | E3: {=+EVALUATE(D3)} -> 7.1
A4: 25㎜葡萄牙灰石材 | B4: 南立面柱脚 | C4: ㎡ | D4: 0.55*(0.6+0.3)+0.55*(1.3+0.5+1.108+3.8+0.6+0.5+1.3)+0.55*(1.3+0.5+1.108+6.5+1.108+0.5+1.3)+0.55*(1.3+0.6) | E4: {=+EVALUATE(D4)} -> 13.3232
A5: 25㎜葡萄牙灰石材 | B5: 东立面柱脚 | C5: ㎡ | D5: 0.55*(4.95+0.15+2.9+0.15+2.9) | E5: {=+EVALUATE(D5)} -> 6.0775
A6: 25㎜葡萄牙灰石材 | B6: 北立面柱脚 | C6: ㎡ | D6: 0.55*0.6*4+0.25*（5.6+4.5+6.7+3.9+3.4+1+2+4.5+5.6） | E6: {=+EVALUATE(D6)} -> 10.62
A7: 25㎜葡萄牙灰石材 | B7: 一层采光井底部 | C7: ㎡ | D7: 0.2*5.11+0.2*5.86+0.2*5.01+0.2*2.46+0.2*1.96+0.2*5.36 | E7: {=+EVALUATE(D7)} -> 5.152
A8: 25㎜葡萄牙米黄石材 | B8: 西立面平板 | C8: ㎡ | D8: 1*3.06+3.5*1.53+0.45*3.06+2.87*0.2+2.87*(0.3+0.2)+2.9*3.06+2.1*3.5-2.7*1.7+0.75*2.1*2+0.75*3.5+(0.23+0.1)*2.88*2 | E8: {=+EVALUATE(D8)} -> 31.1108
A9: 25㎜葡萄牙米黄石材 | B9: 南立面平板 | C9: ㎡ | D9: 0.6*3.06*6+(1.3*2.18+0.65*0.25)*2+(1.3*2.18+0.65*0.25-0.9*1.97)*4+(0.23+0.25)*(10.5+7.85+10.5) | E9: {=+EVALUATE(D9)} -> 35.751
A10: 25㎜葡萄牙米黄石材 | B10: 东立面平板 | C10: ㎡ | D10: 2.9*3.06+4.95*3.06+(0.3+0.2)*2.87+(0.23+0.1)*2.88*2 | E10: {=+EVALUATE(D10)} -> 27.3568
A11: 25㎜葡萄牙米黄石材 | B11: 北立面平板 | C11: ㎡ | D11: 0.6*3.06*2+0.25*3.06*6+(0.6*3.06+1.2*0.23)*4+0.25*4.03*4+(0.25+0.23)*(11.1+6.7+8.3+4.1+11.1) | E11: {=+EVALUATE(D11)} -> 40.564
A12: 25㎜葡萄牙米黄石材线条 | B12: 西立面线条 | C12: 米 | D12: 10.73 | E12: {=+EVALUATE(D12)} -> 10.73
A13: 25㎜葡萄牙米黄石材线条 | B13: 南立面线条 | C13: 米 | D13: =11.7+9.1+11.7 -> 32.5 | E13: {=+EVALUATE(D13)} -> 32.5
A14: 25㎜葡萄牙米黄石材线条 | B14: 东立面线条 | C14: 米 | D14: 10.75 | E14: {=+EVALUATE(D14)} -> 10.75
A15: 25㎜葡萄牙米黄石材线条 | B15: 北立面线条 | C15: 米 | D15: =12.06+1.26+7.3+1.26+9.02+1.26+4.7+1.26+12.06 -> 50.18 | E15: {=+EVALUATE(D15)} -> 50.18
A16: 35㎜蓝眼睛石材（凹槽） | B16: 二层直段320高度 | C16: ㎡ | D16: (3.58+6.2+2.05+3.44+2.83+0.38+3.18+5.43+1.54+2.24+2.33+0.38+2.78+3.08+2.33+3.44+2.05+6.2+3.58)*(0.32+0.04*2) | E16: {=+EVALUATE(D16)} -> 22.816
A17: 35㎜蓝眼睛石材（凹槽） | B17: 二层弧段320高度 | C17: ㎡ | D17: (1.021*7+0.864*3)*(0.32+0.04*2) | E17: {=+EVALUATE(D17)} -> 3.8956
A18: 35㎜蓝眼睛石材（凹槽） | B18: 三层直段390高度 | C18: ㎡ | D18: (3.58+4.83+3.96+4.83+3.58)*(0.39+0.04*2) | E18: {=+EVALUATE(D18)} -> 9.7666
A19: 35㎜蓝眼睛石材（凹槽） | B19: 三层弧段390高度 | C19: ㎡ | D19: (1.021*2)*(0.39+0.04*2) | E19: {=+EVALUATE(D19)} -> 0.95974
A20: 35㎜蓝眼睛石材（凹槽） | B20: 三层直段560高度 | C20: ㎡ | D20: (1.61*3)*(0.56+0.04*2) | E20: {=+EVALUATE(D20)} -> 3.0912
A21: 35㎜蓝眼睛石材（凹槽） | B21: 四层直段470高度 | C21: ㎡ | D21: (2+2.8+1.63+2.8+1.63+1.63+2.8+2)*(0.47+0.04*2) | E21: {=+EVALUATE(D21)} -> 9.5095
A22: 35㎜蓝眼睛石材（凹槽） | B22: 四层弧段470高度 | C22: ㎡ | D22: (1.021*5)*(0.47+0.04*2) | E22: {=+EVALUATE(D22)} -> 2.80775
A23: 35㎜蓝眼睛石材（凹槽） | B23: 四层直段290高度 | C23: ㎡ | D23: (7.15+5.8+7.3)*(0.29+0.04*2) | E23: {=+EVALUATE(D23)} -> 7.4925
A24: 50㎜蓝眼睛石材（光面） | B24: 南立面 | C24: ㎡ | D24: 0.38*3.61+0.26*1.88 | E24: {=+EVALUATE(D24)} -> 1.8606
A25: 25㎜葡萄牙灰石材 | B25: 北立面采光天窗四周 | C25: ㎡ | D25: （1.35+0.4）*（0.4+0.15）*2+4.65*（0.4+0.15）-0.4*0.15*2 | E25: {=+EVALUATE(D25)} -> 4.3625
A26: 25㎜葡萄牙灰石材 | B26: 北立面采光天窗四周 | C26: ㎡ | D26: （1.35+0.4）*（0.4+0.15）*2+4.65*（0.54+0.15）-0.4*0.15*2 | E26: {=+EVALUATE(D26)} -> 5.0135
A27: 25㎜葡萄牙灰石材 | B27: 北立面采光天窗四周 | C27: ㎡ | D27: （1.35+0.4）*（0.4+0.15）*2+4.55*（0.54+0.15）-0.4*0.15*2 | E27: {=+EVALUATE(D27)} -> 4.9445
... A30: 25㎜葡萄牙灰石材 | B30: 北立面采光天窗四周 | C30: ㎡ | D30: （1.35+0.4）*（0.4+0.15）*2+4.9*（0.54+0.15）-0.4*0.15*2 | E30: {=+EVALUATE(D30)} -> 5.186
A31: 25㎜葡萄牙灰石材（下沉小院） | B31: 下沉小院 | C31: ㎡ | D31: 3.397*（0.46+0.37）+3.32*（0.46+0.37）+（2.418+6.555）+（11.789+5.024）+（2.355-6.75-1.912）+（2.25*2+0.3）*0.5+（2.25*2+0.85）*0.5 | E31: {=+EVALUATE(D31)*3} -> 90.38733 | F31: 3户
A33: 铝板幕墙 | E33: =SUM(E34:E115) -> 1865.4302
A34: 2.5㎜中灰色铝板1 | B34: 北立面幕窗上下口 | C34: ㎡ | D34: （4.05*（0.727）+6.2*0.21*4）*2+4.05*1 | E34: {=+EVALUATE(D34)} -> 20.3547
A35: 2.5㎜中灰色铝板1 | B35: 北立面幕窗上下口 | C35: ㎡ | D35: 2.55*0.727+5*0.21*4 | E35: {=+EVALUATE(D35)} -> 6.05385
A36: 2.5㎜中灰色铝板1 | B36: 北立面入户门上方 | C36: ㎡ | D36: 1*1.1*3 | E36: {=+EVALUATE(D36)} -> 3.3
A37: 2.5㎜中灰色铝板1 | B37: 北立面顶部穿孔铝单板上方 | C37: ㎡ | D37: （6.36+7.26+5.16+2.36+6.36）*0.139 | E37: {=+EVALUATE(D37)} -> 3.8225
A38: 2.5㎜浅灰色铝板3（一层墙面） | B38: 北立面18-15轴 | C38: ㎡ | D38: （11.1*2.75-5.25*0.524-4.05*1.75-1.0*2.75-6.2*0.524）+1.75*0.25*2+2.75*0.3*2 | E38: {=+EVALUATE(D38)} -> 17.2127
A39: 2.5㎜浅灰色铝板3（一层墙面） | B39: 北立面15-10轴 | C39: ㎡ | D39: （6.7*3.75-1.1*3.75*2）+2.75*0.3*4 | E39: {=+EVALUATE(D39)} -> 20.175
A40: 2.5㎜浅灰色铝板3（一层墙面） | B40: 北立面10-7轴 | C40: ㎡ | D40: （8.3*2.75-1.1*2.75-2.55*2.75-5.35*0.524）+2.75*0.3*2+2.75*0.25*2 | E40: {=+EVALUATE(D40)} -> 13.0091
A41: 2.5㎜浅灰色铝板3（一层墙面） | B41: 北立面7-4轴 | C41: ㎡ | D41: （4.1*3.75-1.1*3.75-2.3*0.524）+2.75*0.3*2 | E41: {=+EVALUATE(D41)} -> 11.6948
A42: 2.5㎜浅灰色铝板3（一层墙面） | B42: 北立面4-1轴 | C42: ㎡ | D42: （11.1*2.75-5.5*0.524-4.05*1.75-1.0*2.75）+0.75*0.25*2+2.75*0.3*2 | E42: {=+EVALUATE(D42)} -> 19.8305
A43: 2.5㎜浅灰色铝板2（带弧形造型） | B43: 北立面18-15轴 | C43: ㎡ | D43: （4.05+1.1）*1.578+（11.1-4.05-1.1）*1.338 | E43: {=+EVALUATE(D43)} -> 16.0878
A44: 2.5㎜浅灰色铝板2（带弧形造型） | B44: 北立面15-10轴 | C44: ㎡ | D44: 6.7*1.538 | E44: {=+EVALUATE(D44)} -> 10.3046
A45: 2.5㎜浅灰色铝板2（带弧形造型） | B45: 北立面10-7轴 | C45: ㎡ | D45: （1.1+2.05）*1.578+（8.3-1.1-2.05）*1.338 | E45: {=+EVALUATE(D45)} -> 11.8614
A46: 2.5㎜浅灰色铝板2（带弧形造型） | B46: 北立面7-4轴 | C46: ㎡ | D46: 4.1*1.538 | E46: {=+EVALUATE(D46)} -> 6.3058
A47: 2.5㎜浅灰色铝板2（带弧形造型） | B47: 北立面4-1轴 | C47: ㎡ | D47: （4.05+1.1）*1.578+（11.1-4.05-1.1）*1.338 | E47: {=+EVALUATE(D47)} -> 16.0878 | G47: 紫色-浅灰色
A48: 蓝眼睛仿石铝板（带圆弧，带拉槽） | B48: 北立面2/3/4层梁 | C48: ㎡ | D48: （6.2+5+6.2）*0.506+（6.2+5+6.2）*1.348+（6.2+5+6.2）*0.506 | E48: {=+EVALUATE(D48)} -> 41.064 | G48: 黄色-银灰色
A49: 4㎜香槟色穿孔铝单板（双层，内层2.5㎜中灰色铝单板） | B49: 北立面4层梁 | C49: ㎡ | D49: （6.36+7.26+5.16+2.36+6.36）*1.277 | E49: {=+EVALUATE(D49)} -> 35.1175
A50: 2.5㎜中灰色铝板1 | B50: 北立面4层梁 | C50: ㎡ | D50: （6.36+7.26+2.36+6.36）*0.139 | E50: {=+EVALUATE(D50)} -> 3.10526
A51: 蓝眼睛仿石铝板（四边带圆弧） | B51: 北立面 | C51: ㎡ | D51: 4.09*3.49*2 | E51: {=+EVALUATE(D51)} -> 28.5482
A52: 葡萄牙米黄仿石铝板（瓦楞板） | B52: 北立面 | C52: ㎡ | D52: （(2.4+0.1*2)+(2.07+0.1*2)*2）*(7.87+0.1*2) | E52: {=+EVALUATE(D52)} -> 57.6198
A53: 2.5㎜中灰色铝板1 | B53: 葡萄牙米黄石材三边 | C53: ㎡ | D53: （2.4+7.87*2）*0.1+（2.07+7.87*2）*0.1*2 | E53: {=+EVALUATE(D53)} -> 5.376
A54: 浅灰色铝板4 | B54: 北立面，铝板外带线条 | C54: ㎡ | D54: （3.95*6.825+1.65*1.53+1.257）*2+（34.328+10.8*2.332） | E54: {=+EVALUATE(D54)} -> 120.9941
A55: 2.5㎜银灰色铝板（线条造型） | B55: 北立面 | C55: ㎡ | D55: 0.53*（6*2+6.9+4.855+2） | E55: {=+EVALUATE(D55)} -> 13.65015 | F55: 顶部横向
A56: 2.5㎜银灰色铝板（弧形线条造型） | B56: 北立面 | C56: ㎡ | D56: 0.53*（0.628*20） | E56: {=+EVALUATE(D56)} -> 6.6568
A57: 2.5㎜银灰色铝板（双色线条造型）(中灰色/银灰色) | B57: 北立面 | C57: ㎡ | D57: 0.58*（108.856-0.628*20）+(0.346-0.19)*5.52*2 | E57: {=+EVALUATE(D57)} -> 57.57392 | F57: 格栅两边JD-110 | G57: 双色宽度多0.05
A58: 2.5㎜银灰色铝板（双色线条造型）(中灰色/银灰色)弧形 | B58: 北立面 | C58: ㎡ | D58: 0.58*（0.628*20） | E58: {=+EVALUATE(D58)} -> 7.2848
A59: 双色铝板造型线条(中灰色/浅灰色) | B59: 北立面 | C59: ㎡ | D59: 0.475*（24.862-0.236*4）*2+0.475*（22.462-0.236*4）*2 | E59: {=+EVALUATE(D59)} -> 43.1642 | F59: 傍边开窗JD-106
A60: 双色铝板造型线条(中灰色/浅灰色)弧形 | B60: 北立面 | C60: ㎡ | D60: 0.475*（0.236*4）*2+0.475*（0.236*4）*2 | E60: {=+EVALUATE(D60)} -> 1.7936 | F60: 傍边开窗
A61: 双色铝板造型线条(中灰色/浅灰色) | B61: 北立面 | C61: ㎡ | D61: 0.18*（3.35*2+3.95*2）*2 | E61: {=+EVALUATE(D61)} -> 5.256 | F61: JD-107
A62: 双色铝板造型线条(中灰色/浅灰色)弧形 | B62: 北立面 | C62: ㎡ | D62: 0.18*（0.236*4）*2 | E62: {=+EVALUATE(D62)} -> 0.33984
A63: 双色铝板造型线条(中灰色/浅灰色) | B63: 北立面 | C63: ㎡ | D63: 0.505*2.38 | E63: {=+EVALUATE(D63)} -> 1.2019 | F63: 剖3，JD-119,
A64: 双色铝板造型线条(中灰色/浅灰色) | B64: 北立面 | C64: ㎡ | D64: 0.574*22.722 | E64: {=+EVALUATE(D64)} -> 13.042428 | F64: JD-109
A65: 葡萄牙米黄仿石铝板（瓦楞板） | B65: 东西立面 | C65: ㎡ | D65: （4.197+0.429）*（6.37+0.1*2）*2 | E65: {=+EVALUATE(D65)} -> 60.78564
A66: 葡萄牙米黄仿石铝板（瓦楞板）弧形 | B66: 东西立面 | C66: ㎡ | D66: 0.788*（6.37+0.1*2）*2 | E66: {=+EVALUATE(D66)} -> 10.35432
A67: 浅灰色瓦楞铝板 | B67: 东西立面 | C67: ㎡ | D67: （0.64+0.05*2）*2.86*2 | E67: {=+EVALUATE(D67)} -> 4.2328
A68: 2.5㎜银灰色铝板（线条造型） | B68: 东西立面 | C68: ㎡ | D68: 0.53*16.237*2 | E68: {=+EVALUATE(D68)} -> 17.21122 | F68: JD-117
A69: 2.5㎜银灰色铝板（弧形线条造型） | B69: 东西立面 | C69: ㎡ | D69: 0.53*（0.628*2）*2 | E69: {=+EVALUATE(D69)} -> 1.33136
A70: 2.5㎜银灰色铝板（线条造型） | B70: 东西立面 | C70: ㎡ | D70: 0.44*（4.9+0）*2 | E70: {=+EVALUATE(D70)} -> 4.312 | F70: 剖7，3层
A71: 2.5㎜银灰色铝板（弧形线条造型） | B71: 东西立面 | C71: ㎡ | D71: 0.44*（0.628*2）*2 | E71: {=+EVALUATE(D71)} -> 1.10528
A72: 2.5㎜中灰色铝板1 | B72: 东西立面 | C72: ㎡ | D72: 0.2*16.237*2 | E72: {=+EVALUATE(D72)} -> 6.4948
A73: 双色铝板造型线条(中灰色/香槟色) | B73: 东南立面，西南立面 | C73: ㎡ | D73: 0.42*（12.287+14.387）*2 | E73: {=+EVALUATE(D73)} -> 22.40616 | F73: 剖7
A74: 双色铝板造型线条(中灰色/香槟色)弧形 | B74: 东南立面，西南立面 | C74: ㎡ | D74: 0.42*（0.298*4）*2 | E74: {=+EVALUATE(D74)} -> 1.00128
A75: 2.5㎜香槟色铝单板 | B75: 东南立面，西南立面 | C75: ㎡ | D75: （0.5*3.08*2）*2 | E75: {=+EVALUATE(D75)} -> 6.16 | F75: 梯形 | G75: 所有栏杆下铝板都未算
A76: 2.5㎜香槟色铝单板（弧形） | B76: 东南立面，西南立面 | C76: ㎡ | D76: （0.5*0.298*4）*2 | E76: {=+EVALUATE(D76)} -> 1.192 | F76: 梯形
A77: 2.5㎜银灰色铝板（线条造型） | B77: 东南立面，西南立面 | C77: ㎡ | D77: 0.63*（11.412-0.682*2）*2 | E77: {=+EVALUATE(D77)} -> 12.66048 | F77: 剖7
A78: 2.5㎜银灰色铝板（弧形线条造型） | B78: 东南立面，西南立面 | C78: ㎡ | D78: 0.63*（0.682*2）*2 | E78: {=+EVALUATE(D78)} -> 1.71864 | F78: 剖7
A79: 2.5㎜中灰色铝板1 | B79: 东南立面，西南立面4层 | C79: ㎡ | D79: 11.142*0.1*2 | E79: {=+EVALUATE(D79)} -> 2.2284
A80: 2.5㎜中灰色铝板1 | B80: 南立面 | C80: ㎡ | D80: 1.287*（10.38+7.73+10.38） | E80: {=+EVALUATE(D80)} -> 36.66663 | F80: 参剖1
A81: 2.5㎜浅灰色铝板2（带弧形造型） | B81: 南立面 | C81: ㎡ | D81: 1.398*（10.38+7.73+10.38） | E81: {=+EVALUATE(D81)} -> 39.82902
A82: 2.5㎜银灰色铝板（线条造型） | B82: 南立面，1-2轴/17-18轴 | C82: ㎡ | D82: 0.99*5.94*2 | E82: {=+EVALUATE(D82)} -> 11.7612 | F82: JD-122
A83: 2.5㎜银灰色铝板（线条造型） | B83: 南立面，1-2轴/17-18轴 | C83: ㎡ | D83: 0.83*10.914*2 | E83: {=+EVALUATE(D83)} -> 18.11724 | F83: JD-120
A84: 2.5㎜银灰色铝板（弧形线条造型） | B84: 南立面，1-2轴/17-18轴 | C84: ㎡ | D84: 0.83*（0.628*2）*2 | E84: {=+EVALUATE(D84)} -> 2.08496
A85: 双色铝板造型线条(中灰色/浅灰色) | B85: 南立面 | C85: ㎡ | D85: 0.475*（9.825-0.361*4）*3 | E85: {=+EVALUATE(D85)} -> 11.942925
A86: 双色铝板造型线条(中灰色/浅灰色)弧形 | B86: 南立面 | C86: ㎡ | D86: 0.475*（0.361*4）*3 | E86: {=+EVALUATE(D86)} -> 2.0577
A87: 2.5㎜银灰色铝板（线条造型） | B87: 南立面，横向，三层栏杆处 | C87: ㎡ | D87: 0.74*（7.59+3.6） | E87: {=+EVALUATE(D87)} -> 8.2806 | F87: JD-135
A88: 2.5㎜银灰色铝板（弧形线条造型） | B88: 南立面，横向 | C88: ㎡ | D88: 0.74*（0.393*2） | E88: {=+EVALUATE(D88)} -> 0.58164 | F88: JD-135
A89: 双色铝板造型线条(中灰色/浅灰色) | B89: 南立面,7轴竖向 | C89: ㎡ | D89: 0.475*（6.03）*2 | E89: {=+EVALUATE(D89)} -> 5.7285
A90: 2.5㎜浅灰色铝板3（一层墙面） | B90: 南立面，7轴竖向凹槽造型 | C90: ㎡ | D90: 0.877*3.7+1.827*3.3+3.277*3.3+0.477*1.3 | E90: {=+EVALUATE(D90)} -> 20.7082 | F90: 平面图
A91: 2.5㎜银灰色铝板（线条造型） | B91: 南立面，2-7轴 | C91: ㎡ | D91: 2.18*20.819+（5.4*3.265*2+11.529*2) | E91: {=+EVALUATE(D91)} -> 103.70542 | F91: 剖11
A92: 2.5㎜银灰色铝板（弧形线条造型） | B92: 南立面，2-7轴 | C92: ㎡ | D92: 2.18*（0.628*3）+(5.4*0.628*2) | E92: {=+EVALUATE(D92)} -> 10.88952 | F92: 剖11
A93: 4㎜香槟色穿孔铝单板（双层，内层1.5㎜镀锌钢板） | B93: 南立面，2-7轴 | C93: ㎡ | D93: (4.445*7.05+18*2+3.649*1.474)*1 | E93: {=+EVALUATE(D93)} -> 72.715876 | F93: 剖11
A94: 4㎜香槟色穿孔铝单板（双层，内层1.5㎜镀锌钢板）弧形 | B94: 南立面，2-7轴 | C94: ㎡ | D94: (0.298*4.445*2)*1 | E94: {=+EVALUATE(D94)} -> 2.64922 | F94: 剖11
A95: 2.5㎜银灰色铝板 | B95: 南立面 | C95: ㎡ | D95: 0.99*（14.254+1.2-0.628*3） | E95: {=+EVALUATE(D95)} -> 13.4343
A96: 2.5㎜银灰色铝板 | B96: 南立面 | C96: ㎡ | D96: 0.99*（0.628*2） | E96: {=+EVALUATE(D96)} -> 1.24344
A97: 双色铝板造型线条(中灰色/香槟色) | B97: 南立面，7-8轴 | C97: ㎡ | D97: 0.42*14.154 | E97: {=+EVALUATE(D97)} -> 5.94468
A98: 双色铝板造型线条(中灰色/香槟色)弧形 | B98: 南立面，7-8轴 | C98: ㎡ | D98: 0.42*（0.298*4） | E98: {=+EVALUATE(D98)} -> 0.50064
A99: 2.5㎜银灰色铝板（线条造型） | B99: 南立面，7-17轴，三层栏杆处 | C99: ㎡ | D99: 0.74*（4.6+6.23+3.6+7.59+3.6） | E99: {=+EVALUATE(D99)} -> 18.9588
A100: 2.5㎜银灰色铝板（弧形线条造型） | B100: 南立面，7-17轴 | C100: ㎡ | D100: 0.74*（0.393*3）*2 | E100: {=+EVALUATE(D100)} -> 1.74492
A101: 2.5㎜银灰色铝板（线条造型） | B101: 南立面，8-17轴 | C101: ㎡ | D101: 2.18*27.442+（5.4*3.265*2+11.529*2) | E101: {=+EVALUATE(D101)} -> 118.14356 | F101: 参剖11
A102: 2.5㎜银灰色铝板（弧形线条造型） | B102: 南立面，8-17轴 | C102: ㎡ | D102: 2.18*（0.628*3）+(5.4*0.628*2) | E102: {=+EVALUATE(D102)} -> 10.88952 | F102: 参剖11
A103: 2.5㎜浅灰色铝板3（一层墙面） | B103: 南立面，12轴竖向凹槽造型 | C103: ㎡ | D103: 13.277*4.38 | E103: {=+EVALUATE(D103)} -> 58.15326
...

Sheet 辅材及安装费
A1: 辅材及制作安装费
A2: 序号 | B2: 名称 | C2: 单位 | D2: 二次加工费 | E2: 辅材 | F2: 运输费用 | G2: 制作安装费 | H2: 合计
A3: 1 | B3: 铝板幕墙 | C3: 元/m2 | E3: 5 | F3: 5 | G3: 165 | H3: =+SUM(E3:G3) -> 175
A4: 2 | B4: 铝板幕墙-无龙骨 | C4: 元/m2 | E4: 5 | F4: 5 | G4: 68 | H4: =+SUM(E4:G4) -> 78
A5: 3 | B5: 幕墙式铝合窗 | C5: 元/m2 | D5: 40 | E5: 5 | F5: 5 | G5: 175 | H5: =+SUM(D5:G5) -> 225 | I5: 35
A6: 5 | B6: 玻璃栏杆 | C6: 元/m2 | E6: 10 | F6: 5 | G6: 135 | H6: =+SUM(E6:G6) -> 150
A7: 6 | B7: 格栅 | C7: 元/m2 | E7: 10 | F7: 5 | G7: =40+115 -> 155 | H7: =+SUM(E7:G7) -> 170
A8: 7 | B8: 石材幕墙 | C8: 元/m2 | D8: 12 | E8: 10 | F8: 5 | G8: 210 | H8: =+SUM(D8:G8) -> 237
A9: 8 | B9: 石材线条 | C9: 元/米 | E9: 2 | F9: 2 | G9: 25 | H9: =+SUM(E9:G9) -> 29
A10: 9 | B10: 80系列断桥隔热铝合金窗 | C10: 元/m2 | D10: 40 | E10: 10 | F10: 10 | G10: 80 | H10: =+SUM(D10:G10) -> 140
A11: 10 | B11: 铝合金百叶 | C11: 元/m2 | D11: 30 | E11: 10 | F11: 5 | G11: 65 | H11: =+SUM(D11:G11) -> 110
A12: 11 | B12: 铝合金线条 | C12: 元/米 | E12: 2 | F12: 1 | G12: 15 | H12: =+SUM(E12:G12) -> 18
A13: 12 | B13: 采光顶 | C13: 元/m2 | E13: 10 | F13: 5 | G13: =40+170 -> 210 | H13: =+SUM(E13:G13) -> 225
A14: 13 | B14: 防火隔断 | C14: 元/米 | E14: 2 | F14: 2 | G14: 25 | H14: =+SUM(E14:G14) -> 29
A15: 14 | B15: 镀锌铁皮封堵 | C15: 元/m2 | E15: 1 | F15: 1 | G15: 35 | H15: =+SUM(E15:G15) -> 37
A16: 15 | B16: 不锈钢天沟 | C16: 元/米 | E16: 5 | F16: 1 | G16: 130 | H16: =+SUM(E16:G16) -> 136
A17: 16 | B17: 座槽式玻璃幕墙 | C17: 元/m2 | E17: 10 | F17: 5 | G17: =20+170 -> 190 | H17: =+SUM(E17:G17) -> 205
A18: 17 | B18: T型钢玻璃幕墙 | C18: 元/m2 | E18: 10 | F18: 5 | G18: 180 | H18: =+SUM(E18:G18) -> 195
A19: 18 | B19: 明框玻璃幕墙 | C19: 元/m2 | E19: 10 | F19: 5 | G19: 170 | H19: =+SUM(E19:G19) -> 185
A20: 19 | B20: 金属网幕墙 | C20: 元/m2 | E20: 10 | F20: 5 | G20: 130 | H20: =+SUM(E20:G20) -> 145
A21: 20 | B21: 铝板背衬板 | C21: 元/m2 | E21: 5 | F21: 5 | G21: 35 | H21: =+SUM(E21:G21) -> 45

Sheet 措施
B1: 措施费
A2: 序号 | B2: 项目名称 | C2: 单位 | D2: 数量 | E2: 单价 | F2: 小计 | G2: 施工管理费、利润 | H2: 合价 | I2: 0 | L2: =88044/1000/6+6 -> 20.674
A3: 1 | B3: 防护棚 | C3: 项 | D3: 0 | E3: =+O70 -> 0 | F3: =D3*E3 -> 0 | G3: =F3*$I$2 -> 0 | H3: =F3+G3 -> 0 | I3: =+H3/$H$22 -> 0 | L3: 数量 | M3: 租期（月） | N3: 租赁费（元/月） | O3: 安拆（元/台） | P3: 进出运费（元/台） | Q3: 移位（元/台） | R3: 检测（元/台） | S3: 专家论证
A4: 2 | B4: 安全、文明施工费 | C4: 项 | D4: 0 | E4: 0 | F4: =D4*E4 -> 0 | G4: =F4*$I$2 -> 0 | H4: =F4+G4 -> 0 | I4: =+H4/$H$22 -> 0 | J4: 施工一段，高度≤100m | L4: 0 | M4: 4 | N4: =26*30 -> 780 | O4: 900 | P4: 200 | Q4: 550 | R4: 270 | S4: 0 | T4: =L4*(M4*N4+O4+P4+R4) -> 0
A5: 3 | B5: 临时设施费 | C5: 项 | D5: 0 | E5: 0 | F5: =D5*E5 -> 0 | G5: =F5*$I$2 -> 0 | H5: =F5+G5 -> 0 | I5: =+H5/$H$22 -> 0 | N5: =26*30 -> 780 | O5: 900 | P5: 200 | Q5: 550 | R5: 270 | T5: =L5*(M5*N5+O5+P5+Q5+R5) -> 0
A6: 4 | B6: 成品、半成品及设备保护费 | C6: m² | D6: 1 | E6: 1.5 | F6: =D6*E6 -> 1.5 | G6: =F6*$I$2 -> 0 | H6: =F6+G6 -> 1.5 | I6: =+H6/$H$22 -> 1.5304405e-05 | N6: =26*30 -> 780 | O6: 900 | P6: 200 | Q6: 550 | R6: 270 | T6: =L6*(M6*N6+O6+P6+Q6+R6) -> 0
A7: 5 | B7: 成品、半成品及设备堆放费 | C7: m² | D7: =+D6 -> 1 | E7: 1.5 | F7: =D7*E7 -> 1.5 | G7: =F7*$I$2 -> 0 | H7: =F7+G7 -> 1.5 | I7: =+H7/$H$22 -> 1.5304405e-05 | T7: =L7*(M7*N7+O7+P7+Q7+R7) -> 0
A8: 6 | B8: 幕墙清洗保洁费用(一次) | C8: m² | D8: =D6 -> 1 | E8: 2 | F8: =D8*E8 -> 2 | G8: =F8*$I$2 -> 0 | H8: =F8+G8 -> 2 | I8: =+H8/$H$22 -> 2.0405873e-05 | T8: =L8*(M8*N8+O8+P8+Q8+R8) -> 0
A9: 7 | B9: 二次搬运费 | C9: m² | D9: =D8 -> 1 | E9: 0 | F9: =D9*E9 -> 0 | G9: =F9*$I$2 -> 0 | H9: =F9+G9 -> 0 | I9: =+H9/$H$22 -> 0 | T9: =L9*(M9*N9+O9+P9+Q9+R9) -> 0
A10: 8 | B10: 垃圾清运费用 | C10: 项 | D10: =D9 -> 1 | E10: 1 | F10: =D10*E10 -> 1 | G10: =F10*$I$2 -> 0 | H10: =F10+G10 -> 1 | I10: =+H10/$H$22 -> 1.0202936e-05 | T10: =SUM(S4:T9) -> 0
A11: 9 | B11: 国标四性检测 | C11: 项 | D11: 1 | E11: 20000 | F11: =D11*E11 -> 20000 | G11: =F11*$I$2 -> 0 | H11: =F11+G11 -> 20000 | I11: =+H11/$H$22 -> 0.20405873 | L11: 数量 | M11: 单价
A12: 10 | B12: 防雷接地 | C12: m² | D12: =D6 -> 1 | E12: 1 | F12: =D12*E12 -> 1 | G12: =F12*$I$2 -> 0 | H12: =F12+G12 -> 1 | I12: =+H12/$H$22 -> 1.0202936e-05 | K12: 双排 | L12: =125000/1000*16 -> 2000 | M12: 35 | N12: =L12*M12 -> 70000
A13: 11 | B13: 淋水试验（二次） | C13: m² | D13: =+D12 -> 1 | E13: 1.5 | F13: =D13*E13 -> 1.5 | G13: =F13*$I$2 -> 0 | H13: =F13+G13 -> 1.5 | I13: =+H13/$H$22 -> 1.5304405e-05 | K13: 满堂 | L13: =+T16 -> 0 | M13: 17 | N13: =L13*M13 -> 0
A14: 12 | B14: 措施费(吊篮、脚手架) | C14: 项 | D14: 1 | E14: =T10+N12+N13 -> 70000 | F14: =D14*E14 -> 70000 | G14: =F14*$I$2 -> 0 | H14: =F14+G14 -> 70000 | I14: =+H14/$H$22 -> 0.71420555
A15: 13 | B15: 剪刀车、直臂车 | C15: 项 | D15: 1 | E15: 3000 | F15: =D15*E15 -> 3000 | G15: =F15*$I$2 -> 0 | H15: =F15+G15 -> 3000 | I15: =+H15/$H$22 -> 0.030608809
A16: 14 | B16: 开模费 | C16: 项 | D16: 0 | E16: 0 | F16: =D16*E16 -> 0 | G16: =F16*$I$2 -> 0 | H16: =F16+G16 -> 0 | I16: =+H16/$H$22 -> 0
A17: 15 | B17: 水电费 | C17: m² | D17: =+D12 -> 1 | E17: 1.5 | F17: =D17*E17 -> 1.5 | G17: =F17*$I$2 -> 0 | H17: =F17+G17 -> 1.5 | I17: =+H17/$H$22 -> 1.5304405e-05
A18: 16 | B18: 住宿费 | C18: m² | D18: =+D17 -> 1 | E18: 1 | F18: =D18*E18 -> 1 | G18: =F18*$I$2 -> 0 | H18: =F18+G18 -> 1 | I18: =+H18/$H$22 -> 1.0202936e-05
A19: 17 | B19: 专家论证费 | C19: 项 | D19: 1 | E19: 5000 | F19: =D19*E19 -> 5000 | G19: =F19*$I$2 -> 0 | H19: =F19+G19 -> 5000 | I19: =+H19/$H$22 -> 0.051014682
A20: 18 | B20: 施工许可证 | C20: 项 | D20: 1 | F20: =D20*E20 -> 0 | G20: =F20*$I$2 -> 0 | H20: =F20+G20 -> 0 | I20: =+H20/$H$22 -> 0
A21: 19 | B21: 设计费 | C21: 项 | D21: 1 | E21: 0 | F21: =D21*E21 -> 0 | G21: =F21*$I$2 -> 0 | H21: =F21+G21 -> 0 | I21: =+H21/$H$22 -> 0
A22: 20 | B22: 不含税小计 | H22: =SUM(H3:H21) -> 98011
H23: =H22/D18 -> 98011
G86: 120*60*5 | H86: 13.345 | I86: 0.77 | J86: 1 | K86: =+J86*I86*H86 -> 10.27565 | L86: 3.9115044 | M86: =+L86*K86 -> 40.19325
G87: 100*50*5 | H87: 10.99 | I87: 0.25 | J87: 2 | K87: =+J87*I87*H87 -> 5.495 | L87: 3.9115044 | M87: =+L87*K87 -> 21.493717
G88: 300*200*10 | H88: =0.3*0.2*10*7.85 -> 4.71 | I88: 1 | J88: 2 | K88: =+J88*I88*H88 -> 9.42 | L88: 5.1327434 | M88: =+L88*K88 -> 48.350442
G89: 加劲板 | H89: 1.01 | I89: 2 | J89: 2 | K89: =+J89*I89*H89 -> 4.04 | L89: 5.1327434 | M89: =+L89*K89 -> 20.736283
G90: 螺栓 | K90: =+J88*I88*4 -> 8 | L90: 1.9469027 | M90: =+L90*K90 -> 15.575221
L91: 材料费 | M91: =SUM(M86:M90) -> 146.34891
L92: 安装费 | M92: 80
M93: =SUM(M91:M92) -> 226.34891

Sheet 综合单价分析表（商业）
B1: 综合单价分析表
A2: 1 | B2: 序号 | C2: 清单项名称： | D2: =+A10 -> 首层座槽式玻璃幕墙（15+2.25SGP+15㎜全超白钢化夹层玻璃）（超宽） | F2: 玻璃幕墙 | H2: 费率 | I2: 金额 | J2: 单位 | K2: =VLOOKUP(A2,'商业工程量清单 '!$A$4:$D$44,4,FALSE) -> 25.92
B3: 1 | C3: 直接工程费 | D3: 人工费 | I3: =J15 -> 210 | J3: 元 | L3: 1#楼南立面 | M3: 16剖 | O3: 7.2 | P3: 3.6 | Q3: 1 | R3: =+Q3*P3*O3 -> 25.92
B4: 2 | D4: 材料费 | I4: =J42 -> 1437.136 | J4: 元
B5: 3 | D5: 机械费 | I5: =J43 -> 5 | J5: 元 | M5: 名称 | N5: 米重 | O5: 长/宽 | P5: 数量 | Q5: 总重 | R5: 单方
B6: 4 | C6: 直接费 | D6: (1)+（2）+（3） | I6: =SUM(I3:I5) -> 1652.136 | J6: 元 | L6: 粉末喷涂铝型材T6 | M6: 铝合金立柱 | N6: 3.111 | O6: =P3 -> 3.6 | P6: 1 | Q6: =+P6*O6*N6 -> 11.1996 | R6: =+Q6/R3 -> 0.43208333
B7: 5 | C7: 公司管理、利润 | D7: （4）*a% | H7: =+'材料表 '!$E$178 -> 0 | I7: =H7*I6 -> 0 | J7: 元 | L7: 阳极氧化铝型材T5 | M7: 铝合金副框 | N7: 0.507 | O7: =O6*2 -> 7.2 | P7: 1 | Q7: =+P7*O7*N7 -> 3.6504 | R7: =+Q7/R3 -> 0.14083333
B8: 6 | C8: 现场管理费 | D8: （4）*b% | H8: =+'材料表 '!$E$179 -> 0 | I8: =H8*I6 -> 0 | J8: 元 | L8: 阳极氧化铝型材T6 | M8: 铝合金压块 | N8: 0.499 | O8: =P3/0.3*0.05 -> 0.6 | P8: 1 | Q8: =+P8*O8*N8 -> 0.2994 | R8: =+Q8/R3 -> 0.011550926
B9: 7 | C9: 税金 | D9: [(4)+(5)+(6)]*c% | H9: =+'材料表 '!$E$180 -> 0.09 | I9: =(I6+I7+I8)*H9 -> 148.69224 | J9: 元 | L9: 阳极氧化铝型材T6 | M9: 立柱插芯 | N9: =2.9 -> 2.9 | O9: 0.2 | P9: 1 | Q9: =+P9*O9*N9 -> 0.58 | R9: =+Q9/R3 -> 0.022376543
A10: 首层座槽式玻璃幕墙（15+2.25SGP+15㎜全超白钢化夹层玻璃）（超宽） | B10: 8 | C10: 综合单价 | D10: （4）-（7）之和 | I10: =SUM(I6:I9) -> 1800.8283 | J10: 元/m² | L10: 阳极氧化铝型材T6 | P10: 1 | Q10: =+P10*O10*N10 -> 0 | R10: =+Q10/R3 -> 0
B11: 其中 | L11: 光身料铝型材T5 | P11: 1 | Q11: =+P11*O11*N11 -> 0 | R11: =+Q11/R3 -> 0
B12: 1 | C12: 人工费 | D12: 名称 | E12: 单位 | H12: 数量 | I12: 单价 | J12: 金额（元） | L12: 粉末喷涂铝型材T5 | P12: 1 | Q12: =+P12*O12*N12 -> 0 | R12: =+Q12/R3 -> 0
B13: 2 | D13: 座槽式玻璃幕墙 | E13: ㎡ | H13: 1 | I13: =+辅材及安装费!$G$17+20 -> 210 | J13: =H13*I13 -> 210 | L13: 粉末喷涂铝型材T6 | P13: 1 | Q13: =+P13*O13*N13 -> 0 | R13: =+Q13/R3 -> 0
B14: 3 | P14: 1 | Q14: =+P14*O14*N14 -> 0 | R14: =+Q14/R3 -> 0
B15: 4 | D15: 人工费合计 | E15: 元 | J15: =SUM(J13:J13) -> 210 | P15: 1
B16: 1 | C16: 材料费 | D16: 粉末喷涂铝型材T6 | E16: =+VLOOKUP(D16,'材料表 '!C:F,2,0) -> kg | F16: =+SUMIF($L$3:$L$43,D16,$R$3:$R$43) -> 0.43208333 | G16: =+VLOOKUP(D16,'材料表 '!C:F,4,0) -> 0.03 | H16: =F16*(G16+1) -> 0.44504583 | I16: =+VLOOKUP(D16,'材料表 '!C:F,3,0) -> 25.849558 | J16: =H16*I16 -> 11.504238 | K16: =H16*K2 -> 11.535588 | P16: 1
B17: 2 | D17: 粉末喷涂铝型材T5 | E17: =+VLOOKUP(D17,'材料表 '!C:F,2,0) -> kg | F17: =+SUMIF($L$3:$L$43,D17,$R$3:$R$43) -> 0 | G17: =+VLOOKUP(D17,'材料表 '!C:F,4,0) -> 0.03 | H17: =F17*(G17+1) -> 0 | I17: =+VLOOKUP(D17,'材料表 '!C:F,3,0) -> 25.672566 | J17: =H17*I17 -> 0 | K17: =H17*K2 -> 0
B18: 3 | D18: 阳极氧化铝型材T5 | E18: =+VLOOKUP(D18,'材料表 '!C:F,2,0) -> kg | F18: =+SUMIF($L$3:$L$43,D18,$R$3:$R$43) -> 0.14083333 | G18: =+VLOOKUP(D18,'材料表 '!C:F,4,0) -> 0.03 | H18: =F18*(G18+1) -> 0.14505833 | I18: =+VLOOKUP(D18,'材料表 '!C:F,3,0) -> 26.115044 | J18: =H18*I18 -> 3.7882048 | K18: =H18*K2 -> 3.759912
B19: 4 | D19: 阳极氧化铝型材T6 | E19: =+VLOOKUP(D19,'材料表 '!C:F,2,0) -> kg | F19: =+SUMIF($L$3:$L$43,D19,$R$3:$R$43) -> 0.033927469 | G19: =+VLOOKUP(D19,'材料表 '!C:F,4,0) -> 0.03 | H19: =F19*(G19+1) -> 0.034945293 | I19: =+VLOOKUP(D19,'材料表 '!C:F,3,0) -> 26.115044 | J19: =H19*I19 -> 0.91259788 | K19: =H19*K2 -> 0.905782 | L19: 隔热条（H=39mm） | O19: =(O6*P6) -> 3.6 | P19: 1 | Q19: =+P19*O19 -> 3.6 | R19: =+Q19/R3 -> 0.13888889
B20: 5 | D20: 光身料铝型材T5 | E20: =+VLOOKUP(D20,'材料表 '!C:F,2,0) -> kg | F20: =+SUMIF($L$3:$L$43,D20,$R$3:$R$43) -> 0 | G20: =+VLOOKUP(D20,'材料表 '!C:F,4,0) -> 0.03 | H20: =F20*(G20+1) -> 0 | I20: =+VLOOKUP(D20,'材料表 '!C:F,3,0) -> 24.433628 | J20: =H20*I20 -> 0 | K20: =H20*K2 -> 0
B21: 6 | D21: 铝材表面氟碳喷涂 | E21: =+VLOOKUP(D21,'材料表 '!C:F,2,0) -> m2 | F21: =+SUMIF($L$3:$L$43,D21,$R$3:$R$43) -> 0 | G21: =+VLOOKUP(D21,'材料表 '!C:F,4,0) -> 0 | H21: =F21*(G21+1) -> 0 | I21: =+VLOOKUP(D21,'材料表 '!C:F,3,0) -> 49.557522 | J21: =H21*I21 -> 0 | K21: =H21*K2 -> 0 | L21: 热镀锌埋件 | M21: （200+120）*300*8 | N21: =0.32*0.3*8*7.85 -> 6.0288 | O21: 2 | P21: 1 | Q21: =+P21*O21*N21 -> 12.0576 | R21: =+Q21/R3 -> 0.46518519
B22: 7 | K22: =H22*K2 -> 0 | L22: 热镀锌钢连接件 | M22: L=130，100*63*8角钢 | N22: 9.88 | O22: =0.13 -> 0.13 | P22: 4 | Q22: =+P22*O22*N22 -> 5.1376 | R22: =Q22/R3 -> 0.19820988
B23: 8 | D23: 热镀锌钢管 | E23: =+VLOOKUP(D23,'材料表 '!C:F,2,0) -> kg | F23: =+SUMIF($L$3:$L$43,D23,$R$3:$R$43) -> 0 | G23: =+VLOOKUP(D23,'材料表 '!C:F,4,0) -> 0.03 | H23: =F23*(G23+1) -> 0 | I23: =+VLOOKUP(D23,'材料表 '!C:F,3,0) -> 3.8053097 | J23: =H23*I23 -> 0 | K23: =H23*K2 -> 0 | L23: M12化学锚栓 | O23: 6 | P23: =O21*P21 -> 2 | Q23: =O23*P23 -> 12 | R23: =Q23/R3 -> 0.46296296
B24: 9 | D24: 热镀锌角钢 | E24: =+VLOOKUP(D24,'材料表 '!C:F,2,0) -> kg | F24: =+SUMIF($L$3:$L$43,D24,$R$3:$R$43) -> 0 | G24: =+VLOOKUP(D24,'材料表 '!C:F,4,0) -> 0.03 | H24: =F24*(G24+1) -> 0 | I24: =+VLOOKUP(D24,'材料表 '!C:F,3,0) -> 3.539823 | J24: =H24*I24 -> 0 | K24: =H24*K2 -> 0 | L24: M12x120不锈钢螺栓 | O24: 2 | P24: 2 | Q24: =O24*P24 -> 4 | R24: =Q24/R3 -> 0.15432099
B25: 10 | D25: 三元乙丙胶条 | E25: =+VLOOKUP(D25,'材料表 '!C:F,2,0) -> kg | F25: =+SUMIF($L$3:$L$43,D25,$R$3:$R$43) -> 0 | G25: =+VLOOKUP(D25,'材料表 '!C:F,4,0) -> 0.03 | H25: =F25*(G25+1) -> 0 | I25: =+VLOOKUP(D25,'材料表 '!C:F,3,0) -> 19.469027 | J25: =H25*I25 -> 0 | K25: =H25*K2 -> 0 | L25: 热镀锌钢连接件 | N25: =(0.058+0.04*2)*5*7.85 -> 5.4165 | O25: =O3 -> 7.2 | P25: 1 | Q25: =+P25*O25*N25 -> 38.9988 | R25: =+Q25/R3 -> 1.5045833
B26: 11 | D26: 热镀锌埋件 | E26: =+VLOOKUP(D26,'材料表 '!C:F,2,0) -> kg | F26: =+SUMIF($L$3:$L$43,D26,$R$3:$R$43) -> 0.46518519 | G26: =+VLOOKUP(D26,'材料表 '!C:F,4,0) -> 0.03 | H26: =F26*(G26+1) -> 0.47914074 | I26: =+VLOOKUP(D26,'材料表 '!C:F,3,0) -> 6.0176991 | J26: =H26*I26 -> 2.8833248 | K26: =H26*K2 -> 12.419328 | L26: 热镀锌角钢
B27: 12 | D27: 热镀锌钢连接件 | E27: =+VLOOKUP(D27,'材料表 '!C:F,2,0) -> kg | F27: =+SUMIF($L$3:$L$43,D27,$R$3:$R$43) -> 1.7027932 | G27: =+VLOOKUP(D27,'材料表 '!C:F,4,0) -> 0.03 | H27: =F27*(G27+1) -> 1.753877 | I27: =+VLOOKUP(D27,'材料表 '!C:F,3,0) -> 6.0176991 | J27: =H27*I27 -> 10.554304 | K27: =H27*K2 -> 45.460492
B28: 13 | D28: M12化学锚栓 | E28: =+VLOOKUP(D28,'材料表 '!C:F,2,0) -> 套 | F28: =+SUMIF($L$3:$L$43,D28,$R$3:$R$43) -> 0.46296296 | G28: =+VLOOKUP(D28,'材料表 '!C:F,4,0) -> 0 | H28: =F28*(G28+1) -> 0.46296296 | I28: =+VLOOKUP(D28,'材料表 '!C:F,3,0) -> 2.2123894 | J28: =H28*I28 -> 1.0242543 | K28: =H28*K2 -> 12
B29: 14 | D29: M12x120不锈钢螺栓 | E29: =+VLOOKUP(D29,'材料表 '!C:F,2,0) -> 套 | F29: =+SUMIF($L$3:$L$43,D29,$R$3:$R$43) -> 0.15432099 | G29: =+VLOOKUP(D29,'材料表 '!C:F,4,0) -> 0 | H29: =F29*(G29+1) -> 0.15432099 | I29: =+VLOOKUP(D29,'材料表 '!C:F,3,0) -> 2.4778761 | J29: =H29*I29 -> 0.38238829 | K29: =H29*K2 -> 4
B30: 15 | D30: 耐候密封胶 | E30: =+VLOOKUP(D30,'材料表 '!C:F,2,0) -> 支 | F30: =8*8*(O3*4+P3*4)/500/R3+16*32*(P3)/500/R3 -> 0.35555556 | G30: =+VLOOKUP(D30,'材料表 '!C:F,4,0) -> 0.15 | H30: =F30*(G30+1) -> 0.40888889 | I30: =+VLOOKUP(D30,'材料表 '!C:F,3,0) -> 11.504425 | J30: =H30*I30 -> 4.7040315 | K30: =H30*K2 -> 10.5984
B31: 16 | D31: 耐候结构胶 | E31: =+VLOOKUP(D31,'材料表 '!C:F,2,0) -> 支 | F31: =16*8*(P3*P6)*2/500/R3 -> 0.071111111 | G31: =+VLOOKUP(D31,'材料表 '!C:F,4,0) -> 0.15 | H31: =F31*(G31+1) -> 0.081777778 | I31: =+VLOOKUP(D31,'材料表 '!C:F,3,0) -> 14.159292 | J31: =H31*I31 -> 1.1579154 | K31: =H31*K2 -> 2.11968
B32: 17 | K32: =H32*K2 -> 0
B33: 18 | K33: =H33*K2 -> 0
B34: 19 | D34: 15+2.28SGP+15全超白钢化夹层玻璃(超宽)（宽7200㎜，高3600㎜） | E34: =+VLOOKUP(D34,'材料表 '!C:F,2,0) -> m2 | F34: 1.01 | G34: =+VLOOKUP(D34,'材料表 '!C:F,4,0) -> 0.01 | H34: =F34*(G34+1) -> 1.0201 | I34: =+VLOOKUP(D34,'材料表 '!C:F,3,0) -> 1362.8319 | J34: =H34*I34 -> 1390.2248 | K34: =H34*K2 -> 26.440992
B35: 20 | K35: =H35*K2 -> 0
B36: 21 | K36: =H36*K2 -> 0
B37: 22 | K37: =H37*K2 -> 0
B38: 23 | K38: =H38*K2 -> 0
B39: 24 | K39: =H39*K2 -> 0
B40: 25
B41: 26 | D41: 辅材材料费 | E41: m2 | G41: 1 | H41: 1 | I41: =+辅材及安装费!$E$17 -> 10 | J41: =H41*I41 -> 10
B42: 27 | D42: 材料费合计 | J42: =SUM(J16:J41) -> 1437.136
B43: 1 | C43: 其他费 | D43: 机械费+运输费 | E43: m2 | H43: 1 | I43: =+辅材及安装费!$F$17 -> 5 | J43: =H43*I43 -> 5
B44: 综合单价分析表
A45: 2 | B45: 序号 | C45: 清单项名称： | D45: =+A53 -> 首层座槽式玻璃幕墙（12Low-E(双银)+12A+12全超白钢化中空玻璃） | F45: 玻璃幕墙 | H45: 费率 | I45: 金额 | J45: 单位 | K45: =VLOOKUP(A45,'商业工程量清单 '!$A$4:$D$44,4,FALSE) -> 10.98
B46: 1 | C46: 直接工程费 | D46: 人工费 | I46: =J58 -> 190 | J46: 元 | L46: 1#楼南立面 | M46: 16剖 | O46: =1.85+1.2 -> 3.05 | P46: 3.6 | Q46: 1 | R46: =+Q46*P46*O46 -> 10.98
B47: 2 | D47: 材料费 | I47: =J85 -> 371.43564 | J47: 元
B48: 3 | D48: 机械费 | I48: =J86 -> 5 | J48: 元 | M48: 名称 | N48: 米重 | O48: 长/宽 | P48: 数量 | Q48: 总重 | R48: 单方
B49: 4 | C49: 直接费 | D49: (1)+（2）+（3） | I49: =SUM(I46:I48) -> 566.43564 | J49: 元 | L49: 粉末喷涂铝型材T6 | M49: 铝合金立柱 | N49: 3.111 | O49: =P46 -> 3.6 | P49: 2.5 | Q49: =+P49*O49*N49 -> 27.999 | R49: =+Q49/R46 -> 2.55
B50: 5 | C50: 公司管理、利润 | D50: （4）*a% | H50: =+'材料表 '!$E$178 -> 0 | I50: =H50*I49 -> 0 | J50: 元 | L50: 阳极氧化铝型材T5 | M50: 铝合金副框 | N50: 0.507 | O50: =O49*2 -> 7.2 | P50: =P49 -> 2.5 | Q50: =+P50*O50*N50 -> 9.126 | R50: =+Q50/R46 -> 0.83114754
B51: 6 | C51: 现场管理费 | D51: （4）*b% | H51: =+'材料表 '!$E$179 -> 0 | I51: =H51*I49 -> 0 | J51: 元 | L51: 阳极氧化铝型材T6 | M51: 铝合金压块 | N51: 0.499 | O51: =P46/0.3*0.05 -> 0.6 | P51: =P49 -> 2.5 | Q51: =+P51*O51*N51 -> 0.7485 | R51: =+Q51/R46 -> 0.068169399
B52: 7 | C52: 税金 | D52: [(4)+(5)+(6)]*c% | H52: =+'材料表 '!$E$180 -> 0.09 | I52: =(I49+I50+I51)*H52 -> 50.979207 | J52: 元 | L52: 阳极氧化铝型材T6 | M52: 立柱插芯 | N52: =2.9 -> 2.9 | O52: 0.2 | P52: =P49 -> 2.5 | Q52: =+P52*O52*N52 -> 1.45 | R52: =+Q52/R46 -> 0.13205829
A53: 首层座槽式玻璃幕墙（12Low-E(双银)+12A+12全超白钢化中空玻璃） | B53: 8 | C53: 综合单价 | D53: （4）-（7）之和 | I53: =SUM(I49:I52) -> 617.41484 | J53: 元/m² | L53: 阳极氧化铝型材T6 | P53: 1 | Q53: =+P53*O53*N53 -> 0 | R53: =+Q53/R46 -> 0
B54: 其中 | L54: 光身料铝型材T5 | P54: 1 | Q54: =+P54*O54*N54 -> 0 | R54: =+Q54/R46 -> 0
B55: 1 | C55: 人工费 | D55: 名称 | E55: 单位 | H55: 数量 | I55: 单价 | J55: 金额（元） | L55: 粉末喷涂铝型材T5 | P55: 1 | Q55: =+P55*O55*N55 -> 0 | R55: =+Q55/R46 -> 0
B56: 2 | D56: 座槽式玻璃幕墙 | E56: ㎡ | H56: 1 | I56: =+辅材及安装费!$G$17 -> 190 | J56: =H56*I56 -> 190 | L56: 粉末喷涂铝型材T6 | P56: 1 | Q56: =+P56*O56*N56 -> 0 | R56: =+Q56/R46 -> 0
B57: 3 | P57: 1 | Q57: =+P57*O57*N57 -> 0 | R57: =+Q57/R46 -> 0
B58: 4 | D58: 人工费合计 | E58: 元 | J58: =SUM(J56:J56) -> 190 | P58: 1
B59: 1 | C59: 材料费 | D59: 粉末喷涂铝型材T6 | E59: =+VLOOKUP(D59,'材料表 '!C:F,2,0) -> kg | F59: =+SUMIF($L$46:$L$86,D59,$R$46:$R$86) -> 2.55 | G59: =+VLOOKUP(D59,'材料表 '!C:F,4,0) -> 0.03 | H59: =F59*(G59+1) -> 2.6265 | I59: =+VLOOKUP(D59,'材料表 '!C:F,3,0) -> 25.849558 | J59: =H59*I59 -> 67.893863 | K59: =H59*K45 -> 28.83897 | P59: 1
B60: 2 | D60: 粉末喷涂铝型材T5 | E60: =+VLOOKUP(D60,'材料表 '!C:F,2,0) -> kg | F60: =+SUMIF($L$46:$L$86,D60,$R$46:$R$86) -> 0 | G60: =+VLOOKUP(D60,'材料表 '!C:F,4,0) -> 0.03 | H60: =F60*(G60+1) -> 0 | I60: =+VLOOKUP(D60,'材料表 '!C:F,3,0) -> 25.672566 | J60: =H60*I60 -> 0 | K60: =H60*K45 -> 0
B61: 3 | D61: 阳极氧化铝型材T5 | E61: =+VLOOKUP(D61,'材料表 '!C:F,2,0) -> kg | F61: =+SUMIF($L$46:$L$86,D61,$R$46:$R$86) -> 0.83114754 | G61: =+VLOOKUP(D61,'材料表 '!C:F,4,0) -> 0.03 | H61: =F61*(G61+1) -> 0.85608197 | I61: =+VLOOKUP(D61,'材料表 '!C:F,3,0) -> 26.115044 | J61: =H61*I61 -> 22.356618 | K61: =H61*K45 -> 9.39978
B62: 4 | D62: 阳极氧化铝型材T6 | E62: =+VLOOKUP(D62,'材料表 '!C:F,2,0) -> kg | F62: =+SUMIF($L$46:$L$86,D62,$R$46:$R$86) -> 0.20022769 | G62: =+VLOOKUP(D62,'材料表 '!C:F,4,0) -> 0.03 | H62: =F62*(G62+1) -> 0.20623452 | I62: =+VLOOKUP(D62,'材料表 '!C:F,3,0) -> 26.115044 | J62: =H62*I62 -> 5.3858235 | K62: =H62*K45 -> 2.264455 | L62: 隔热条（H=39mm） | O62: =(O49*P49) -> 9 | P62: 1 | Q62: =+P62*O62 -> 9 | R62: =+Q62/R46 -> 0.81967213
B63: 5 | D63: 光身料铝型材T5 | E63: =+VLOOKUP(D63,'材料表 '!C:F,2,0) -> kg | F63: =+SUMIF($L$46:$L$86,D63,$R$46:$R$86) -> 0 | G63: =+VLOOKUP(D63,'材料表 '!C:F,4,0) -> 0.03 | H63: =F63*(G63+1) -> 0 | I63: =+VLOOKUP(D63,'材料表 '!C:F,3,0) -> 24.433628 | J63: =H63*I63 -> 0 | K63: =H63*K45 -> 0
B64: 6 | D64: 铝材表面氟碳喷涂 | E64: =+VLOOKUP(D64,'材料表 '!C:F,2,0) -> m2 | F64: =+SUMIF($L$46:$L$86,D64,$R$46:$R$86) -> 0 | G64: =+VLOOKUP(D64,'材料表 '!C:F,4,0) -> 0 | H64: =F64*(G64+1) -> 0 | I64: =+VLOOKUP(D64,'材料表 '!C:F,3,0) -> 49.557522 | J64: =H64*I64 -> 0 | K64: =H64*K45 -> 0 | L64: 热镀锌埋件 | M64: （200+120）*300*8 | N64: =0.32*0.3*8*7.85 -> 6.0288 | O64: 2 | P64: =P49 -> 2.5 | Q64: =+P64*O64*N64 -> 30.144 | R64: =+Q64/R46 -> 2.7453552
B65: 7 | F65: =+SUMIF($L$46:$L$86,D65,$R$46:$R$86) -> 0 | K65: =H65*K45 -> 0 | L65: 热镀锌钢连接件 | M65: L=130，100*63*8角钢 | N65: 9.88 | O65: =0.13 -> 0.13 | P65: =2*P64 -> 5 | Q65: =+P65*O65*N65 -> 6.422 | R65: =Q65/R46 -> 0.5848816
B66: 8 | D66: 热镀锌钢管 | E66: =+VLOOKUP(D66,'材料表 '!C:F,2,0) -> kg | F66: =+SUMIF($L$46:$L$86,D66,$R$46:$R$86) -> 0 | G66: =+VLOOKUP(D66,'材料表 '!C:F,4,0) -> 0.03 | H66: =F66*(G66+1) -> 0 | I66: =+VLOOKUP(D66,'材料表 '!C:F,3,0) -> 3.8053097 | J66: =H66*I66 -> 0 | K66: =H66*K45 -> 0 | L66: M12化学锚栓 | O66: 6 | P66: =O64*P64 -> 5 | Q66: =O66*P66 -> 30 | R66: =Q66/R46 -> 2.7322404
B67: 9 | D67: 热镀锌角钢 | E67: =+VLOOKUP(D67,'材料表 '!C:F,2,0) -> kg | F67: =+SUMIF($L$46:$L$86,D67,$R$46:$R$86) -> 0 | G67: =+VLOOKUP(D67,'材料表 '!C:F,4,0) -> 0.03 | H67: =F67*(G67+1) -> 0 | I67: =+VLOOKUP(D67,'材料表 '!C:F,3,0) -> 3.539823 | J67: =H67*I67 -> 0 | K67: =H67*K45 -> 0 | L67: M12x120不锈钢螺栓 | O67: 2 | P67: =P49 -> 2.5 | Q67: =O67*P67 -> 5 | R67: =Q67/R46 -> 0.45537341
B68: 10 | D68: 三元乙丙胶条 | E68: =+VLOOKUP(D68,'材料表 '!C:F,2,0) -> kg | F68: =+SUMIF($L$46:$L$86,D68,$R$46:$R$86) -> 0 | G68: =+VLOOKUP(D68,'材料表 '!C:F,4,0) -> 0.03 | H68: =F68*(G68+1) -> 0 | I68: =+VLOOKUP(D68,'材料表 '!C:F,3,0) -> 19.469027 | J68: =H68*I68 -> 0 | K68: =H68*K45 -> 0 | L68: 热镀锌钢连接件 | N68: =(0.058+0.04*2)*5*7.85 -> 5.4165 | O68: =O46 -> 3.05 | P68: 1 | Q68: =+P68*O68*N68 -> 16.520325 | R68: =+Q68/R46 -> 1.5045833
B69: 11 | D69: 热镀锌埋件 | E69: =+VLOOKUP(D69,'材料表 '!C:F,2,0) -> kg | F69: =+SUMIF($L$46:$L$86,D69,$R$46:$R$86) -> 2.7453552 | G69: =+VLOOKUP(D69,'材料表 '!C:F,4,0) -> 0.03 | H69: =F69*(G69+1) -> 2.8277158 | I69: =+VLOOKUP(D69,'材料表 '!C:F,3,0) -> 6.0176991 | J69: =H69*I69 -> 17.016343 | K69: =H69*K45 -> 31.04832 | L69: 热镀锌角钢
B70: 12 | D70: 热镀锌钢连接件 | E70: =+VLOOKUP(D70,'材料表 '!C:F,2,0) -> kg | F70: =+SUMIF($L$46:$L$86,D70,$R$46:$R$86) -> 2.0894649 | G70: =+VLOOKUP(D70,'材料表 '!C:F,4,0) -> 0.03 | H70: =F70*(G70+1) -> 2.1521489 | I70: =+VLOOKUP(D70,'材料表 '!C:F,3,0) -> 6.0176991 | J70: =H70*I70 -> 12.950984 | K70: =H70*K45 -> 23.630595
B71: 13 | D71: M12化学锚栓 | E71: =+VLOOKUP(D71,'材料表 '!C:F,2,0) -> 套 | F71: =+SUMIF($L$46:$L$86,D71,$R$46:$R$86) -> 2.7322404 | G71: =+VLOOKUP(D71,'材料表 '!C:F,4,0) -> 0 | H71: =F71*(G71+1) -> 2.7322404 | I71: =+VLOOKUP(D71,'材料表 '!C:F,3,0) -> 2.2123894 | J71: =H71*I71 -> 6.0447797 | K71: =H71*K45 -> 30
B72: 14 | D72: M12x120不锈钢螺栓 | E72: =+VLOOKUP(D72,'材料表 '!C:F,2,0) -> 套 | F72: =+SUMIF($L$46:$L$86,D72,$R$46:$R$86) -> 0.45537341 | G72: =+VLOOKUP(D72,'材料表 '!C:F,4,0) -> 0 | H72: =F72*(G72+1) -> 0.45537341 | I72: =+VLOOKUP(D72,'材料表 '!C:F,3,0) -> 2.4778761 | J72: =H72*I72 -> 1.1283589 | K72: =H72*K45 -> 5
B73: 15 | D73: 耐候密封胶 | E73: =+VLOOKUP(D73,'材料表 '!C:F,2,0) -> 支 | F73: =8*8*(O46*4+P46*4)/500/R46+16*36*(P46)/500/R46 -> 0.68779599 | G73: =+VLOOKUP(D73,'材料表 '!C:F,4,0) -> 0.15 | H73: =F73*(G73+1) -> 0.79096539 | I73: =+VLOOKUP(D73,'材料表 '!C:F,3,0) -> 11.504425 | J73: =H73*I73 -> 9.0996019 | K73: =H73*K45 -> 8.6848
B74: 16 | D74: 耐候结构胶 | E74: =+VLOOKUP(D74,'材料表 '!C:F,2,0) -> 支 | F74: =16*8*(P46*P49)*2/500/R46 -> 0.41967213 | G74: =+VLOOKUP(D74,'材料表 '!C:F,4,0) -> 0.15 | H74: =F74*(G74+1) -> 0.48262295 | I74: =+VLOOKUP(D74,'材料表 '!C:F,3,0) -> 14.159292 | J74: =H74*I74 -> 6.8335993 | K74: =H74*K45 -> 5.2992
B75: 17 | K75: =H75*K45 -> 0
B76: 18 | K76: =H76*K45 -> 0
B77: 19 | D77: 12Low-E(双银)+12A+12㎜全超白钢化中空玻璃 | E77: =+VLOOKUP(D77,'材料表 '!C:F,2,0) -> m2 | F77: 1 | G77: =+VLOOKUP(D77,'材料表 '!C:F,4,0) -> 0.01 | H77: =F77*(G77+1) -> 1.01 | I77: =+VLOOKUP(D77,'材料表 '!C:F,3,0) -> 210.61947 | J77: =H77*I77 -> 212.72566 | K77: =H77*K45 -> 11.0898
B78: 20 | K78: =H78*K45 -> 0
B79: 21 | K79: =H79*K45 -> 0
B80: 22 | K80: =H80*K45 -> 0
B81: 23 | K81: =H81*K45 -> 0
B82: 24 | K82: =H82*K45 -> 0
B83: 25
B84: 26 | D84: 辅材材料费 | E84: m2 | G84: 1 | H84: 1 | I84: =+辅材及安装费!$E$17 -> 10 | J84: =H84*I84 -> 10
B85: 27 | D85: 材料费合计 | J85: =SUM(J59:J84) -> 371.43564
B86: 1 | C86: 其他费 | D86: 机械费+运输费 | E86: m2 | H86: 1 | I86: =+辅材及安装费!$F$17 -> 5 | J86: =H86*I86 -> 5
B87: 综合单价分析表
A88: 3 | B88: 序号 | C88: 清单项名称： | D88: =+A96 -> 首层座槽式玻璃幕墙（12Low-E(双银)+12A+12全超白钢化中空玻璃）（直+弯弧）（直段宽度300㎜+弧长942㎜，圆弧半径600㎜，高3600㎜） | F88: 玻璃幕墙 | H88: 费率 | I88: 金额 | J88: 单位 | K88: =VLOOKUP(A88,'商业工程量清单 '!$A$4:$D$44,4,FALSE) -> 8.9424
B89: 1 | C89: 直接工程费 | D89: 人工费 | I89: =J101 -> 190 | J89: 元 | L89: 1#楼南立面 | M89: 16剖 | O89: =0.3+0.942 -> 1.242 | P89: 3.6 | Q89: 1 | R89: =+Q89*P89*O89 -> 4.4712
B90: 2 | D90: 材料费 | I90: =J128 -> 1329.9672 | J90: 元
B91: 3 | D91: 机械费 | I91: =J129 -> 5 | J91: 元 | M91: 名称 | N91: 米重 | O91: 长/宽 | P91: 数量 | Q91: 总重 | R91: 单方
B92: 4 | C92: 直接费 | D92: (1)+（2）+（3） | I92: =SUM(I89:I91) -> 1524.9672 | J92: 元 | L92: 粉末喷涂铝型材T6 | M92: 铝合金立柱 | N92: 3.111 | O92: =P89 -> 3.6 | P92: 1.5 | Q92: =+P92*O92*N92 -> 16.7994 | R92: =+Q92/R89 -> 3.7572464
B93: 5 | C93: 公司管理、利润 | D93: （4）*a% | H93: =+'材料表 '!$E$178 -> 0 | I93: =H93*I92 -> 0 | J93: 元 | L93: 阳极氧化铝型材T5 | M93: 铝合金副框 | N93: 0.507 | O93: =O92*2 -> 7.2 | P93: =P92 -> 1.5 | Q93: =+P93*O93*N93 -> 5.4756 | R93: =+Q93/R89 -> 1.2246377
B94: 6 | C94: 现场管理费 | D94: （4）*b% | H94: =+'材料表 '!$E$179 -> 0 | I94: =H94*I92 -> 0 | J94: 元 | L94: 阳极氧化铝型材T6 | M94: 铝合金压块 | N94: 0.499 | O94: =P89/0.3*0.05 -> 0.6 | P94: =P92 -> 1.5 | Q94: =+P94*O94*N94 -> 0.4491 | R94: =+Q94/R89 -> 0.10044283
B95: 7 | C95: 税金 | D95: [(4)+(5)+(6)]*c% | H95: =+'材料表 '!$E$180 -> 0.09 | I95: =(I92+I93+I94)*H95 -> 137.24705 | J95: 元 | L95: 阳极氧化铝型材T6 | M95: 立柱插芯 | N95: =2.9 -> 2.9 | O95: 0.2 | P95: =P92 -> 1.5 | Q95: =+P95*O95*N95 -> 0.87 | R95: =+Q95/R89 -> 0.19457864
A96: 首层座槽式玻璃幕墙（12Low-E(双银)+12A+12全超白钢化中空玻璃）（直+弯弧）（直段宽度300㎜+弧长942㎜，圆弧半径600㎜，高3600㎜） | B96: 8 | C96: 综合单价 | D96: （4）-（7）之和 | I96: =SUM(I92:I95) -> 1662.2142 | J96: 元/m² | L96: 阳极氧化铝型材T6 | P96: 1 | Q96: =+P96*O96*N96 -> 0 | R96: =+Q96/R89 -> 0
B97: 其中 | L97: 光身料铝型材T5 | P97: 1 | Q97: =+P97*O97*N97 -> 0 | R97: =+Q97/R89 -> 0
B98: 1 | C98: 人工费 | D98: 名称 | E98: 单位 | H98: 数量 | I98: 单价 | J98: 金额（元） | L98: 粉末喷涂铝型材T5 | P98: 1 | Q98: =+P98*O98*N98 -> 0 | R98: =+Q98/R89 -> 0
B99: 2 | D99: 座槽式玻璃幕墙 | E99: ㎡ | H99: 1 | I99: =+辅材及安装费!$G$17 -> 190 | J99: =H99*I99 -> 190 | L99: 粉末喷涂铝型材T6 | P99: 1 | Q99: =+P99*O99*N99 -> 0 | R99: =+Q99/R89 -> 0
B100: 3 | P100: 1 | Q100: =+P100*O100*N100 -> 0 | R100: =+Q100/R89 -> 0
...

Sheet 工程量计算式（商业）
A1: 名称 | B1: 位置 | C1: 单位 | D1: 计算式 | E1: 面积 | F1: 备注
A2: 玻璃幕墙 | E2: =SUM(E3:E56) -> 1528.5488
A3: 首层座槽式玻璃幕墙（15+2.25SGP+15㎜全超白钢化夹层玻璃）（超宽） | B3: 1#楼南立面2/01~1/01轴 | C3: ㎡ | D3: 7.2*3.6 | E3: {=+EVALUATE(D3)} -> 25.92 | F3: 1#
A4: 首层座槽式玻璃幕墙（12Low-E(双银)+12A+12全超白钢化中空玻璃） | B4: 1#楼南立面1~2轴 | C4: ㎡ | D4: （1.85+1.2）*3.6 | E4: {=+EVALUATE(D4)} -> 10.98 | F4: 1#
A5: 首层座槽式玻璃幕墙（12Low-E(双银)+12A+12全超白钢化中空玻璃）（直+弯弧）（直段宽度300㎜+弧长942㎜，圆弧半径600㎜，高3600㎜） | B5: 1#楼南立面2/01~1/01轴 | C5: ㎡ | D5: （0.942+0.3）*2*3.6 | E5: {=+EVALUATE(D5)} -> 8.9424 | F5: 1#
A6: 首层座槽式玻璃幕墙（12+1.9SGP+12㎜全超白钢化夹层玻璃） | B6: 1#楼南立面2~22轴 | C6: ㎡ | D6: （1.4*2+30.8+3.9+0.22+1.05*2+5.8）*3.6 | E6: {=+EVALUATE(D6)} -> 164.232 | F6: 1#
A7: 首层座槽式玻璃幕墙（12+1.9SGP+12㎜全超白钢化夹层玻璃）（弯弧）（弧长1414㎜，圆弧半径900㎜，高3600㎜） | B7: 1#楼南立面2~22轴 | C7: ㎡ | D7: （1.414*4）*3.6 | E7: {=+EVALUATE(D7)} -> 20.3616 | F7: 1#
A8: 二层T型钢龙骨玻璃幕墙（8+1.52PVB+8㎜全超白钢化夹层玻璃） | B8: 1#南立面2/01~22轴 | C8: ㎡ | D8: （7.2+1.65+0.985）*3.035+（2.785+30.8+3.9+3.58+5.785）*3.035 | E8: {=+EVALUATE(D8)} -> 172.03897 | F8: 1#
A9: 二层T型钢龙骨玻璃幕墙（8+1.52PVB+8㎜全超白钢化夹层玻璃）（直+弯弧）（直段宽度300㎜+弧长942㎜，圆弧半径600㎜，高3035㎜） | B9: 1#南立面2/01~22轴 | C9: ㎡ | D9: （0.942+0.3）*2*3.035 | E9: {=+EVALUATE(D9)} -> 7.53894 | F9: 1#
A10: 二层T型钢龙骨玻璃幕墙（8+1.52PVB+8㎜全超白钢化夹层玻璃）（弯弧）（弧长1414㎜，圆弧半径900㎜，高3035㎜） | B10: 1#南立面2/01~22轴 | C10: ㎡ | D10: （1.414*4）*2*3.035 | E10: {=+EVALUATE(D10)} -> 34.33192 | F10: 1#
A11: 首层明框玻璃幕墙（10Low-E(双银)+12A+10㎜全超白钢化中空玻璃） | B11: 1#北立面24~4轴，24~15轴二层 | C11: ㎡ | D11: （18.5+1.9-1.8*4-2.48）*2.5 | E11: {=+EVALUATE(D11)} -> 26.8 | F11: 1#
A12: 首层明框玻璃幕墙（10Low-E(双银)+12A+10㎜全超白钢化中空玻璃）（直+弯弧+直）（直段宽度210㎜+弧长1414㎜+直段宽度210㎜，圆弧半径900㎜，高2500㎜） | B12: 1#北立面24~4轴 | C12: ㎡ | D12: （0.21+1.414+0.21）*2.5*5 | E12: {=+EVALUATE(D12)} -> 22.925 | F12: 1#
A13: 首层明框玻璃幕墙（15Low-E(双银)+12A+15㎜全超白钢化中空玻璃） | B13: 北立面24~3/01轴 | C13: ㎡ | D13: （3.103*2）*2.5 | E13: {=+EVALUATE(D13)} -> 15.515 | F13: 1#
A14: 首层明框玻璃幕墙（8+1.52PVB+8Low-E(双银)+12A+8+1.52PVB+8㎜全超白钢化夹层中空玻璃）（超高）（宽2175㎜，高6800㎜） | B14: 北立面4~2轴 | C14: ㎡ | D14: 2.175*6.8 | E14: {=+EVALUATE(D14)} -> 14.79 | F14: 1#
... A55: 二层明框玻璃幕墙（10Low-E(双银)+12A+10㎜全超白钢化中空玻璃） | B55: 2#北立面18~2/01轴,3剖 | C55: ㎡ | D55: （1.85+15.08+1.09*2+4.49+6.3+2.7）*2.345 | E55: {=+EVALUATE(D55)} -> 76.447 | F55: 2#
A56: 二层明框玻璃幕墙（10Low-E(双银)+12A+10㎜全超白钢化中空玻璃）（直+弯弧+直）（直段宽度210㎜+弧长1414㎜+直段宽度210㎜，圆弧半径900㎜，高2345㎜） | B56: 2#北立面18~2/01轴,3剖 | C56: ㎡ | D56: （0.21*2+1.414）*2.345*4+（0.21*2+1.095）*2.345 | E56: {=+EVALUATE(D56)} -> 20.755595 | F56: 2# | H56: =E56+E50 -> 23.029755
A57: 玻璃栏板
A58: 6+1.14PVB+6㎜超白钢化夹层玻璃栏杆 | B58: 1#楼 | C58: m | D58: 26.549-（0.27+0.754）*2 | E58: {=+EVALUATE(D58)} -> 24.501 | F58: 1#
A59: 6+1.14PVB+6㎜超白钢化夹层玻璃栏杆（弧形） | B59: 1#楼 | C59: m | D59: （0.27+0.754）*2 | E59: {=+EVALUATE(D59)} -> 2.048 | F59: 1#
A60: 6+1.14PVB+6㎜超白钢化夹层玻璃栏杆 | B60: 2#楼 | C60: m | D60: 66.281-（0.46+0.754+0.44+0.754）-（0.44+0.754+0.41+0.754）-（0.19+0.754+0.19+0.754） | E60: {=+EVALUATE(D60)} -> 59.627 | F60: 2#
A61: 6+1.14PVB+6㎜超白钢化夹层玻璃栏杆（弧形） | B61: 2#楼 | C61: m | D61: （0.46+0.754+0.44+0.754）+（0.44+0.754+0.41+0.754）+（0.19+0.754+0.19+0.754） | E61: {=+EVALUATE(D61)} -> 6.654 | F61: 2#
A63: 地弹门 | E63: =SUM(E64:E70) -> 138.492
A64: 地弹门（6Low-E(双银)+12A+6㎜全超白钢化中空玻璃） | B64: 1#楼南立面 | C64: ㎡ | D64: 1.8*3.6 | E64: {=+EVALUATE(D64)} -> 6.48 | F64: 1#
A65: 地弹门（6Low-E(双银)+12A+6㎜全超白钢化中空玻璃） | B65: 1#楼北立面 | C65: ㎡ | D65: 1.8*2.5*9 | E65: {=+EVALUATE(D65)} -> 40.5 | F65: 1#
A66: 地弹门（6Low-E(双银)+12A+6㎜全超白钢化中空玻璃） | B66: 2#楼南立面 | C66: ㎡ | D66: 0.9*3.6*2 | E66: {=+EVALUATE(D66)} -> 6.48 | F66: 2#
A67: 地弹门（6Low-E(双银)+12A+6㎜全超白钢化中空玻璃） | B67: 2#楼南立面 | C67: ㎡ | D67: 1.75*3.6+1.75*3.6+1.8*3.6 | E67: {=+EVALUATE(D67)} -> 19.08 | F67: 2#
A68: 地弹门（6Low-E(双银)+12A+6㎜全超白钢化中空玻璃） | B68: 2#楼北立面 | C68: ㎡ | D68: 1.8*2.5*8 | E68: {=+EVALUATE(D68)} -> 36 | F68: 2#
A69: 地弹门（6Low-E(双银)+12A+6㎜全超白钢化中空玻璃） | B69: 2#楼北立面二层 | C69: ㎡ | D69: 1.8*2.33+1.8*2.345*4 | E69: {=+EVALUATE(D69)} -> 21.078 | F69: 2#
A70: 地弹门（6Low-E(双银)+12A+6㎜全超白钢化中空玻璃） | B70: 2#楼东立面 | C70: ㎡ | D70: 1.7*2.8+1.7*2.42 | E70: {=+EVALUATE(D70)} -> 8.874 | F70: 2#
C71: ㎡
A72: 金属幕墙 | C72: ㎡ | E72: =SUM(E73:E76) -> 431.63129
A73: 二层金属网 | B73: 1#楼南立面2/01~22轴 | C73: ㎡ | D73: （11.849+0.95-1.21*2）*3.043+（42.512+3.5+7.471-1.681*4）*3.043 | E73: {=+EVALUATE(D73)} -> 173.87093 | F73: 1#
A74: 二层金属网（圆弧） | B74: 1#楼南立面2/01~22轴 | C74: ㎡ | D74: （1.21*2）*3.043+（1.681*4）*3.043 | E74: {=+EVALUATE(D74)} -> 27.825192 | F74: 1#
A75: 二层金属网 | B75: 2#楼南立面5/01~23轴，9剖 | C75: ㎡ | D75: （6.05+5.4+6.05+3.835+0.84+8.7+1.65+3.42+1.65+8.7+0.84+0.4+3.45+13.55+0.55）*3.043 | E75: {=+EVALUATE(D75)} -> 198.05365 | F75: 2#
A76: 二层金属网（圆弧） | B76: 2#楼南立面5/01~23轴，9剖 | C76: ㎡ | D76: （1.414*2+1.135+1.498+1.135+1.681+1.1*2）*3.043 | E76: {=+EVALUATE(D76)} -> 31.881511 | F76: 2#
C78: ㎡ | E78: =SUM(E79:E119) -> 4585.9053
A79: 中灰色仿石材铝单板 | B79: 1#楼北立面 | C79: ㎡ | D79: （18.5+1.9-2.48）*0.535+（11.605）*0.935 | E79: {=+EVALUATE(D79)} -> 20.437875 | F79: 1#
A80: 中灰色仿石材铝单板（弧形） | B80: 1#楼北立面 | C80: ㎡ | D80: （0.21*2+1.414）*0.535+（0.21*2+1.414）*0.935*2 | E80: {=+EVALUATE(D80)} -> 4.41077 | F80: 1#
A81: 香槟色瓦楞板 | B81: 1#楼北立面，JD-202/203 | C81: ㎡ | D81: (11.4+1.85+2.88+1.5)*0.64+（11.605+1.4）*0.27 | E81: {=+EVALUATE(D81)} -> 14.79455 | F81: 1#
A82: 香槟色瓦楞板（弧形） | B82: 1#楼北立面 | C82: ㎡ | D82: （0.21*2+1.414）*0.64*3+(0.21*2+1.414)*0.27*2 | E82: {=+EVALUATE(D82)} -> 4.51164 | F82: 1#
A83: 银灰色铝合金瓦楞板（异形） | B83: 1#楼北立面，JD-205 | C83: ㎡ | D83: （11.4+1.85+2.88）*0.25+（11.605）*0.25+10.53*0.25 | E83: {=+EVALUATE(D83)} -> 9.56625 | F83: 1#
A84: 银灰色铝合金瓦楞板（异形）（弧形） | B84: 1#楼北立面，JD-205 | C84: ㎡ | D84: （0.21*2+1.414）*0.25+（0.21*2+1.414）*0.25*4+（0.21*2+0.942）*0.25*2 | E84: {=+EVALUATE(D84)} -> 2.9735 | F84: 1#
A85: 中灰色铝单板 | B85: 1#楼北立面15~14轴 | C85: ㎡ | D85: 1.5*0.7 | E85: {=+EVALUATE(D85)} -> 1.05 | F85: 1#
A86: 吊顶：25㎜香槟色蜂窝铝板 | B86: 1#楼 | C86: ㎡ | D86: 182.686+50.2*0.1+61.877*0.1 | E86: {=+EVALUATE(D86)} -> 193.8937 | F86: 1#
A87: 吊顶：香槟色铝板 | B87: 1#楼 | C87: ㎡ | D87: 187.79+（44.896+9.718+133.309-51）+51.194*0.1 | E87: {=+EVALUATE(D87)} -> 329.8324 | F87: 1#
A88: 雨蓬上表面：银灰色铝板 | B88: 1#楼，JD-211 | C88: ㎡ | D88: 50.2*2.956+51.194*2.956+61.877*2.956 | E88: {=+EVALUATE(D88)} -> 482.62908 | F88: 1#
A89: 银灰色铝单板 | B89: 1#楼北立面24轴造型柱，JD-235 | C89: ㎡ | D89: 3.766*6.85 | E89: {=+EVALUATE(D89)} -> 25.7971 | F89: 1#
A90: 银灰色铝单板 | B90: 1#楼北立面3/01轴造型柱 | C90: ㎡ | D90: 3.68*6.85 | E90: {=+EVALUATE(D90)} -> 25.208 | F90: 1#
... A119: 3㎜浅灰色穿孔铝板 | B119: 不锈钢天沟上盖板 | C119: ㎡ | D119: 0.313*（34.7+138.182+48.617+6.605） | E119: {=+EVALUATE(D119)} -> 71.396552 | F119: 2#
A120: 石材幕墙 | E120: =SUM(E121:E149) -> 817.91032
A121: 30mm厚光面贝金米黄石材 | B121: 1#楼南立面2轴交A轴位置石材造型柱 | C121: ㎡ | D121: 2.292*6.61 | E121: {=+EVALUATE(D121)} -> 15.15012 | F121: 1#
A122: 30mm厚光面贝金米黄石材 | B122: 1#楼南立面22轴至24轴交C轴 | C122: ㎡ | D122: 6.8*9.3 | E122: {=+EVALUATE(D122)} -> 63.24 | F122: 1#
A123: 40mm厚自然面贝金米黄石材 | B123: 1#楼南立面22轴至24轴交C轴 | C123: ㎡ | D123: 2.4*1.02+0.92*2.62+1.1*3 | E123: {=+EVALUATE(D123)} -> 8.1584 | F123: 1#
A124: 40mm厚拉槽面贝金米黄石材 | B124: 1#楼南立面22轴至24轴，下沉庭院 | C124: ㎡ | D124: (5.4+4.48+8.6+5.8)*(2.6+0.7+0.07) | E124: {=+EVALUATE(D124)} -> 81.8236 | F124: 1#
A125: 贝金米黄石材拉槽线条1 | B125: 1#楼南立面22轴至24轴，下沉庭院上部线条 | C125: m | D125: 5.4+4.48+8.6+5.8 | E125: {=+EVALUATE(D125)} -> 24.28 | F125: 1#
A126: 贝金米黄石材拉槽线条2 | B126: 1#楼南立面22轴至24轴，下沉庭院下部弧形线条 | C126: m | D126: 5.4+4.48+8.6+5.8 | E126: {=+EVALUATE(D126)} -> 24.28 | F126: 1#
A127: 30mm厚光面贝金米黄石材 | B127: 1#楼北立面4轴至2轴交G轴 | C127: ㎡ | D127: 4.379*6.8*2 | E127: {=+EVALUATE(D127)} -> 59.5544 | F127: 1#
A128: 30mm厚光面贝金米黄石材 | B128: 1#楼北立面21轴至18轴交J轴 | C128: m | D128: 2.108*3*2 | E128: {=+EVALUATE(D128)} -> 12.648 | F128: 1#
A129: 30mm厚光面贝金米黄石材 | B129: 1#楼北立面3/01轴右侧柱中石材 | C129: m | D129: 2.347+2.308*2 | E129: {=+EVALUATE(D129)} -> 6.963 | F129: 1#
A130: 30mm厚光面深灰色石材 | B130: 1#楼北立面2/01轴至3/01轴 | C130: ㎡ | D130: 0.81*6.8 | E130: {=+EVALUATE(D130)} -> 5.508 | F130: 1#
A131: 30mm厚光面深灰色石材 | B131: 1#楼北立面15轴二层 | C131: ㎡ | D131: 0.75*3.1 | E131: {=+EVALUATE(D131)} -> 2.325 | F131: 1#
A132: 30mm厚光面福鼎黑石材（造型柱基座） | B132: 1#楼北立面3/01轴至4/01轴中间 | C132: ㎡ | D132: （1.1+2.4）*2*0.9 | E132: {=+EVALUATE(D132)} -> 6.3 | F132: 1#
... A138: 贝金米黄石材拉槽线条2 | B138: 2#楼南立面4/01轴至2轴，下沉庭院下部弧形线条 | C138: m | D138: 5.4+4.48+8.6+5.8 | E138: {=+EVALUATE(D138)} -> 24.28 | F138: 2#
A139: 30mm厚光面贝金米黄石材 | B139: 2#楼北立面23轴 | C139: ㎡ | D139: 7.29 | E139: {=+EVALUATE(D139)} -> 7.29 | F139: 2#
A140: 30mm厚光面贝金米黄石材 | B140: 2#楼北立面1/17轴至15轴 | C140: ㎡ | D140: =(0.514+2.083)*3 -> 7.791 | E140: {=+EVALUATE(D140)} -> 7.791 | F140: 2#
A141: 30mm厚光面贝金米黄石材 | B141: 2#楼北立面4轴至2轴 | C141: ㎡ | D141: 1.878*3*2 | E141: {=+EVALUATE(D141)} -> 11.268 | F141: 2#
A142: 30mm厚光面贝金米黄石材 | B142: 2#楼北立面1轴 | C142: ㎡ | D142: 4.908*3 | E142: {=+EVALUATE(D142)} -> 14.724 | F142: 2#
A143: 30mm厚光面贝金米黄石材 | B143: 2#楼北立面5/01轴左侧造型柱 | C143: ㎡ | D143: 2.347+2.308*2 | E143: {=+EVALUATE(D143)} -> 6.963 | F143: 2#
A144: 30mm厚光面贝金米黄石材 | B144: 2#楼北立面5/01轴至4/01轴交B轴至F轴内庭 | C144: ㎡ | D144: 28.952+62.141+14.056 | E144: {=+EVALUATE(D144)} -> 105.149 | F144: 2#
A145: 30mm厚光面贝金米黄石材 | B145: 2#楼北立面5/01轴至4/01轴交B轴至F轴内庭 | C145: ㎡ | D145: 12.61*2 | E145: {=+EVALUATE(D145)} -> 25.22 | F145: 2#
A146: 40mm厚自然面贝金米黄石材 | B146: 2#楼北立面5/01轴至4/01轴交B轴至F轴内庭 | C146: ㎡ | D146: 2.08+2.28+2.09 | E146: {=+EVALUATE(D146)} -> 6.45 | F146: 2#
A147: 40mm厚拉槽面贝金米黄石材 | B147: 2#楼北立面5/01轴至4/01轴交B轴至F轴内庭 | C147: ㎡ | D147: 9.318+3.07 | E147: {=+EVALUATE(D147)} -> 12.388 | F147: 2#
A148: 30mm厚光面贝金米黄石材（造型柱弧形） | B148: 2#楼南立面1/01轴右侧柱子 | C148: ㎡ | D148: 3.912*6.6*2 | E148: {=+EVALUATE(D148)-E149} -> 30.828 | F148: 2#
A149: 30mm厚透光云石（造型柱弧形） | B149: 2#楼南立面1/01轴右侧柱子 | C149: ㎡ | D149: 1.131*4*4.6 | E149: {=+EVALUATE(D149)} -> 20.8104 | F149: 2#
A154: 铝合金格栅百叶 | C154: m | E154: =SUM(E155:E158) -> 140.296
A155: 铝合金格栅 | B155: 1#楼北立面 | C155: ㎡ | D155: 1.5*（3+3.1）+1.5*（3+3.1） | E155: {=+EVALUATE(D155)} -> 18.3 | F155: 1#
A156: 铝合金格栅 | B156: 2#楼北立面 | C156: ㎡ | D156: 1.5*（3+3.1）+1.6*3.1 | E156: {=+EVALUATE(D156)} -> 14.11 | F156: 2#
A157: 铝合金百叶 | B157: 2#楼北立面 | C157: ㎡ | D157: 2.3*2.6+1.4*2.5 | E157: {=+EVALUATE(D157)} -> 9.48 | F157: 2#
A158: 铝合金百叶 | B158: 2#楼东立面 | C158: ㎡ | D158: 4.6*6.3+11.02*6.3 | E158: {=+EVALUATE(D158)} -> 98.406 | F158: 2#
A164: 铝合金线条 | E164: =SUM(E165:E175) -> 6195.201
A165: 香槟色格栅线条（40*50） | B165: 1#楼北立面 | C165: m | D165: 4.42*511 | E165: {=+EVALUATE(D165)} -> 2258.62 | F165: 1#
A166: 香槟色铝合金线条（169*100） | B166: 1#楼北立面雨棚灯槽 | C166: m | D166: 50.2+51.194+61.877 | E166: {=+EVALUATE(D166)} -> 163.271 | F166: 1#
A167: 铝合金线条（80*160） | B167: 1#楼造型柱上，JD-235 | C167: m | D167: 6.9*4 | E167: {=+EVALUATE(D167)} -> 27.6 | F167: 1#
A168: 浅灰色铝合金线条（200*50） | B168: 1#楼北立面 | C168: m | D168: 114.395 | E168: {=+EVALUATE(D168)} -> 114.395 | F168: 1#
A169: 浅灰色铝合金线条（200*50） | B169: 1#楼南立面 | C169: m | D169: 68.777 | E169: {=+EVALUATE(D169)} -> 68.777 | F169: 1#
A170: 香槟色铝合金线条（169*100） | B170: 1#楼南立面2/01造型柱 | C170: m | D170: 15.314*2 | E170: {=+EVALUATE(D170)} -> 30.628 | F170: 1#
A171: 银灰色铝合金线条（120*30） | B171: 1#楼北立面 | C171: m | D171: (11.4+(0.21*2+1.414)*1)+1.5*2+(2.8+(0.21*2+1.414)*2)+(11.605+1.4+(0.21*2+1.414)*2) | E171: {=+EVALUATE(D171)} -> 39.375 | F171: 1#
A172: 香槟色铝合金线条（169*100） | B172: 2#楼南立面23轴柱 | C172: m | D172: 7.8 | E172: {=+EVALUATE(D172)} -> 7.8 | F172: 2#
A173: 浅灰色铝合金线条（200*50） | B173: 2#楼南立面 | C173: m | D173: 170.773 | E173: {=+EVALUATE(D173)} -> 170.773 | F173: 2#
A174: 香槟色铝合金线条（169*100） | B174: 2#楼北立面雨棚灯槽 | C174: m | D174: 67.62+72.342 | E174: {=+EVALUATE(D174)} -> 139.962 | F174: 2#
A175: 香槟色格栅线条（40*50） | B175: 2#楼 | C175: m | D175: 4.6*690 | E175: {=+EVALUATE(D175)} -> 3174 | F175: 2#
A176: 银灰色铝合金线条（120*30） | B176: 2#楼 | C176: m | D176: (12.18+5.6+(0.21*2+1.414)*0)+(1.85+15.08+1.8*2+(0.21*2+1.414)*2)+(3.98+4.49+0.21*2+1.414)+(6.3+2.7+1.8+(0.21*2+1.414)*2) | E176: {=+EVALUATE(D176)} -> 66.75 | F176: 2#
A179: 不锈钢天沟 | B179: 1#楼 | C179: m | D179: 103.686+29.83+73.354+7.545+22.294+8.875+（2.501+8.01+3.4+3.405） | E179: {=+EVALUATE(D179)} -> 262.9 | F179: 1#
A180: 不锈钢天沟 | B180: 2#楼 | C180: m | D180: 34.7+138.182+48.617+6.605 | E180: {=+EVALUATE(D180)} -> 228.104 | F180: 2#
C181: m | E181: {=+EVALUATE(D181)} -> #VALUE!
A182: 防火隔断 | B182: 1#楼 | C182: m | D182: 228*3 | E182: {=+EVALUATE(D182)} -> 684
A183: 防火隔断 | B183: 2#楼 | C183: m | D183: 228*3 | E183: {=+EVALUATE(D183)} -> 684
C184: ㎡ | E184: {=+EVALUATE(D184)} -> #VALUE!
A185: 1.5㎜镀锌钢板封堵 | B185: 1#楼 | C185: m | D185: 50*0.5 | E185: {=+EVALUATE(D185)} -> 25
A186: 1.5㎜镀锌钢板封堵 | B186: 2#楼 | C186: m | D186: 50*0.5 | E186: {=+EVALUATE(D186)} -> 25
...
